Workbook
Name t_973431DD2C61366DBACC56E61E132E05: 'Dropdown Lists'!$C$1:$S$1
Name t_CE9696B61FAB33F2B7AC38BD1A6904FE: 'Dropdown Lists'!$C$2:$D$2
Name t_E596E04876A938D89430E31F12190EAE: 'Dropdown Lists'!$C$3:$D$3
Name t_210AC56516C831C3B975426026564B85: 'Dropdown Lists'!$C$4:$H$4
Name t_5DB35C4529DB3F96BF4F53E1FEC22A97: 'Dropdown Lists'!$C$5:$G$5
Name t_5A2E371F897639048DDE5DABAB9B152C: 'Dropdown Lists'!$C$6:$P$6
Name t_6CC11CB0854138C9A2CAB6DC90AACA9A: 'Dropdown Lists'!$C$7:$L$7
Name t_4BDCEE54E14C361091E3B7E7BC6BFA58: 'Dropdown Lists'!$C$8:$F$8
Name t_4E8EB62C344D3136894C37789B634AC8: 'Dropdown Lists'!$C$9:$K$9
Name t_B0B8A13405AC332B85C28D653BD74B34: 'Dropdown Lists'!$C$10:$H$10
Name t_BA7DD3CAEAAF3F6C820F178068C1218E: 'Dropdown Lists'!$C$11:$S$11
Name t_4D36BB0BF9A633DDA10597E97D2DE70D: 'Dropdown Lists'!$C$12:$G$12
Name t_B8ED491BA39F3348BAC02EDEAF8D3E6A: 'Dropdown Lists'!$C$13:$K$13
Name t_82B46A7862C13CCC82AB8265B43CD5D1: 'Dropdown Lists'!$C$14:$V$14
Name t_102B0F8B23393DE98AFB27DE3D742D48: 'Dropdown Lists'!$C$15:$F$15
Name t_59D4DF059C473EBE9972B0D6D3C6BFD5: 'Dropdown Lists'!$C$16:$E$16
Name t_BCE822F8514631DFAA900D604C1FA3AD: 'Dropdown Lists'!$C$17:$C$17
Name t_4E2BBC766FB4340DA4F274AC6BC0E42A: 'Dropdown Lists'!$C$18:$C$18
Name t_FC32CA4BE4523AFA87DDD9FFB97F7808: 'Dropdown Lists'!$C$19:$H$19
Name t_C085911E85C936C6BD19084938DB0495: 'Dropdown Lists'!$C$20:$T$20
Name t_94660DF92DF63DDEA8BF802328086FC7: 'Dropdown Lists'!$C$21:$T$21
Name t_73E6512CB46F348A83947FB39BCF752F: 'Dropdown Lists'!$C$22:$T$22
Name t_C8870444BCC03E0F81602AC536FFB503: 'Dropdown Lists'!$C$23:$Y$23
Name t_F76924BDB46A359E806CC3D9D6088934: 'Dropdown Lists'!$C$24:$AL$24
Name t_26E3C87B829339BE8536D2D39B5C0888: 'Dropdown Lists'!$C$25:$AA$25
Name t_7EF3CCB8B63637A7A601CBF4D95C11D1: 'Dropdown Lists'!$C$26:$Y$26
Name t_AB465CBD00B53EAB84E00C94A08B5DEA: 'Dropdown Lists'!$C$27:$AL$27
Name t_D3C5568F8E863690832B5922067B68BD: 'Dropdown Lists'!$C$28:$AM$28
Name t_CFCAAD4DFABC30AEAFB900B42A679B7C: 'Dropdown Lists'!$C$29:$Z$29
Name t_DB9F6C5F247E3B5BBFF538B0768DAB78: 'Dropdown Lists'!$C$30:$Y$30
Name t_AA8D9890C22B3144A1B285F31A98A592: 'Dropdown Lists'!$C$31:$AI$31
Name t_1F78D7F4F84730749F0793B28E15DC40: 'Dropdown Lists'!$C$32:$T$32
Name t_164E2C004CFD34F692F316843ED05685: 'Dropdown Lists'!$C$33:$AI$33
Name t_2E9EA565169F3AAFA61C54E852739B92: 'Dropdown Lists'!$C$34:$AM$34
Name t_2F1C8F4BA36D3317B8A60F8F04E34E81: 'Dropdown Lists'!$C$35:$Y$35
Name t_F21A47916C653886B5F7633E0C76CC00: 'Dropdown Lists'!$C$36:$E$36
Name t_DA1B0BA69BFB3BF69586BF4ED975D7AD: 'Dropdown Lists'!$C$37:$E$37
Name t_96B6F55C541D3B82B4149970D9A046FE: 'Dropdown Lists'!$C$38:$R$38
Name t_1A68E0AEE23C30F9BFEF78A191852BDE: 'Dropdown Lists'!$C$39:$R$39
Name t_5EDF549B7C5A3BAC9E1416871DC2FDAF: 'Dropdown Lists'!$C$40:$M$40
Name t_F89DD745747D3D5EB9B38DAB834260A9: 'Dropdown Lists'!$C$41:$M$41
Name t_95B334C7F57D3368AD089F0AE00AD0BA: 'Dropdown Lists'!$C$42:$S$42
Name t_8C5BD9C9DBF23D6D8E539580040DA10C: 'Dropdown Lists'!$C$43:$AH$43
Name t_D497537DA1F13695BD79B47E62B33DA2: 'Dropdown Lists'!$C$44:$R$44
Name t_4D79DF73E5C93EEB8A7925BF6E60384D: 'Dropdown Lists'!$C$45:$AC$45
Name t_4CFE4A5C24343316925FE6F113EAF0DA: 'Dropdown Lists'!$C$46:$R$46
Name t_9C9B8F8D92673BCFA86B74DABFA9D856: 'Dropdown Lists'!$C$47:$M$47
Name t_1DBC9E8133AF3C05946B29B34A4C48D0: 'Dropdown Lists'!$C$48:$M$48
Name t_FB0FDA8FA83B38899957AE743B80676D: 'Dropdown Lists'!$C$49:$AI$49
Name t_10AA201A7F9C369D904AC4FDF2E5F638: 'Dropdown Lists'!$C$50:$AC$50
Name t_E6899D1116443FB6936F2B4F5F9BC1AC: 'Dropdown Lists'!$C$51:$AI$51
Name t_4F97159A8B4D3DD0BD09A071FCD98B18: 'Dropdown Lists'!$C$52:$S$52
Name t_53B44E93E11B304895EDFEA6F3AF1904: 'Dropdown Lists'!$C$53:$J$53
Name t_962B956138A734B78A21651BBEA7EFD1: 'Dropdown Lists'!$C$54:$AH$54
Name t_AF5EFC01161B3C7DB5C210293259F858: 'Dropdown Lists'!$C$55:$M$55
Name t_D675724A16653158972AB5FA2AB7D672: 'Dropdown Lists'!$C$56:$M$56
Name t_1A45D7239F783D2199C0A85AA469EA8B: 'Dropdown Lists'!$C$57:$R$57
Name t_14F0E574DE5F33B8841AA0C3A025C18B: 'Dropdown Lists'!$C$58:$R$58
Name t_0840E90374183A469D364E5B1077E4F9: 'Dropdown Lists'!$C$59:$AD$59
Name t_8B8C178010303A41AB4AE679DA70F99B: 'Dropdown Lists'!$C$60:$AN$60

Sheet Instructions
A1: Using your Template
A2: Print this page
A3: On this page, you'll find the necessary details to generate, verify, and submit your template spreadsheet to Temu. For ease of reference throughout the process, we suggest printing out this page.
A4: Save a version of this file on your hard drive in Excel format. Next, input your product information into the Template tab, adhering to the following instructions.
A6: Image Tab
A7: Refer to the Images tab to familiarize yourself with Temu's guidelines for visual content. Ensure that the images you contribute to Temu align with these specified standards to maintain uniformity and excellence.
A8: It's important that an image is supplied for all products. Upload images by providing the image URL.
A10: Example Tab
A11: Check out the Example tab to view a sample of how to input product details. This is provided just for your guidance. Remember, to prevent the incorporation of incorrect product information into your inventory file, you should not edit your own products directly within the Example sheet.
A13: Template Tab
A14: Navigate to the Template tab to populate it with your listing specifics. When you select a Product Type 1. Recommended software: Due to file compatibility considerations, it is recommended to use Office - Excel to use and edit the template file; 2. Template integrity: Do not modify or delete the sheet names, column headers, or their order in the template file. For cells with dropdown enumerations, select and fill in values from the dropdown list. 3. Units of measurement: the units in the template file are related to the publishing site a. The German, Italian, French, Netherlands, Belgium, and Spanish marketplaces all use the metric system: the length unit is centimeters, the weight unit is grams, and the currency unit is EUR i. The length range is 0.1 cm-9,999.9 cm, with a maximum of 1 decimal point, and will be rounded up; ii. The weight range is 0.1 g-9,999,999.9 g, with a maximum of 1 decimal place, and will be rounded up; iii. The price range is €0.01-€99999999.99, with a maximum of 2 decimal places, and will be rounded up. b. The US marketplace uses the imperial system: the length unit is inches, the weight unit is pounds, and the currency unit is USD i. The length range is 0.1 in-999.9 in, with a maximum of 1 decimal point, and will be rounded up; ii. The weight range is 0.01 lb-9999.99 lb, with a maximum of 2 decimal point, and will be rounded up; iii. The price range is $0.01-$99999999.99, with a maximum of 2 decimal points, and will be rounded up. c. Marketplace in UK is metric: the length unit is centimeters, the weight unit is grams, and the currency unit is GBP i. The length range is 0.1 cm-9,999.9 cm, with a maximum of 1 decimal point, and will be rounded up; ii. The weight range is 0.1 g-9,999,999.9 g, with a maximum of 1 decimal place, and will be rounded up; iii. The price range is £0.01-£99999999.99, with a maximum of 2 decimal places, and will be rounded up. 4. Qualifications and photos: Excel does not currently support uploading qualification documents or photos. For products that require these materials, visit Product Compliance to provide them after submission. 5. Mandatory fields: The Excel file includes built-in formulas. When you select a Category, mandatory fields will be indicated with a red border. Ensure all mandatory fields are correctly filled in. While you are not required to fill in optional fields, it is recommended that you provide as much information as possible for better product performance. 6. Quantity limit: In each file, up to 2000 lines of content are allowed, otherwise products will not be able to be added to the file. 7. Duplicate columns: The Excel file is collapsed by default. You can click on 1 and 2 at the top of the Excel file.
A17: Submit the spreadsheet
... A23: From time to time, Temu will update valid values, data validation rules, explanatory text, and requirements. Please use the latest generated template files.

Sheet Images
A1: Image Standards
A3: Every product on Temu needs one or more product images. Choose images that are clear, straightforward, and easy to understand. They must accurately represent the product and be information-rich and attractively presented. Show only the product that is being offered for sale. Whenever possible, provide several images, with each one showing different angles and details of the product. This is your opportunity to show your product to your customer, so quality matters.
A4: We reserve the right to reject images that do not meet our image standards.
A5: It is your responsibility to ensure that you have all necessary rights to the images you submit.
A7: SKU images
A9: The SKU images will be displayed at the top of the product page. Different SKU images will form a carousel of the product.
A10: For apparel products, the images you upload should be with a maximum size of 3MB, an aspect ratio of 3:4, width ≥ 1340px, height ≥ 1785px. The SKUs with the same color will share a set of carousel images.
A11: For non-apparel products, the images you upload should be with a maximum size of 3MB, an aspect ratio of 1:1, and width and height ≥ 800px.
A12: You can upload up to ten images, with each cell containing one image URL.
A14: Product video
A16: The product video will be displayed at the top of the product page.
A17: The video you upload should be with a maximum size of 100MB, a length not exceeding 180 seconds, and a minimum resolution of 720P.
... A28: Upload the video with a maximum size of 300MB, a length not exceeding 180 seconds, an aspect ratio of either 1:1, 4:3, or 16:9, and a minimum resolution of 720P.

Sheet Example
A1: 1. Besides reviewing the contents of the Example tab, kindly peruse the Instructions tab provided in this document.
A2: 2. Be aware that the examples provided serve merely as illustrations. The columns appearing in your tailored template will vary according to the selected Category. Utilize the Template tab to generate the template spreadsheet.
A3: 3. Some of the optional columns are collapsed for the purpose of better representation. Please show those collapsed areas by clicking '+' button on the corresponding column or section
A4: 4. Errors when you submit a product entry can be resolved by viewing the Processing results, or by contacting Seller Support.
A5: Some fields are Required. Other are Optional. | B5: Product Identity | H5: Product Description | BN5: Product Detail | GT5: Sale Property (At Least One, At Most Two) | HL5: Size Chart | IE5: Variations | IY5: Offer | JC5: Qualifications
B6: Category | C6: Product Name | D6: Contribution Goods | E6: Contribution SKU | F6: Brand | G6: Trademark | H6: Product Description | I6: Bullet Point | J6: Bullet Point | K6: Bullet Point | L6: Bullet Point | M6: Bullet Point | N6: Bullet Point | O6: Detail Images URL | P6: Detail Images URL | Q6: Detail Images URL | R6: Detail Images URL | S6: Detail Images URL | T6: Detail Images URL | U6: Detail Images URL | V6: Detail Images URL | W6: Detail Images URL | X6: Detail Images URL | Y6: Detail Images URL | Z6: Detail Images URL | AA6: Detail Images URL | AB6: Detail Images URL | AC6: Detail Images URL | AD6: Detail Images URL | AE6: Detail Images URL | AF6: Detail Images URL | AG6: Detail Images URL | AH6: Detail Images URL | AI6: Detail Images URL | AJ6: Detail Images URL | AK6: Detail Images URL | AL6: Detail Images URL | AM6: Detail Images URL | AN6: Detail Images URL | AO6: Detail Images URL | AP6: Detail Images URL | AQ6: Detail Images URL | AR6: Detail Images URL | AS6: Detail Images URL | AT6: Detail Images URL | AU6: Detail Images URL | AV6: Detail Images URL | AW6: Detail Images URL | AX6: Detail Images URL | AY6: Detail Images URL | AZ6: Detail Images URL | BA6: Detail Images URL | BB6: Detail Images URL | BC6: Detail Images URL | BD6: Detail Images URL | BE6: Detail Images URL | BF6: Detail Images URL | BG6: Detail Images URL | BH6: Detail Images URL | BI6: Detail Images URL | BJ6: Detail Images URL | BK6: Detail Images URL | BL6: Detail Images URL | BM6: Detail Video URL | BN6: 4115 - Shelf Life - value | BO6: 4115 - Shelf Life - unit | BP6: 4118 - Speciality | BQ6: 4118 - Speciality | BR6: 4118 - Speciality | BS6: 4119 - Item Weight - value | BT6: 4119 - Item Weight - unit | BU6: 4120 - Package Weight - value | BV6: 4120 - Package Weight - unit | BW6: 4121 - Allergen Information | BX6: 4121 - Allergen Information | BY6: 4121 - Allergen Information | BZ6: 4121 - Allergen Information | CA6: 4121 - Allergen Information | CB6: 4121 - Allergen Information | CC6: 4121 - Allergen Information | CD6: 4121 - Allergen Information | CE6: 4121 - Allergen Information | CF6: 4121 - Allergen Information | CG6: 195 - Diet Type | CH6: 195 - Diet Type | CI6: 195 - Diet Type | CJ6: 6160 - Brand Name | CK6: 6210 - USDA certified | CL6: 4110 - Production Date | CM6: 6440 - best before | CN6: 361 - Package Quantity | CO6: 12 - Material | CP6: 12 - Material | CQ6: 12 - Material | CR6: 12 - Material | CS6: 12 - Material | CT6: 4134 - Publisher | CU6: 4130 - Country/Region Of Origin | CV6: 4137 - Author | CW6: 1120 - Set or not | CX6: 4133 - Binding Type | CY6: 4123 - Languages | CZ6: 4123 - Languages | DA6: 4123 - Languages | DB6: 4142 - Year Of Publication | DC6: 4124 - Number Of Pages (pages) - value | DD6: 4124 - Number Of Pages (pages) - unit | DE6: 4131 - Number Of Words (10,000 Words) | DF6: 4127 - Product Weight (g) - value | DG6: 4127 - Product Weight (g) - unit | DH6: 4128 - Maximum Reading Age (years) - value | DI6: 4128 - Maximum Reading Age (years) - unit | DJ6: 4129 - Minimum Reading Age (years) - value | DK6: 4129 - Minimum Reading Age (years) - unit | DL6: 121 - Material | DM6: 121 - Material | DN6: 121 - Material | DO6: 121 - Material | DP6: 121 - Material | DQ6: 132 - Finish Type | DR6: 210 - Furniture Finish | DS6: 19 - Style | DT6: 1561 - Power Supply | DU6: 1132 - Operating Voltage | DV6: 1485 - Plug Type | DW6: 1485 - Plug Type | DX6: 1485 - Plug Type | DY6: 1571 - Acceptable Voltage Range | DZ6: 4102 - Contain Wooden Materials | EA6: 4097 - Tree Species | EB6: 4097 - Tree Species | EC6: 4098 - Wood Formation Type | ED6: 4098 - Wood Formation Type | EE6: 4098 - Wood Formation Type | EF6: 4099 - Fiberboard Density | EG6: 6171 - Wether Independent | EH6: 6172 - Closed Storage Capacity | EI6: 6173 - Height After Assembly | EJ6: 6174 - Physical Weight | EK6: 2153 - Battery Properties | EL6: 2147 - Rechargeable Battery | EM6: 2154 - Solar Battery Type | EN6: 3740 - Non-rechargeable Battery | EO6: 2028 - Battery Capacity (mAh) - value | EP6: 2028 - Battery Capacity (mAh) - unit | EQ6: 63 - Color | ER6: 15 - Composition:Nylon | ES6: 15 - Composition:Polyester | ET6: 15 - Composition:Polyamide | EU6: 15 - Composition:Elastane | EV6: 15 - Composition:Spandex | EW6: 15 - Composition:Acrylic | EX6: 15 - Composition:Cotton | EY6: 15 - Composition:Silk | EZ6: 15 - Composition:Linen | FA6: 15 - Composition:Modal | FB6: 15 - Composition:Viscose | FC6: 15 - Composition:Rayon | FD6: 15 - Composition:Carbon | FE6: 15 - Composition:Metal | FF6: 15 - Composition:Wool | FG6: 15 - Composition:Cashmere | FH6: 15 - Composition:Mohair | FI6: 15 - Composition:Rabbit Hair | FJ6: 15 - Composition:Bovine Leather | FK6: 15 - Composition:Sheep Leather | FL6: 15 - Composition:Pig Leather | FM6: 15 - Composition:Polyurethane | FN6: 15 - Composition:Polyvinyl Chloride | FO6: 15 - Composition:Cupro | FP6: 15 - Composition:Lyocell | FQ6: 15 - Composition:Acetate | FR6: 15 - Composition:Down | FS6: 15 - Composition:Feather | FT6: 15 - Composition:Duck Down | FU6: 15 - Composition:Alpaca | FV6: 15 - Composition:Metallized Fibres | FW6: 15 - Composition:Polypropylene fibers | FX6: 15 - Composition:Other Fibers | FY6: 28 - Length | FZ6: 74 - Belt | GA6: 29 - Sleeve Length | GB6: 27 - Sleeve Type | GC6: 94 - Chest Pad | GD6: 83 - Details | GE6: 26 - Pattern | GF6: 24 - Sheer | GG6: 22 - Fabric | GH6: 86 - Placket Type | GI6: 78 - Lining | GJ6: 113 - Contour | GK6: 76 - Season | GL6: 20 - Operation Instruction | GM6: 114 - Fit Type | GN6: 1352 - Fabric Elasticity | GO6: 1919 - Printing Type | GP6: 2103 - Style source | GQ6: 1192 - Weaving Method | GR6: 21 - Collar Style | GS6: 6227 - Collection | GT6: Variation Theme | GU6: Size Family | GV6: Sub-Size Family | GW6: Size | GX6: Color | GY6: Color | GZ6: Size | HA6: Style | HB6: Material | HC6: Flavors | HD6: Applicable People | HE6: Capacity | HF6: Composition | HG6: Weight | HH6: Items | HI6: Quantity | HJ6: Model | HK6: Hair Length | HL6: Unit | HM6: US Size | HN6: Tops - Product - Shoulder width | HO6: Tops - Product - Bust size | HP6: Tops - Product - Clothes length | HQ6: Tops - Product - Sleeve length | HR6: Tops - Product - Waist size | HS6: Tops - Product - Underbust | HT6: Tops - Product - Neck | HU6: Tops - Product - Hem | HV6: Tops - Product - Cuffs | HW6: Tops - Body - Bust - min | HX6: Tops - Body - Bust - max | HY6: Tops - Body - Waist - min | HZ6: Tops - Body - Waist - max | IA6: Tops - Body - Hips - min | IB6: Tops - Body - Hips - max | IC6: Tops - Body - Height - min | ID6: Tops - Body - Height - max | IE6: SKU Images URL | IF6: SKU Images URL | IG6: SKU Images URL | IH6: SKU Images URL | II6: SKU Images URL | IJ6: SKU Images URL | IK6: SKU Images URL | IL6: SKU Images URL | IM6: SKU Images URL | IN6: SKU Images URL | IO6: Quantity | IP6: Base Price - EUP | IQ6: List Price - EUP | IR6: Not available for List price | IS6: Weight - g | IT6: Length - cm | IU6: Width - cm | IV6: Height - cm | IW6: External Product ID Type | IX6: External Product ID | IY6: Handling Time | IZ6: Shipping Template | JA6: Import Designation | JB6: Item Tax Code | JC6: Product Guide
A7: Example 1: This is an example of providing a new listing. This example has no variation and is listed as a single detail page. | B7: 29069 | C7: Example Women T-shirt, 156 Black T-shirt | D7: EXAMPLE-156-US-Black-one-size | E7: EXAMPLE-156-US-Black-one-size | H7: Unleash your personal style with our classic fit tee. Crafted from 100% cotton, it offers unmatched comfort and durability. The tee features a unique, eye-catching graphic that embodies modern chic. Perfect for casual outings or layering under a jacket, this T-shirt is versatile for any occasion. With a breathable fabric that holds its shape, it's a wardrobe staple you'll reach for time and again. Make a statement and stay cozy in a shirt designed to express who you are. (Character count: 493) | I7: 100% premium cotton for ultimate comfort. | J7: Timeless design meets modern style. | K7: Durable fabric, perfect for daily wear | L7: Machine washable and easy to care for. | M7: Versatile fit for every body type. | O7: http://www.companyname.com/images/1250.main.jpg | P7: http://www.companyname.com/images/1250.main.jpg | Q7: http://www.companyname.com/images/1250.main.jpg | R7: http://www.companyname.com/images/1250.main.jpg | CO7: Recycle Polyester | DS7: Y2K | ER7: 32 | ES7: 28 | ET7: 40 | FY7: Short Length | FZ7: Yes | GA7: Long Sleeve | GB7: Raglan sleeve | GC7: No Padding | GD7: Fake Pockets | GE7: Mushroom | GF7: No | GG7: Non-Stretch | GH7: Half Placket | GI7: Cashmere | GJ7: H | GK7: Fall | GL7: Do not wash | GM7: Regular | GN7: No Elasticity | GO7: Positioning Printing | GP7: Buyer provides | GQ7: Woven | GR7: Off the Shoulder | GS7: Middle East | GT7: Size × Color | GU7: US/EU size | GV7: One Size | GW7: one-size | GX7: Black | HL7: cm | HM7: one-size | HO7: 36 | HP7: 28 | HW7: 33.9 | HX7: 35.5 | HY7: 26 | HZ7: 27.6 | IA7: 35.9 | IB7: 37.4 | IE7: http://www.companyname.com/images/1250.main.jpg | IF7: http://www.companyname.com/images/1250.main.jpg | IG7: http://www.companyname.com/images/1250.main.jpg | IO7: 5 | IP7: 2.99 | IQ7: 5.99 | IS7: 9.2 | IT7: 2 | IU7: 3 | IV7: 4 | IY7: 1 Day | IZ7: test1 | JA7: Imported | JB7: GEN STANDARD
B8: 12408 | C8: Example reclaimed Cabinet Solid Wood with 4 Drawers | D8: EXAMPLE-576-Brown | E8: EXAMPLE-576-Brown | DL8: Wood | DQ8: Painted | DR8: Cedar | DS8: Vintage | DT8: Plug Powered | DU8: 110V (included)-240V (included) | DV8: US Plug | DZ8: Yes | EA8: Hardwood | EC8: Block Board (large Core Board) | EG8: Yes | EH8: <3.2 Cubic Feet | EI8: <27 Inches | EJ8: <30 Lbs | EK8: Without Battery | EQ8: Red | GT8: Color × Style | GY8: Red | HA8: Vintage | IE8: http://www.companyname.com/images/1250.main.jpg | IF8: http://www.companyname.com/images/1250.main.jpg | IG8: http://www.companyname.com/images/1250.main.jpg | IO8: 0 | IP8: 2.99 | IQ8: 5.99 | IS8: 9.2 | IT8: 2 | IU8: 3 | IV8: 4 | IY8: 1 Day | IZ8: test1 | JA8: Imported | JB8: GEN STANDARD | JC8: http://www.companyname.com/images/productguide.pdf
B9: 44936 | C9: Example book for US with isbn | D9: EXAMPLEISBN9787040205190 | E9: EXAMPLEISBN9787040205190 | CT9: Example publisher | CU9: USA | CV9: Example author | CW9: No | CX9: Paperback | CY9: English | DB9: 44604 | DC9: 300 | DD9: Page | DE9: 1000 | DF9: 200 | DG9: g | DH9: 99 | DI9: years old | DJ9: 1 | DK9: years old | GT9: Items | HH9: Example book for US with isbn | IE9: http://www.companyname.com/images/1250.main.jpg | IF9: http://www.companyname.com/images/1250.main.jpg | IG9: http://www.companyname.com/images/1250.main.jpg | IO9: 20 | IP9: 7.82 | IQ9: 10.23 | IS9: 9.2 | IT9: 2 | IU9: 3 | IV9: 4 | IW9: ISBN | IX9: 920000021 | IY9: 1 Day | IZ9: test1 | JA9: Imported | JB9: BOOKS GEN
B10: 42550 | C10: Example food Potato Chips Pack of 6 - 80g per bag | D10: EXAMPLE-Pack6 - 80g | E10: EXAMPLE-Pack6 - 80g | BN10: 30 | BO10: Day | BP10: Wild-Caught | BQ10: Certified-Humane-Raised-And-Handled | BS10: 90 | BT10: g | BU10: 106 | BV10: g | BW10: Contains cow's milk | BX10: Contains Peanuts | CG10: Plant Based | CJ10: Example brand name | CK10: less than 70% organic ingredients | CL10: 45550 | CM10: 45641 | GT10: Weight | HG10: 90g | IE10: http://www.companyname.com/images/1250.main.jpg | IF10: http://www.companyname.com/images/1250.main.jpg | IG10: http://www.companyname.com/images/1250.main.jpg | IO10: 20 | IP10: 5.39 | IR10: N/A | IS10: 9.2 | IT10: 2 | IU10: 3 | IV10: 4 | IY10: 1 Day | IZ10: test1 | JA10: Imported | JB10: FOOD GEN
A12: Example 2: This is an example of a product with 1 variation theme (i.e., size) with 3 variations. These are 3 "Child" SKUs in a "Parent" Goods. Note: For product-level information such as Product Name, Product Description, Product Detail, Offer, Qualifications, please ensure that each line is filled out correctly and the information is consistently entered. | B12: 29069 | C12: Example Women T-shirt, 156 Black T-shirt | D12: EXAMPLE-156-US-Black | E12: EXAMPLE-156-US-Black-S | H12: Unleash your personal style with our classic fit tee. Crafted from 100% cotton, it offers unmatched comfort and durability. The tee features a unique, eye-catching graphic that embodies modern chic. Perfect for casual outings or layering under a jacket, this T-shirt is versatile for any occasion. With a breathable fabric that holds its shape, it's a wardrobe staple you'll reach for time and again. Make a statement and stay cozy in a shirt designed to express who you are. (Character count: 493) | I12: 100% premium cotton for ultimate comfort. | J12: Timeless design meets modern style. | K12: Durable fabric, perfect for daily wear | L12: Machine washable and easy to care for. | M12: Versatile fit for every body type. | O12: http://www.companyname.com/images/1250.main.jpg | P12: http://www.companyname.com/images/1250.main.jpg | Q12: http://www.companyname.com/images/1250.main.jpg | R12: http://www.companyname.com/images/1250.main.jpg | CO12: Recycle Polyester | DS12: Y2K | ER12: 32 | ES12: 28 | ET12: 40 | FY12: Short Length | FZ12: Yes | GA12: Long Sleeve | GB12: Raglan sleeve | GC12: No Padding | GD12: Fake Pockets | GE12: Mushroom | GF12: No | GG12: Non-Stretch | GH12: Half Placket | GI12: Cashmere | GJ12: H | GK12: Fall | GL12: Do not wash | GM12: Regular | GN12: No Elasticity | GO12: Positioning Printing | GP12: Buyer provides | GQ12: Woven | GR12: Off the Shoulder | GS12: Middle East | GT12: Size × Color | GU12: US/EU size | GV12: Alpha | GW12: S | GX12: Black | HL12: cm | HM12: 0 | HO12: 36 | HP12: 28 | HW12: 33.9 | HX12: 35.5 | HY12: 26 | HZ12: 27.6 | IA12: 35.9 | IB12: 37.4 | IE12: http://www.companyname.com/images/1250.main.jpg | IF12: http://www.companyname.com/images/1250.main.jpg | IG12: http://www.companyname.com/images/1250.main.jpg | IO12: 5 | IP12: 2.99 | IQ12: 5.99 | IS12: 9.2 | IT12: 2 | IU12: 3 | IV12: 4 | IY12: 1 Day | IZ12: test1 | JA12: Imported | JB12: GEN STANDARD
B13: 29069 | C13: Example Women T-shirt, 156 Black T-shirt | D13: EXAMPLE-156-US-Black | E13: EXAMPLE-156-US-Black-M | H13: Unleash your personal style with our classic fit tee. Crafted from 100% cotton, it offers unmatched comfort and durability. The tee features a unique, eye-catching graphic that embodies modern chic. Perfect for casual outings or layering under a jacket, this T-shirt is versatile for any occasion. With a breathable fabric that holds its shape, it's a wardrobe staple you'll reach for time and again. Make a statement and stay cozy in a shirt designed to express who you are. (Character count: 493) | I13: 100% premium cotton for ultimate comfort. | J13: Timeless design meets modern style. | K13: Durable fabric, perfect for daily wear | L13: Machine washable and easy to care for. | M13: Versatile fit for every body type. | O13: http://www.companyname.com/images/1250.main.jpg | P13: http://www.companyname.com/images/1250.main.jpg | Q13: http://www.companyname.com/images/1250.main.jpg | R13: http://www.companyname.com/images/1250.main.jpg | CO13: Recycle Polyester | DS13: Y2K | ER13: 32 | ES13: 28 | ET13: 40 | FY13: Short Length | FZ13: Yes | GA13: Long Sleeve | GB13: Raglan sleeve | GC13: No Padding | GD13: Fake Pockets | GE13: Mushroom | GF13: No | GG13: Non-Stretch | GH13: Half Placket | GI13: Cashmere | GJ13: H | GK13: Fall | GL13: Do not wash | GM13: Regular | GN13: No Elasticity | GO13: Positioning Printing | GP13: Buyer provides | GQ13: Woven | GR13: Off the Shoulder | GS13: Middle East | GT13: Size × Color | GU13: US/EU size | GV13: Alpha | GW13: M | GX13: Black | HL13: cm | HM13: 2 | HO13: 40 | HP13: 29 | HW13: 35.5 | HX13: 37 | HY13: 27.6 | HZ13: 29.2 | IA13: 27.4 | IB13: 39 | IE13: http://www.companyname.com/images/1250.main.jpg | IF13: http://www.companyname.com/images/1250.main.jpg | IG13: http://www.companyname.com/images/1250.main.jpg | IO13: 5 | IP13: 2.99 | IQ13: 5.99 | IS13: 9.2 | IT13: 2 | IU13: 3 | IV13: 4 | IY13: 1 Day | IZ13: test1 | JA13: Imported | JB13: GEN STANDARD
B14: 29069 | C14: Example Women T-shirt, 156 Black T-shirt | D14: EXAMPLE-156-US-Black | E14: EXAMPLE-156-US-Black-L | H14: Unleash your personal style with our classic fit tee. Crafted from 100% cotton, it offers unmatched comfort and durability. The tee features a unique, eye-catching graphic that embodies modern chic. Perfect for casual outings or layering under a jacket, this T-shirt is versatile for any occasion. With a breathable fabric that holds its shape, it's a wardrobe staple you'll reach for time and again. Make a statement and stay cozy in a shirt designed to express who you are. (Character count: 493) | I14: 100% premium cotton for ultimate comfort. | J14: Timeless design meets modern style. | K14: Durable fabric, perfect for daily wear | L14: Machine washable and easy to care for. | M14: Versatile fit for every body type. | O14: http://www.companyname.com/images/1250.main.jpg | P14: http://www.companyname.com/images/1250.main.jpg | Q14: http://www.companyname.com/images/1250.main.jpg | R14: http://www.companyname.com/images/1250.main.jpg | CO14: Recycle Polyester | DS14: Y2K | ER14: 32 | ES14: 28 | ET14: 40 | FY14: Short Length | FZ14: Yes | GA14: Long Sleeve | GB14: Raglan sleeve | GC14: No Padding | GD14: Fake Pockets | GE14: Mushroom | GF14: No | GG14: Non-Stretch | GH14: Half Placket | GI14: Cashmere | GJ14: H | GK14: Fall | GL14: Do not wash | GM14: Regular | GN14: No Elasticity | GO14: Positioning Printing | GP14: Buyer provides | GQ14: Woven | GR14: Off the Shoulder | GS14: Middle East | GT14: Size × Color | GU14: US/EU size | GV14: Alpha | GW14: L | GX14: Black | HL14: cm | HM14: 4 | HO14: 44 | HP14: 30 | HW14: 37.4 | HX14: 39.8 | HY14: 29.6 | HZ14: 31.9 | IA14: 39.4 | IB14: 41.8 | IE14: http://www.companyname.com/images/1250.main.jpg | IF14: http://www.companyname.com/images/1250.main.jpg | IG14: http://www.companyname.com/images/1250.main.jpg | IO14: 5 | IP14: 2.99 | IQ14: 5.99 | IS14: 9.2 | IT14: 2 | IU14: 3 | IV14: 4 | IY14: 1 Day | IZ14: test1 | JA14: Imported | JB14: GEN STANDARD
B15: 12408 | C15: Example reclaimed Cabinet Solid Wood with 4 Drawers | D15: EXAMPLE-576 | E15: EXAMPLE-576-Brown | DL15: Wood | DQ15: Painted | DR15: Cedar | DS15: Vintage | DT15: Plug Powered | DU15: 110V (included)-240V (included) | DV15: US Plug | DZ15: Yes | EA15: Hardwood | EC15: Block Board (large Core Board) | EG15: Yes | EH15: <3.2 Cubic Feet | EI15: <27 Inches | EJ15: <30 Lbs | EK15: Without Battery | EQ15: Red | GT15: Color | GY15: Brown | IE15: http://www.companyname.com/images/1250.main.jpg | IF15: http://www.companyname.com/images/1250.main.jpg | IG15: http://www.companyname.com/images/1250.main.jpg | IO15: 5 | IP15: 2.99 | IQ15: 5.99 | IS15: 9.2 | IT15: 2 | IU15: 3 | IV15: 4 | IY15: 1 Day | IZ15: test1 | JA15: Imported | JB15: GEN STANDARD
B16: 12408 | C16: Example reclaimed Cabinet Solid Wood with 4 Drawers | D16: EXAMPLE-576 | E16: EXAMPLE-576-white | DL16: Wood | DQ16: Painted | DR16: Cedar | DS16: Vintage | DT16: Plug Powered | DU16: 110V (included)-240V (included) | DV16: US Plug | DZ16: Yes | EA16: Hardwood | EC16: Block Board (large Core Board) | EG16: Yes | EH16: <3.2 Cubic Feet | EI16: <27 Inches | EJ16: <30 Lbs | EK16: Without Battery | EQ16: Red | GT16: Color | GY16: white | IE16: http://www.companyname.com/images/1250.main.jpg | IF16: http://www.companyname.com/images/1250.main.jpg | IG16: http://www.companyname.com/images/1250.main.jpg | IO16: 5 | IP16: 2.99 | IQ16: 5.99 | IS16: 9.2 | IT16: 2 | IU16: 3 | IV16: 4 | IY16: 1 Day | IZ16: test1 | JA16: Imported | JB16: GEN STANDARD
B17: 12408 | C17: Example reclaimed Cabinet Solid Wood with 4 Drawers | D17: EXAMPLE-576 | E17: EXAMPLE-576-red | DL17: Wood | DQ17: Painted | DR17: Cedar | DS17: Vintage | DT17: Plug Powered | DU17: 110V (included)-240V (included) | DV17: US Plug | DZ17: Yes | EA17: Hardwood | EC17: Block Board (large Core Board) | EG17: Yes | EH17: <3.2 Cubic Feet | EI17: <27 Inches | EJ17: <30 Lbs | EK17: Without Battery | EQ17: Red | GT17: Color | GY17: red | IE17: http://www.companyname.com/images/1250.main.jpg | IF17: http://www.companyname.com/images/1250.main.jpg | IG17: http://www.companyname.com/images/1250.main.jpg | IO17: 5 | IP17: 2.99 | IQ17: 5.99 | IS17: 9.2 | IT17: 2 | IU17: 3 | IV17: 4 | IY17: 1 Day | IZ17: test1 | JA17: Imported | JB17: GEN STANDARD
A19: Example 3: This is an example of a product with 2 variation themes (i.e., size and color) with 4 variations. These are 4 "Child" SKUs in a "Parent" Goods. Note: For product-level information such as Product Name, Product Description, Product Detail, Offer, Qualifications, please ensure that each line is filled out correctly and the information is consistently entered. | B19: 29069 | C19: Example Women T-shirt, 156 Black T-shirt | D19: EXAMPLE-156-US | E19: EXAMPLE-156-US-Black-S | H19: Unleash your personal style with our classic fit tee. Crafted from 100% cotton, it offers unmatched comfort and durability. The tee features a unique, eye-catching graphic that embodies modern chic. Perfect for casual outings or layering under a jacket, this T-shirt is versatile for any occasion. With a breathable fabric that holds its shape, it's a wardrobe staple you'll reach for time and again. Make a statement and stay cozy in a shirt designed to express who you are. (Character count: 493) | I19: 100% premium cotton for ultimate comfort. | J19: Timeless design meets modern style. | K19: Durable fabric, perfect for daily wear | L19: Machine washable and easy to care for. | M19: Versatile fit for every body type. | O19: http://www.companyname.com/images/1250.main.jpg | P19: http://www.companyname.com/images/1250.main.jpg | Q19: http://www.companyname.com/images/1250.main.jpg | R19: http://www.companyname.com/images/1250.main.jpg | CO19: Recycle Polyester | DS19: Y2K | ER19: 32 | ES19: 28 | ET19: 40 | FY19: Short Length | FZ19: Yes | GA19: Long Sleeve | GB19: Raglan sleeve | GC19: No Padding | GD19: Fake Pockets | GE19: Mushroom | GF19: No | GG19: Non-Stretch | GH19: Half Placket | GI19: Cashmere | GJ19: H | GK19: Fall | GL19: Do not wash | GM19: Regular | GN19: No Elasticity | GO19: Positioning Printing | GP19: Buyer provides | GQ19: Woven | GR19: Off the Shoulder | GS19: Middle East | GT19: Size × Color | GU19: US/EU size | GV19: Alpha | GW19: S | GX19: Black | HL19: cm | HM19: 0 | HO19: 36 | HP19: 28 | HW19: 33.9 | HX19: 35.5 | HY19: 26 | HZ19: 27.6 | IA19: 35.9 | IB19: 37.4 | IE19: http://www.companyname.com/images/1250.main.jpg | IF19: http://www.companyname.com/images/1250.main.jpg | IG19: http://www.companyname.com/images/1250.main.jpg | IO19: 5 | IP19: 2.99 | IQ19: 5.99 | IS19: 9.2 | IT19: 2 | IU19: 3 | IV19: 4 | IY19: 1 Day | IZ19: test1 | JA19: Imported | JB19: GEN STANDARD
B20: 29069 | C20: Example Women T-shirt, 156 Black T-shirt | D20: EXAMPLE-156-US | E20: EXAMPLE-156-US-Black-M | H20: Unleash your personal style with our classic fit tee. Crafted from 100% cotton, it offers unmatched comfort and durability. The tee features a unique, eye-catching graphic that embodies modern chic. Perfect for casual outings or layering under a jacket, this T-shirt is versatile for any occasion. With a breathable fabric that holds its shape, it's a wardrobe staple you'll reach for time and again. Make a statement and stay cozy in a shirt designed to express who you are. (Character count: 493) | I20: 100% premium cotton for ultimate comfort. | J20: Timeless design meets modern style. | K20: Durable fabric, perfect for daily wear | L20: Machine washable and easy to care for. | M20: Versatile fit for every body type. | O20: http://www.companyname.com/images/1250.main.jpg | P20: http://www.companyname.com/images/1250.main.jpg | Q20: http://www.companyname.com/images/1250.main.jpg | R20: http://www.companyname.com/images/1250.main.jpg | CO20: Recycle Polyester | DS20: Y2K | ER20: 32 | ES20: 28 | ET20: 40 | FY20: Short Length | FZ20: Yes | GA20: Long Sleeve | GB20: Raglan sleeve | GC20: No Padding | GD20: Fake Pockets | GE20: Mushroom | GF20: No | GG20: Non-Stretch | GH20: Half Placket | GI20: Cashmere | GJ20: H | GK20: Fall | GL20: Do not wash | GM20: Regular | GN20: No Elasticity | GO20: Positioning Printing | GP20: Buyer provides | GQ20: Woven | GR20: Off the Shoulder | GS20: Middle East | GT20: Size × Color | GU20: US/EU size | GV20: Alpha | GW20: M | GX20: Black | HL20: cm | HM20: 2 | HO20: 40 | HP20: 29 | HW20: 35.5 | HX20: 37 | HY20: 27.6 | HZ20: 29.2 | IA20: 27.4 | IB20: 39 | IE20: http://www.companyname.com/images/1250.main.jpg | IF20: http://www.companyname.com/images/1250.main.jpg | IG20: http://www.companyname.com/images/1250.main.jpg | IO20: 5 | IP20: 2.99 | IQ20: 5.99 | IS20: 9.2 | IT20: 2 | IU20: 3 | IV20: 4 | IY20: 1 Day | IZ20: test1 | JA20: Imported | JB20: GEN STANDARD
B21: 29069 | C21: Example Women T-shirt, 156 Black T-shirt | D21: EXAMPLE-156-US | E21: EXAMPLE-156-US-red-S | H21: Unleash your personal style with our classic fit tee. Crafted from 100% cotton, it offers unmatched comfort and durability. The tee features a unique, eye-catching graphic that embodies modern chic. Perfect for casual outings or layering under a jacket, this T-shirt is versatile for any occasion. With a breathable fabric that holds its shape, it's a wardrobe staple you'll reach for time and again. Make a statement and stay cozy in a shirt designed to express who you are. (Character count: 493) | I21: 100% premium cotton for ultimate comfort. | J21: Timeless design meets modern style. | K21: Durable fabric, perfect for daily wear | L21: Machine washable and easy to care for. | M21: Versatile fit for every body type. | O21: http://www.companyname.com/images/1250.main.jpg | P21: http://www.companyname.com/images/1250.main.jpg | Q21: http://www.companyname.com/images/1250.main.jpg | R21: http://www.companyname.com/images/1250.main.jpg | CO21: Recycle Polyester | DS21: Y2K | ER21: 32 | ES21: 28 | ET21: 40 | FY21: Short Length | FZ21: Yes | GA21: Long Sleeve | GB21: Raglan sleeve | GC21: No Padding | GD21: Fake Pockets | GE21: Mushroom | GF21: No | GG21: Non-Stretch | GH21: Half Placket | GI21: Cashmere | GJ21: H | GK21: Fall | GL21: Do not wash | GM21: Regular | GN21: No Elasticity | GO21: Positioning Printing | GP21: Buyer provides | GQ21: Woven | GR21: Off the Shoulder | GS21: Middle East | GT21: Size × Color | GU21: US/EU size | GV21: Alpha | GW21: S | GX21: Red | HL21: cm | HM21: 0 | HO21: 36 | HP21: 28 | HW21: 33.9 | HX21: 35.5 | HY21: 26 | HZ21: 27.6 | IA21: 35.9 | IB21: 37.4 | IE21: http://www.companyname.com/images/1250.main.jpg | IF21: http://www.companyname.com/images/1250.main.jpg | IG21: http://www.companyname.com/images/1250.main.jpg | IO21: 5 | IP21: 3.99 | IQ21: 7.99 | IS21: 9.2 | IT21: 2 | IU21: 3 | IV21: 4 | IY21: 1 Day | IZ21: test1 | JA21: Imported | JB21: GEN STANDARD
B22: 29069 | C22: Example Women T-shirt, 156 Black T-shirt | D22: EXAMPLE-156-US | E22: EXAMPLE-156-US-red-M | H22: Unleash your personal style with our classic fit tee. Crafted from 100% cotton, it offers unmatched comfort and durability. The tee features a unique, eye-catching graphic that embodies modern chic. Perfect for casual outings or layering under a jacket, this T-shirt is versatile for any occasion. With a breathable fabric that holds its shape, it's a wardrobe staple you'll reach for time and again. Make a statement and stay cozy in a shirt designed to express who you are. (Character count: 493) | I22: 100% premium cotton for ultimate comfort. | J22: Timeless design meets modern style. | K22: Durable fabric, perfect for daily wear | L22: Machine washable and easy to care for. | M22: Versatile fit for every body type. | O22: http://www.companyname.com/images/1250.main.jpg | P22: http://www.companyname.com/images/1250.main.jpg | Q22: http://www.companyname.com/images/1250.main.jpg | R22: http://www.companyname.com/images/1250.main.jpg | CO22: Recycle Polyester | DS22: Y2K | ER22: 32 | ES22: 28 | ET22: 40 | FY22: Short Length | FZ22: Yes | GA22: Long Sleeve | GB22: Raglan sleeve | GC22: No Padding | GD22: Fake Pockets | GE22: Mushroom | GF22: No | GG22: Non-Stretch | GH22: Half Placket | GI22: Cashmere | GJ22: H | GK22: Fall | GL22: Do not wash | GM22: Regular | GN22: No Elasticity | GO22: Positioning Printing | GP22: Buyer provides | GQ22: Woven | GR22: Off the Shoulder | GS22: Middle East | GT22: Size × Color | GU22: US/EU size | GV22: Alpha | GW22: M | GX22: Red | HL22: cm | HM22: 2 | HO22: 40 | HP22: 29 | HW22: 35.5 | HX22: 37 | HY22: 27.6 | HZ22: 29.2 | IA22: 27.4 | IB22: 39 | IE22: http://www.companyname.com/images/1250.main.jpg | IF22: http://www.companyname.com/images/1250.main.jpg | IG22: http://www.companyname.com/images/1250.main.jpg | IO22: 5 | IP22: 3.99 | IQ22: 7.99 | IS22: 9.2 | IT22: 2 | IU22: 3 | IV22: 4 | IY22: 1 Day | IZ22: test1 | JA22: Imported | JB22: GEN STANDARD
B23: 12408 | C23: Example reclaimed Cabinet Solid Wood with 4 Drawers | D23: EXAMPLE-576 | E23: Example_Brand Night Stand with 4 Drawers (White, 21 inch) | DL23: Wood | DQ23: Painted | DR23: Cedar | DS23: Vintage | DT23: Plug Powered | DU23: 110V (included)-240V (included) | DV23: US Plug | DZ23: Yes | EA23: Hardwood | EC23: Block Board (large Core Board) | EG23: Yes | EH23: <3.2 Cubic Feet | EI23: <27 Inches | EJ23: <30 Lbs | EK23: Without Battery | EQ23: Red | GT23: Color × Size | GY23: White | GZ23: 21 inch | IE23: http://www.companyname.com/images/1250.main.jpg | IF23: http://www.companyname.com/images/1250.main.jpg | IG23: http://www.companyname.com/images/1250.main.jpg | IO23: 5 | IP23: 2.99 | IQ23: 5.99 | IS23: 9.2 | IT23: 2 | IU23: 3 | IV23: 4 | IY23: 1 Day | IZ23: test1 | JA23: Imported | JB23: GEN STANDARD
B24: 12408 | C24: Example reclaimed Cabinet Solid Wood with 4 Drawers | D24: EXAMPLE-576 | E24: Example_Brand Night Stand with 2 Drawers (White, 24 inch) | DL24: Wood | DQ24: Painted | DR24: Cedar | DS24: Vintage | DT24: Plug Powered | DU24: 110V (included)-240V (included) | DV24: US Plug | DZ24: Yes | EA24: Hardwood | EC24: Block Board (large Core Board) | EG24: Yes | EH24: <3.2 Cubic Feet | EI24: <27 Inches | EJ24: <30 Lbs | EK24: Without Battery | EQ24: Red | GT24: Color × Size | GY24: White | GZ24: 24 inch | IE24: http://www.companyname.com/images/1250.main.jpg | IF24: http://www.companyname.com/images/1250.main.jpg | IG24: http://www.companyname.com/images/1250.main.jpg | IO24: 5 | IP24: 2.99 | IQ24: 5.99 | IS24: 9.2 | IT24: 2 | IU24: 3 | IV24: 4 | IY24: 1 Day | IZ24: test1 | JA24: Imported | JB24: GEN STANDARD
B25: 12408 | C25: Example reclaimed Cabinet Solid Wood with 4 Drawers | D25: EXAMPLE-576 | E25: Example_Brand Night Stand with 2 Drawers (Grey, 21 inch) | DL25: Wood | DQ25: Painted | DR25: Cedar | DS25: Vintage | DT25: Plug Powered | DU25: 110V (included)-240V (included) | DV25: US Plug | DZ25: Yes | EA25: Hardwood | EC25: Block Board (large Core Board) | EG25: Yes | EH25: <3.2 Cubic Feet | EI25: <27 Inches | EJ25: <30 Lbs | EK25: Without Battery | EQ25: Red | GT25: Color × Size | GY25: Grey | GZ25: 21 inch | IE25: http://www.companyname.com/images/1250.main.jpg | IF25: http://www.companyname.com/images/1250.main.jpg | IG25: http://www.companyname.com/images/1250.main.jpg | IO25: 5 | IP25: 2.99 | IQ25: 5.99 | IS25: 9.2 | IT25: 2 | IU25: 3 | IV25: 4 | IY25: 1 Day | IZ25: test1 | JA25: Imported | JB25: GEN STANDARD
B26: 12408 | C26: Example reclaimed Cabinet Solid Wood with 4 Drawers | D26: EXAMPLE-576 | E26: Example_Brand Night Stand with 2 Drawers (Grey, 24 inch) | DL26: Wood | DQ26: Painted | DR26: Cedar | DS26: Vintage | DT26: Plug Powered | DU26: 110V (included)-240V (included) | DV26: US Plug | DZ26: Yes | EA26: Hardwood | EC26: Block Board (large Core Board) | EG26: Yes | EH26: <3.2 Cubic Feet | EI26: <27 Inches | EJ26: <30 Lbs | EK26: Without Battery | EQ26: Red | GT26: Color × Size | GY26: Grey | GZ26: 24 inch | IE26: http://www.companyname.com/images/1250.main.jpg | IF26: http://www.companyname.com/images/1250.main.jpg | IG26: http://www.companyname.com/images/1250.main.jpg | IO26: 5 | IP26: 2.99 | IQ26: 5.99 | IS26: 9.2 | IT26: 2 | IU26: 3 | IV26: 4 | IY26: 1 Day | IZ26: test1 | JA26: Imported | JB26: GEN STANDARD

Sheet Data Definitions
A1: How to complete your template
A2: Group Name | B2: Field Name | C2: Local Label Name | D2: Definition and Use | E2: Accepted Values | F2: Example | G2: Required?
A3: Product Identity - These are attributes that are important to buyers and should be populated for all your items. Some are required to create an offer.
B4: t_0_category | C4: Category | D4: Only supports uploading a single category of goods. Category ID has been preset in the dropdown. | E4: Input an appropriate category. | F4: 13788 | G4: Required
B5: t_0_productname | C5: Product Name | D5: Following MMS guidelines: Maximum of 500 characters, must not contain blank lines or more than two consecutive spaces. | E5: Provide a name for the item including brand, color, fit and size,in 500 characters | F5: Robert Graham Men's Maya Bay Short Sleeve Classic Fit Shirt, Cranberry, X-Large | G5: Required
B6: t_0_contributiongoods | C6: Contribution Goods | D6: The code provided by the platform to providers for marking and managing parent product links, filled in by the merchant. Must be unique within the store. Rows with the same Contribution Goods value will be treated by the system as different child SKUs under the same parent product. Please do not use leading or trailing spaces in SKUs. | E6: This attribute indicates the SKU number as assigned by the contributor | F6: ABC123 | G6: Required
B7: t_0_contributionsku | C7: Contribution SKU | D7: The code provided by the platform to providers for marking and managing sub-product links, filled in by the merchant. Must be unique within the store.Please do not use leading or trailing spaces in SKUs. | E7: This attribute indicates the SKU number as assigned by the contributor | F7: ABC123 | G7: Required
B8: t_0_brand | C8: Brand | D8: If the product requires brand information, please select both Brand and Trademark of that. | E8: Select the brand name of the product https://seller-eu.temu.com/performance/account-health.html?tab=compliance&opType=register | F8: Nike | G8: Optional
B9: t_0_trademark | C9: Trademark | D9: If the product requires brand information, please select both Brand and Trademark of that. Please take care when selecting the Brand and Trademark you want to associate with. | E9: Select the trademark name of the product | F9: Nike | G9: Optional
A10: Product Description - These attributes have an effect on how customers can find your product on the site using browse or search
B11: t_1_productdescription | C11: Product Description | D11: A text description of the product. | E11: Following MMS guidelines: Maximum of 2000 characters, not support the rich text formatting. | F11: Long sleeve v-neck cardigan with a ribbed waistline and pockets with bow detailing | G11: Optional
B12: t_1_bulletpoint | C12: Bullet Point | D12: Brief descriptive text, called out via a bullet point, regarding a specific aspect of the product. These display directly under or next to your product photo, it is useful to put interesting information in these fields. Bullet points will be inserted automatically. | E12: Following MMS guidelines: Maximum of 700 characters, not support the rich text formatting. You can upload one bullet point per cell | F12: Made with nourishing pure aloe vera gel | G12: Optional
B13: t_1_detailimagesurl | C13: Detail Images URL | D13: The URL for detail images of your product. These images will be shown on the detail page when the customer clicks through to see other views associated with the product. For example, you can use this field to show the label information or packaging of your product. Upload additional images with different views to the item, or with some emotional surrounding as additional image. | E13: Obtain URLs from any image hosting website and enter them into the respective cells. i. Aspect ratio: min of 1:3; ii. Width or height: min of 480px; iii. File size: max of 3MB; iv. File types: jpeg, jpg, png | F13: http://www.companyname.com/images/1250.main.jpg | G13: Optional
B14: t_1_detailvideourl | C14: Detail Video URL | D14: The URL for detail video of your product. The detail video will be presented at the top of the product details section. | E14: Obtain URLs from any image hosting website and enter them into the respective cells. i. Aspect ratio: 1:1, 4:3, 16:9 ii. Resolution: min of 720p iii. Duration: max of 180s iv. File size: max of 300MB v. File types: wmv, avi, 3gp, mov, mp4, flv, rmvb, mkv, m4v, x-flv | F14: http://www.companyname.com/videos/1250..mp4 | G14: Optional
A15: Sale Property (At Least One, At Most Two) - These attributes used for product is available in different variations
B16: t_3_variationtheme | C16: Variation Theme | D16: Describes the parameter(s) by which the parent product may vary. The value input for this field should be the same for all the SKUs of the same product. Example: If the product varies by size, input the value Size. If the product varies by color, input the value Color. Terms used for variation themes are created by you the merchant. (e.g. 'quantity' can be any number that you choose). | E16: Select and applicable variation theme. | F16: Color × Size | G16: Required
A17: Variations - These are attributes that are important to buyers and should be populated for the sku of the product
B18: t_5_skuimagesurl | C18: SKU Images URL | D18: The SKU images will be displayed at the top of the product page when the customer clicks through to see other views associated with the product. Different SKU images will form a carousel of the product. For example, you can use this field to show the label information or packaging of your product. Upload additional images with different views to the item, or with some emotional surrounding as additional image. | E18: a. For clothes: i. Aspect ratio: 3:4 ii. Width: min of 1340px iii. Height: min of 1785px iv. File size: max of 3MB v. File types: jpeg, jpg, png b. For other products: i. Aspect ratio: 1:1 ii. Width or height: min of 800px iii. File size: max of 3MB iv. File types: jpeg, jpg, png | F18: http://www.companyname.com/images/1250.main.jpg | G18: Required
B19: t_5_dimensions | C19: Dimensions | D19: Please use imperial units to indicate product dimensions. This can help buyers get a better understanding of the size and specifications of the product. | E19: a. For clothes: i. Aspect ratio: 3:4 ii. Width: min of 1340px iii. Height: min of 1785px iv. File size: max of 3MB v. File types: jpeg, jpg, png b. For other products: i. Aspect ratio: 1:1 ii. Width or height: min of 800px iii. File size: max of 3MB iv. File types: jpeg, jpg, png | F19: http://www.companyname.com/images/1250.dimension.jpg | G19: Optional
B20: t_5_quantity | C20: Quantity | D20: Enter the quantity of the item you are making available for sale. This is your current INVENTORY commitment. Quantity is required for all "child" or stand-alone items. If left blank when first submitting the product information, the item will be displayed as "Out of stock." | E20: Enter the quantity of the item you are making available for sale. This is your current inventory commitment (as a whole number) | F20: 152 | G20: Required
B21: t_5_baseprice_eur | C21: Base Price - EUR | D21: The Base Price should reflect your costs and expected profit. You'll receive sales proceeds based on the Operative Price for each product sold. The final Retail Price is not directly linked to your payment settlement. Base price must be less than list price. | E21: The price range is €0.01-€99999999.99, with a maximum of 2 decimal places, and will be rounded up. | F21: 3.99 | G21: Required
B22: t_5_Recommended retail price_eur | C22: Recommended retail price - EUR | D22: The list price is the suggested or recommended retail price of a product set by the manufacturer. It must be a genuine selling price on the market and in compliance with applicable laws and regulations. If your product is listed for sale in the EU, the product must have been advertised and sold at or above the provided list price by at least one EU retailer. By inputting a list price you are confirming that: - You are not the only seller of the product on the market where the product will be sold (and where a list price comparison will be made); and - You have evidence that the list price you are providing is a genuine price at which the product is generally sold. You must make such evidence available to Temu on request. Base price must be less than list price. | E22: The price range is €0.01-€99999999.99, with a maximum of 2 decimal places, and will be rounded up. | F22: 5.79 | G22: Required
B23: t_5_notavailableforlistprice | C23: Not available for List price | D23: The list price is the suggested or recommended retail price of a product set by the manufacturer. It must be a genuine selling price in the market, complying with applicable laws and regulations. If your product is listed for sale in the EU, the product must have been advertised and sold at the list price provided or above by at least one EU retailer. If your product does not have a list price that meets these criteria, you may set as N/A(Not available). | E23: Select N/A if your product does not have a list price | F23: N/A | G23: Optional
B24: t_5_weight_g | C24: Weight - g | D24: This will be used to indicate the package weight of the SKU and will be used by Temu to estimate logistics costs. Please fill this in accurately. | E24: The weight range is 0.1 g-9,999,999.9 g, with a maximum of 1 decimal place, and will be rounded up | F24: 10.2 | G24: Required
B25: t_5_length_cm | C25: Length - cm | D25: This will be used to indicate the package volune of the SKU and will be used by Temu to estimate logistics costs. Please fill this in accurately. | E25: The length range is 0.1 cm-9,999.9 cm, with a maximum of 1 decimal point, and will be rounded up | F25: 3.1 | G25: Required
B26: t_5_width_cm | C26: Width - cm | D26: This will be used to indicate the package volune of the SKU and will be used by Temu to estimate logistics costs. Please fill this in accurately. | E26: The length range is 0.1 cm-9,999.9 cm, with a maximum of 1 decimal point, and will be rounded up | F26: 2.1 | G26: Required
B27: t_5_height_cm | C27: Height - cm | D27: This will be used to indicate the package volune of the SKU and will be used by Temu to estimate logistics costs. Please fill this in accurately. | E27: The length range is 0.1 cm-9,999.9 cm, with a maximum of 1 decimal point, and will be rounded up | F27: 1.1 | G27: Required
B28: t_5_externalproductidtype | C28: External Product ID Type | D28: The type of standard, unique identifier entered in the Product ID field. This is a required field if Product ID is provided. | E28: The type of standard, unique identifier entered in the Product ID field. This is a required field if Product ID is provided. | F28: UPC | G28: Optional
B29: t_5_externalproductid | C29: External Product ID | D29: A standard, alphanumeric string that uniquely identifies the product. This could be a GCID (16 alphanumeric characters), UPC or EAN. This is a required field if product_id_type is provided. | E29: Provide the corresponding external product id value based on the type that was selected | F29: 714532191586 | G29: Optional
A30: Offer - These attributes are required to make your product buyable for customers on the site
B31: t_6_handlingtime | C31: Handling Time | D31: Indicates the time, in days, between when you receive an order for an item and when you can ship the item. The default production time is one to two business days. Use this field if your production time is greater than two business days. | E31: The same as MMS. Only supports 1, 2 days. | F31: 1 Day | G31: Required
B32: t_6_shippingtemplate | C32: Shipping Template | D32: Sellers can create a set of ship configurations based on business needs and use cases. The ship configurations can be region based and have rules to set SLA and rate for the region. When listing product to create offer, seller needs to select one ship configuration for the product. The ship configuration will be used to retrieve the valid ship options on the website. | E32: Must first finish creating the shipping template in [https://seller-eu.temu.com/shipping-templates-create.html], and all available shipping template names in the store will be displayed here. | F32: "Free Shipping Template", "Default Template" | G32: Required
B33: t_6_fulfillmentchannel | C33: Fulfillment Channel | G33: Required
B34: t_6_itemtaxcode | C34: Item Tax Code | D34: The Item tax code (ITC) matches a product with the correct VAT rate prescribed for the relevant product category. If no ITC is assigned to the product, the default value from “calculation settings” will be applied. | E34: Enter the item tax code supplied to you by temu.com. | F34: GEN STANDARD | G34: Optional
A35: Qualifications - Attributes used to comply with consumer laws in the country or region where the item is sold
B36: t_8_product_guide | C36: Product Guide | E36: Please get the URL of the manual from any image hosting website and fill it into the cell. Product Guide Filing Requirements: a. File size: max of 15MB b. File type: pdf | F36: http://www.companyname.com/guide/1250.pdf | G36: Optional
B37: t_8_Country/Region of Origin | C37: Country/Region of Origin | D37: The Country/Region of Origin of a product is generally the country or region where the product was wholly produced or manufactured. If more than one country or region is involved in the product’s production or manufacture, the Country/Region of Origin is generally where the last "substantial transformation" of the product occurred. | E37: Select the Country/Region of the product | F37: Germany | G37: Required
B38: t_8_Province of Origin | C38: Province of Origin | D38: When the country of origin is Mainland China, the province of origin cannot not be empty. | E38: Select the Province of the product | G38: Required
B39: t_8_Have any products under this goods ID been placed on the EU (or Northern Ireland) market after December 13, 2024? | C39: Have any products under this goods ID been placed on the EU (or Northern Ireland) market after December 13, 2024? | D39: If you select “Yes. Products under this goods ID have been placed on the EU(or Northern Ireland) market after December 13, 2024.” your product must comply with the relevant GPSR requirements，Declare the manufacturer、EU responsible person、 identification code、warning and safety information (if applicable) and upload Compliance images in the Product Compliance page. Otherwise, non-compliant goods will be removed from the EU site and the Northern Ireland region of the UK. If you have not yet submitted the required information, Please submit on the product editing page as soon as possible. You can know more about the GPSR requirements by searching“GPSR filing information and FAQs”on help center-Policy&Operational article page. | G39: Required
B40: t_8_Product Identification | C40: Product Identification | D40: For products placed on the EU (or Northern Ireland) market after December 13, 2024, you shall declare the product identification, otherwise it will affect sales in EU (or Northern Ireland) market. You can declare batch number, serial number, or any other elements that can be used to identify and trace the product as product identification. | G40: Required
B41: t_8_Manufacturer | C41: Manufacturer | D41: The manufacturer must be consistent with the information in the actual photo. | E41: Must first finish adding the manufacturer in [https://seller-eu.temu.com/performance/account-health.html?subTab=manufacturer], and all manufacturer names in the store will be displayed here. | G41: Required
B42: t_8_EU responsible person | C42: EU responsible person | D42: If the manufacturer is within the EU, it's not necessary to select a responsible person. If you select a responsible person, please ensure that it's consistent with the information in the actual photo. | E42: Must first finish adding the responsible person in [https://seller-eu.temu.com/performance/account-health.html?subTab=person], and all responsible person names in the store will be displayed here. | G42: Required

Sheet Template
A1: Processing Results | E1: Product Identity | T1: Product Description | DS1: Product Detail | KF1: Sale Property (At Least One, At Most Two) | KK1: Size Chart | LO1: Variations | MS1: Offer | MW1: Qualifications
A2: Goods Id | B2: Sku Id | C2: Status | D2: Details | E2: Category | F2: Category Name | G2: Product type | H2: Customization processing technique | I2: Primary technique | J2: Secondary technique | K2: Secondary technique | L2: Product Name | M2: Contribution Goods | N2: Contribution SKU | O2: Update or Add | P2: Goods Id | Q2: Sku Id | R2: Brand | S2: Trademark | T2: Product Description | U2: Bullet Point | V2: Bullet Point | W2: Bullet Point | X2: Bullet Point | Y2: Bullet Point | Z2: Bullet Point | AA2: Detail Images URL | AB2: Detail Images URL | AC2: Detail Images URL | AD2: Detail Images URL | AE2: Detail Images URL | AF2: Detail Images URL | AG2: Detail Images URL | AH2: Detail Images URL | AI2: Detail Images URL | AJ2: Detail Images URL | AK2: Detail Images URL | AL2: Detail Images URL | AM2: Detail Images URL | AN2: Detail Images URL | AO2: Detail Images URL | AP2: Detail Images URL | AQ2: Detail Images URL | AR2: Detail Images URL | AS2: Detail Images URL | AT2: Detail Images URL | AU2: Detail Images URL | AV2: Detail Images URL | AW2: Detail Images URL | AX2: Detail Images URL | AY2: Detail Images URL | AZ2: Detail Images URL | BA2: Detail Images URL | BB2: Detail Images URL | BC2: Detail Images URL | BD2: Detail Images URL | BE2: Detail Images URL | BF2: Detail Images URL | BG2: Detail Images URL | BH2: Detail Images URL | BI2: Detail Images URL | BJ2: Detail Images URL | BK2: Detail Images URL | BL2: Detail Images URL | BM2: Detail Images URL | BN2: Detail Images URL | BO2: Detail Images URL | BP2: Detail Images URL | BQ2: Detail Images URL | BR2: Detail Images URL | BS2: Detail Images URL | BT2: Detail Images URL | BU2: Detail Images URL | BV2: Detail Images URL | BW2: Detail Images URL | BX2: Detail Images URL | BY2: Detail Images URL | BZ2: Detail Images URL | CA2: Detail Images URL | CB2: Detail Images URL | CC2: Detail Images URL | CD2: Detail Images URL | CE2: Detail Images URL | CF2: Detail Images URL | CG2: Detail Images URL | CH2: Detail Images URL | CI2: Detail Images URL | CJ2: Detail Images URL | CK2: Detail Images URL | CL2: Detail Images URL | CM2: Detail Images URL | CN2: Detail Images URL | CO2: Detail Images URL | CP2: Detail Images URL | CQ2: Detail Images URL | CR2: Detail Images URL | CS2: Detail Images URL | CT2: Detail Images URL | CU2: Detail Images URL | CV2: Detail Images URL | CW2: Detail Images URL | CX2: Detail Images URL | CY2: Detail Images URL | CZ2: Detail Images URL | DA2: Detail Images URL | DB2: Detail Images URL | DC2: Detail Images URL | DD2: Detail Images URL | DE2: Detail Images URL | DF2: Detail Images URL | DG2: Detail Images URL | DH2: Detail Images URL | DI2: Detail Images URL | DJ2: Detail Images URL | DK2: Detail Images URL | DL2: Detail Images URL | DM2: Detail Images URL | DN2: Detail Images URL | DO2: Detail Images URL | DP2: Detail Images URL | DQ2: Detail Images URL | DR2: Detail Video URL | DS2: 1259 - Upper Material | DT2: 1259 - Upper Material | DU2: 7964 - Mesh Types of Fabric | DV2: 7550 - Fabric Material Composition | DW2: 1261 - Sole Material | DX2: 1261 - Sole Material | DY2: 1260 - Inner Material | DZ2: 1260 - Inner Material | EA2: 7965 - Lining Fabric Type | EB2: 92 - Closure Type | EC2: 92 - Closure Type | ED2: 92 - Closure Type | EE2: 92 - Closure Type | EF2: 1264 - Toe Cap | EG2: 1449 - Applicable Age | EH2: 90 - occasion | EI2: 90 - occasion | EJ2: 90 - occasion | EK2: 19 - Style | EL2: 19 - Style | EM2: 19 - Style | EN2: 143 - Special Features | EO2: 143 - Special Features | EP2: 143 - Special Features | EQ2: 1093 - Popular Elements | ER2: 1093 - Popular Elements | ES2: 1093 - Popular Elements | ET2: 76 - Season | EU2: 76 - Season | EV2: 76 - Season | EW2: 115 - Applicable People | EX2: 115 - Applicable People | EY2: 115 - Applicable People | EZ2: 26 - Pattern | FA2: 26 - Pattern | FB2: 26 - Pattern | FC2: 1101 - Upper height&cylinder height | FD2: 1262 - Insole Material | FE2: 1262 - Insole Material | FF2: 1132 - Operating Voltage | FG2: 137 - Battery Type | FH2: 20 - Operation Instruction | FI2: 1919 - Printing Type | FJ2: 7963 - Secondary Upper Material | FK2: 7969 - Secondary Mesh Types of Fabric | FL2: 7970 - Secondary Fabric Material Components | FM2: 9154 - Approximate Location Of Material Label | FN2: 9154 - Approximate Location Of Material Label | FO2: 9154 - Approximate Location Of Material Label | FP2: 7550 - Fabric Material Composition | FQ2: 15 - Composition:Nylon | FR2: 15 - Composition:Polyester | FS2: 15 - Composition:Polyamide | FT2: 15 - Composition:Elastane | FU2: 15 - Composition:Acrylic | FV2: 15 - Composition:Cotton | FW2: 15 - Composition:Silk | FX2: 15 - Composition:Linen | FY2: 15 - Composition:Modal | FZ2: 15 - Composition:Viscose | GA2: 15 - Composition:Carbon-Fiber | GB2: 15 - Composition:Metal | GC2: 15 - Composition:Wool | GD2: 15 - Composition:Cashmere | GE2: 15 - Composition:Mohair | GF2: 15 - Composition:Rabbit Hair | GG2: 15 - Composition:Bovine Leather | GH2: 15 - Composition:Sheep Leather | GI2: 15 - Composition:Pig Leather | GJ2: 15 - Composition:Polyurethane | GK2: 15 - Composition:Polyvinyl Chloride | GL2: 15 - Composition:Cupro | GM2: 15 - Composition:Lyocell | GN2: 15 - Composition:Acetate | GO2: 15 - Composition:Alpaca | GP2: 15 - Composition:Metallized Fibres | GQ2: 15 - Composition:Polyethylene | GR2: 15 - Composition:Other Fibers | GS2: 15 - Composition:Silicone | GT2: 12 - Material | GU2: 7639 - Base Fabric Composition:Silk | GV2: 7639 - Base Fabric Composition:Linen | GW2: 7639 - Base Fabric Composition:Modal | GX2: 7639 - Base Fabric Composition:Viscose | GY2: 7639 - Base Fabric Composition:Carbon-Fiber | GZ2: 7639 - Base Fabric Composition:Metal | HA2: 7639 - Base Fabric Composition:Wool | HB2: 7639 - Base Fabric Composition:Cashmere | HC2: 7639 - Base Fabric Composition:Mohair | HD2: 7639 - Base Fabric Composition:Rabbit Hair | HE2: 7639 - Base Fabric Composition:Bovine Leather | HF2: 7639 - Base Fabric Composition:Sheep Leather | HG2: 7639 - Base Fabric Composition:Pig Leather | HH2: 7639 - Base Fabric Composition:Polyurethane | HI2: 7639 - Base Fabric Composition:Polyvinyl Chloride | HJ2: 7639 - Base Fabric Composition:Cupro | HK2: 7639 - Base Fabric Composition:Lyocell | HL2: 7639 - Base Fabric Composition:Acetate | HM2: 7639 - Base Fabric Composition:Down | HN2: 7639 - Base Fabric Composition:Feather | HO2: 7639 - Base Fabric Composition:Duck Down | HP2: 7639 - Base Fabric Composition:Alpaca | HQ2: 7639 - Base Fabric Composition:Other Fibers | HR2: 7639 - Base Fabric Composition:Polyester | HS2: 7639 - Base Fabric Composition:Metallized Fibres | HT2: 7639 - Base Fabric Composition:Triacetate | HU2: 7639 - Base Fabric Composition:Polypropylene | HV2: 7639 - Base Fabric Composition:Ramie | HW2: 7639 - Base Fabric Composition:Nylon | HX2: 7639 - Base Fabric Composition:Polyamide | HY2: 7639 - Base Fabric Composition:Elastane | HZ2: 7639 - Base Fabric Composition:Acrylic | IA2: 7639 - Base Fabric Composition:Cotton | IB2: 82 - Socks Type | IC2: 83 - Details | ID2: 75 - Gender | IE2: 1306 - Number Of Products | IF2: 1192 - Weaving Method | IG2: 6227 - Collection | IH2: 2103 - Style source | II2: 6926 - Fabric Texture 1 | IJ2: 6930 - Fabric Weight 1 (g/m²) - value | IK2: 6930 - Fabric Weight 1 (g/m²) - unit | IL2: 6927 - Fabric Texture 2 | IM2: 6931 - Fabric Weight 2 (g/m²) - value | IN2: 6931 - Fabric Weight 2 (g/m²) - unit | IO2: 6928 - Lining Texture | IP2: 6934 - Lining Weight (g/m²) - value | IQ2: 6934 - Lining Weight (g/m²) - unit | IR2: 6547 - Lining Ingredients:Silk | IS2: 6547 - Lining Ingredients:Linen | IT2: 6547 - Lining Ingredients:Modal | IU2: 6547 - Lining Ingredients:Viscose | IV2: 6547 - Lining Ingredients:Carbon-Fiber | IW2: 6547 - Lining Ingredients:Metal | IX2: 6547 - Lining Ingredients:Wool | IY2: 6547 - Lining Ingredients:Cashmere | IZ2: 6547 - Lining Ingredients:Mohair | JA2: 6547 - Lining Ingredients:Rabbit Hair | JB2: 6547 - Lining Ingredients:Bovine Leather | JC2: 6547 - Lining Ingredients:Sheep Leather | JD2: 6547 - Lining Ingredients:Pig Leather | JE2: 6547 - Lining Ingredients:Polyurethane | JF2: 6547 - Lining Ingredients:Polyvinyl Chloride | JG2: 6547 - Lining Ingredients:Cupro | JH2: 6547 - Lining Ingredients:Lyocell | JI2: 6547 - Lining Ingredients:Acetate | JJ2: 6547 - Lining Ingredients:Down | JK2: 6547 - Lining Ingredients:Feather | JL2: 6547 - Lining Ingredients:Duck Down | JM2: 6547 - Lining Ingredients:Alpaca | JN2: 6547 - Lining Ingredients:Other Fibers | JO2: 6547 - Lining Ingredients:Metallized Fibres | JP2: 6547 - Lining Ingredients:Polypropylene | JQ2: 6547 - Lining Ingredients:Ramie | JR2: 6547 - Lining Ingredients:Nylon | JS2: 6547 - Lining Ingredients:Polyester | JT2: 6547 - Lining Ingredients:Polyamide | JU2: 6547 - Lining Ingredients:Elastane | JV2: 6547 - Lining Ingredients:Acrylic | JW2: 6547 - Lining Ingredients:Cotton | JX2: 7654 - Is it lined with plush? | JY2: 7955 - Are they wide-fit shoes? | JZ2: 84 - Type | KA2: 203 - All-season | KB2: 6443 - Origin | KC2: 466 - Heel Type | KD2: 420 - Toe Style | KE2: 128 - Embellishment | KF2: Variation Theme | KG2: Size Family | KH2: Sub-Size Family | KI2: Size | KJ2: Color | KK2: Size Chart Method | KL2: Size Chart Image | KM2: Unit | KN2: EU size | KO2: 13 - Shoes - Product - Foot length | KP2: 13 - Shoes - Product - Foot width | KQ2: 13 - Shoes - Product - Ball girth | KR2: 13 - Shoes - Product - Shoe inner length | KS2: 11 - Shoes - Product - Foot length | KT2: 11 - Shoes - Product - Foot width | KU2: 11 - Shoes - Product - Ball girth | KV2: 11 - Shoes - Product - Shoe inner length | KW2: 11 - Shoes - Product - instep girth | KX2: 25 - Socks - Product - Length | KY2: 25 - Socks - Product - Width | KZ2: 25 - Socks - Product - Height | LA2: 107 - Shoes - Product - Foot length | LB2: 107 - Shoes - Product - Foot width | LC2: 107 - Shoes - Product - Ball girth | LD2: 107 - Shoes - Product - Shoe inner length | LE2: 12 - Shoes - Product - Foot length | LF2: 12 - Shoes - Product - Foot width | LG2: 12 - Shoes - Product - Ball girth | LH2: 12 - Shoes - Product - Shoe platform height | LI2: 12 - Shoes - Product - Boot shaft height | LJ2: 12 - Shoes - Product - Calf circumference | LK2: 12 - Shoes - Product - Shoe collar circumference | LL2: 12 - Shoes - Product - Heel height | LM2: 12 - Shoes - Product - Shoe inner length | LN2: 12 - Shoes - Product - instep girth | LO2: SKU Images URL | LP2: SKU Images URL | LQ2: SKU Images URL | LR2: SKU Images URL | LS2: SKU Images URL | LT2: SKU Images URL | LU2: SKU Images URL | LV2: SKU Images URL | LW2: SKU Images URL | LX2: SKU Images URL | LY2: Quantity | LZ2: Base Price - EUR | MA2: Reference Link | MB2: List Price - EUR | MC2: Not available for List price | MD2: Weight - g | ME2: Length - cm | MF2: Width - cm | MG2: Height - cm | MH2: SKU type | MI2: Individually packed | MJ2: Total packaging quantity | MK2: Packaging unit | ML2: Total item quantity | MM2: Item unit | MN2: Net content | MO2: Total net content | MP2: Net content unit | MQ2: External Product ID Type | MR2: External Product ID | MS2: Shipping Template | MT2: Handling Time | MU2: Fulfillment Channel | MV2: Item Tax Code | MW2: Country/Region of Origin | MX2: Province of Origin | MY2: SKU Packaging Information (with visible label) | MZ2: SKU Packaging Information (with visible label) | NA2: SKU Packaging Information (with visible label) | NB2: SKU Packaging Information (with visible label) | NC2: SKU Packaging Information (with visible label) | ND2: SKU Packaging Information (with visible label) | NE2: SKU Packaging Information (with visible label) | NF2: SKU Packaging Information (with visible label) | NG2: SKU Packaging Information (with visible label) | NH2: SKU Packaging Information (with visible label) | NI2: SKU Packaging Information (with visible label) | NJ2: SKU Packaging Information (with visible label) | NK2: SKU Packaging Information (with visible label) | NL2: SKU Packaging Information (with visible label) | NM2: SKU Packaging Information (with visible label) | NN2: SKU Packaging Information (with visible label) | NO2: SKU Packaging Information (with visible label) | NP2: SKU Packaging Information (with visible label) | NQ2: SKU Packaging Information (with visible label) | NR2: SKU Packaging Information (with visible label) | NS2: SKU Packaging Information (with visible label) | NT2: SKU Packaging Information (with visible label) | NU2: SKU Packaging Information (with visible label) | NV2: SKU Packaging Information (with visible label) | NW2: SKU Packaging Information (with visible label) | NX2: SKU Packaging Information (with visible label) | NY2: SKU Packaging Information (with visible label) | NZ2: SKU Packaging Information (with visible label) | OA2: SKU Packaging Information (with visible label) | OB2: SKU Packaging Information (with visible label) | OC2: SKU Packaging Information (with visible label) | OD2: SKU Packaging Information (with visible label) | OE2: SKU Packaging Information (with visible label) | OF2: SKU Packaging Information (with visible label) | OG2: SKU Packaging Information (with visible label) | OH2: SKU Packaging Information (with visible label) | OI2: SKU Packaging Information (with visible label) | OJ2: SKU Packaging Information (with visible label) | OK2: SKU Packaging Information (with visible label) | OL2: SKU Packaging Information (with visible label) | OM2: SKU Packaging Information (with visible label) | ON2: SKU Packaging Information (with visible label) | OO2: SKU Packaging Information (with visible label) | OP2: SKU Packaging Information (with visible label) | OQ2: SKU Packaging Information (with visible label) | OR2: Origin Label & Manufacturer Information | OS2: Origin Label & Manufacturer Information | OT2: Origin Label & Manufacturer Information | OU2: Origin Label & Manufacturer Information | OV2: Origin Label & Manufacturer Information | OW2: Product Identification | OX2: Manufacturer | OY2: EU Responsible person | OZ2: Have any products under this goods ID been placed on the EU (or Northern Ireland) market after December 13, 2024?
A3: Reserved line, prohibit any operation. | B3: Reserved line, prohibit any operation. | C3: Reserved line, prohibit any operation. | D3: Reserved line, prohibit any operation. | E3: eyJ0ZW1wbGF0ZV9pZCI6MjgzMzY4NDI2MDA5ODE3LCJ0ZW1wbGF0ZV9sYW5ndWFnZSI6ImVuIiwic2l0ZV9pZCI6MTQxLCJ2ZXJzaW9uIjoiMy4wLjAiLCJ0eXBlIjowfQ== | F3: Reserved line, prohibit any operation. | G3: Reserved line, prohibit any operation. | H3: Reserved line, prohibit any operation. | I3: Reserved line, prohibit any operation. | J3: Reserved line, prohibit any operation. | K3: Reserved line, prohibit any operation. | L3: Reserved line, prohibit any operation. | M3: Reserved line, prohibit any operation. | N3: Reserved line, prohibit any operation. | O3: Reserved line, prohibit any operation. | P3: Reserved line, prohibit any operation. | Q3: Reserved line, prohibit any operation. | R3: Reserved line, prohibit any operation. | S3: Reserved line, prohibit any operation. | T3: Reserved line, prohibit any operation. | U3: Reserved line, prohibit any operation. | V3: Reserved line, prohibit any operation. | W3: Reserved line, prohibit any operation. | X3: Reserved line, prohibit any operation. | Y3: Reserved line, prohibit any operation. | Z3: Reserved line, prohibit any operation. | AA3: Reserved line, prohibit any operation. | AB3: Reserved line, prohibit any operation. | AC3: Reserved line, prohibit any operation. | AD3: Reserved line, prohibit any operation. | AE3: Reserved line, prohibit any operation. | AF3: Reserved line, prohibit any operation. | AG3: Reserved line, prohibit any operation. | AH3: Reserved line, prohibit any operation. | AI3: Reserved line, prohibit any operation. | AJ3: Reserved line, prohibit any operation. | AK3: Reserved line, prohibit any operation. | AL3: Reserved line, prohibit any operation. | AM3: Reserved line, prohibit any operation. | AN3: Reserved line, prohibit any operation. | AO3: Reserved line, prohibit any operation. | AP3: Reserved line, prohibit any operation. | AQ3: Reserved line, prohibit any operation. | AR3: Reserved line, prohibit any operation. | AS3: Reserved line, prohibit any operation. | AT3: Reserved line, prohibit any operation. | AU3: Reserved line, prohibit any operation. | AV3: Reserved line, prohibit any operation. | AW3: Reserved line, prohibit any operation. | AX3: Reserved line, prohibit any operation. | AY3: Reserved line, prohibit any operation. | AZ3: Reserved line, prohibit any operation. | BA3: Reserved line, prohibit any operation. | BB3: Reserved line, prohibit any operation. | BC3: Reserved line, prohibit any operation. | BD3: Reserved line, prohibit any operation. | BE3: Reserved line, prohibit any operation. | BF3: Reserved line, prohibit any operation. | BG3: Reserved line, prohibit any operation. | BH3: Reserved line, prohibit any operation. | BI3: Reserved line, prohibit any operation. | BJ3: Reserved line, prohibit any operation. | BK3: Reserved line, prohibit any operation. | BL3: Reserved line, prohibit any operation. | BM3: Reserved line, prohibit any operation. | BN3: Reserved line, prohibit any operation. | BO3: Reserved line, prohibit any operation. | BP3: Reserved line, prohibit any operation. | BQ3: Reserved line, prohibit any operation. | BR3: Reserved line, prohibit any operation. | BS3: Reserved line, prohibit any operation. | BT3: Reserved line, prohibit any operation. | BU3: Reserved line, prohibit any operation. | BV3: Reserved line, prohibit any operation. | BW3: Reserved line, prohibit any operation. | BX3: Reserved line, prohibit any operation. | BY3: Reserved line, prohibit any operation. | BZ3: Reserved line, prohibit any operation. | CA3: Reserved line, prohibit any operation. | CB3: Reserved line, prohibit any operation. | CC3: Reserved line, prohibit any operation. | CD3: Reserved line, prohibit any operation. | CE3: Reserved line, prohibit any operation. | CF3: Reserved line, prohibit any operation. | CG3: Reserved line, prohibit any operation. | CH3: Reserved line, prohibit any operation. | CI3: Reserved line, prohibit any operation. | CJ3: Reserved line, prohibit any operation. | CK3: Reserved line, prohibit any operation. | CL3: Reserved line, prohibit any operation. | CM3: Reserved line, prohibit any operation. | CN3: Reserved line, prohibit any operation. | CO3: Reserved line, prohibit any operation. | CP3: Reserved line, prohibit any operation. | CQ3: Reserved line, prohibit any operation. | CR3: Reserved line, prohibit any operation. | CS3: Reserved line, prohibit any operation. | CT3: Reserved line, prohibit any operation. | CU3: Reserved line, prohibit any operation. | CV3: Reserved line, prohibit any operation.
A4: t_0_Goods Id | B4: t_0_Sku Id | C4: t_0_Status | D4: t_0_Details | E4: t_1_Category | F4: t_1_Category Name | G4: t_1_Product type | H4: t_1_Customization processing technique | I4: t_1_Primary technique | J4: t_1_Secondary technique | K4: t_1_Secondary technique | L4: t_1_Product Name | M4: t_1_Contribution Goods | N4: t_1_Contribution SKU | O4: t_1_Update or Add | P4: t_1_Goods Id | Q4: t_1_Sku Id | R4: t_1_Brand | S4: t_1_Trademark | T4: t_2_Product Description | U4: t_2_Bullet Point | V4: t_2_Bullet Point | W4: t_2_Bullet Point | X4: t_2_Bullet Point | Y4: t_2_Bullet Point | Z4: t_2_Bullet Point | AA4: t_2_Detail Images URL | AB4: t_2_Detail Images URL | AC4: t_2_Detail Images URL | AD4: t_2_Detail Images URL | AE4: t_2_Detail Images URL | AF4: t_2_Detail Images URL | AG4: t_2_Detail Images URL | AH4: t_2_Detail Images URL | AI4: t_2_Detail Images URL | AJ4: t_2_Detail Images URL | AK4: t_2_Detail Images URL | AL4: t_2_Detail Images URL | AM4: t_2_Detail Images URL | AN4: t_2_Detail Images URL | AO4: t_2_Detail Images URL | AP4: t_2_Detail Images URL | AQ4: t_2_Detail Images URL | AR4: t_2_Detail Images URL | AS4: t_2_Detail Images URL | AT4: t_2_Detail Images URL | AU4: t_2_Detail Images URL | AV4: t_2_Detail Images URL | AW4: t_2_Detail Images URL | AX4: t_2_Detail Images URL | AY4: t_2_Detail Images URL | AZ4: t_2_Detail Images URL | BA4: t_2_Detail Images URL | BB4: t_2_Detail Images URL | BC4: t_2_Detail Images URL | BD4: t_2_Detail Images URL | BE4: t_2_Detail Images URL | BF4: t_2_Detail Images URL | BG4: t_2_Detail Images URL | BH4: t_2_Detail Images URL | BI4: t_2_Detail Images URL | BJ4: t_2_Detail Images URL | BK4: t_2_Detail Images URL | BL4: t_2_Detail Images URL | BM4: t_2_Detail Images URL | BN4: t_2_Detail Images URL | BO4: t_2_Detail Images URL | BP4: t_2_Detail Images URL | BQ4: t_2_Detail Images URL | BR4: t_2_Detail Images URL | BS4: t_2_Detail Images URL | BT4: t_2_Detail Images URL | BU4: t_2_Detail Images URL | BV4: t_2_Detail Images URL | BW4: t_2_Detail Images URL | BX4: t_2_Detail Images URL | BY4: t_2_Detail Images URL | BZ4: t_2_Detail Images URL | CA4: t_2_Detail Images URL | CB4: t_2_Detail Images URL | CC4: t_2_Detail Images URL | CD4: t_2_Detail Images URL | CE4: t_2_Detail Images URL | CF4: t_2_Detail Images URL | CG4: t_2_Detail Images URL | CH4: t_2_Detail Images URL | CI4: t_2_Detail Images URL | CJ4: t_2_Detail Images URL | CK4: t_2_Detail Images URL | CL4: t_2_Detail Images URL | CM4: t_2_Detail Images URL | CN4: t_2_Detail Images URL | CO4: t_2_Detail Images URL | CP4: t_2_Detail Images URL | CQ4: t_2_Detail Images URL | CR4: t_2_Detail Images URL | CS4: t_2_Detail Images URL | CT4: t_2_Detail Images URL | CU4: t_2_Detail Images URL | CV4: t_2_Detail Images URL | CW4: t_2_Detail Images URL | CX4: t_2_Detail Images URL | CY4: t_2_Detail Images URL | CZ4: t_2_Detail Images URL | DA4: t_2_Detail Images URL | DB4: t_2_Detail Images URL | DC4: t_2_Detail Images URL | DD4: t_2_Detail Images URL | DE4: t_2_Detail Images URL | DF4: t_2_Detail Images URL | DG4: t_2_Detail Images URL | DH4: t_2_Detail Images URL | DI4: t_2_Detail Images URL | DJ4: t_2_Detail Images URL | DK4: t_2_Detail Images URL | DL4: t_2_Detail Images URL | DM4: t_2_Detail Images URL | DN4: t_2_Detail Images URL | DO4: t_2_Detail Images URL | DP4: t_2_Detail Images URL | DQ4: t_2_Detail Images URL | DR4: t_2_Detail Video URL | DS4: t_3_Property:1259 | DT4: t_3_Property:1259 | DU4: t_3_Property:7964|1259 | DV4: t_3_Property:7550|1259:7964 | DW4: t_3_Property:1261 | DX4: t_3_Property:1261 | DY4: t_3_Property:1260 | DZ4: t_3_Property:1260 | EA4: t_3_Property:7965|1260 | EB4: t_3_Property:92 | EC4: t_3_Property:92 | ED4: t_3_Property:92 | EE4: t_3_Property:92 | EF4: t_3_Property:1264 | EG4: t_3_Property:1449 | EH4: t_3_Property:90 | EI4: t_3_Property:90 | EJ4: t_3_Property:90 | EK4: t_3_Property:19 | EL4: t_3_Property:19 | EM4: t_3_Property:19 | EN4: t_3_Property:143 | EO4: t_3_Property:143 | EP4: t_3_Property:143 | EQ4: t_3_Property:1093 | ER4: t_3_Property:1093 | ES4: t_3_Property:1093 | ET4: t_3_Property:76 | EU4: t_3_Property:76 | EV4: t_3_Property:76 | EW4: t_3_Property:115 | EX4: t_3_Property:115 | EY4: t_3_Property:115 | EZ4: t_3_Property:26 | FA4: t_3_Property:26 | FB4: t_3_Property:26 | FC4: t_3_Property:1101 | FD4: t_3_Property:1262 | FE4: t_3_Property:1262 | FF4: t_3_Property:1132 | FG4: t_3_Property:137 | FH4: t_3_Property:20 | FI4: t_3_Property:1919 | FJ4: t_3_Property:7963 | FK4: t_3_Property:7969|7963 | FL4: t_3_Property:7970|7963:7969 | FM4: t_3_Property:9154 | FN4: t_3_Property:9154 | FO4: t_3_Property:9154 | FP4: t_3_Property:7550|1259 | FQ4: t_3_Property:15:35385 | FR4: t_3_Property:15:35386 | FS4: t_3_Property:15:35387 | FT4: t_3_Property:15:35388 | FU4: t_3_Property:15:35390 | FV4: t_3_Property:15:35391 | FW4: t_3_Property:15:35392 | FX4: t_3_Property:15:35393 | FY4: t_3_Property:15:35394 | FZ4: t_3_Property:15:35395 | GA4: t_3_Property:15:35397 | GB4: t_3_Property:15:35398 | GC4: t_3_Property:15:35399 | GD4: t_3_Property:15:35400 | GE4: t_3_Property:15:35401 | GF4: t_3_Property:15:35403 | GG4: t_3_Property:15:35404 | GH4: t_3_Property:15:35405 | GI4: t_3_Property:15:35406 | GJ4: t_3_Property:15:35407 | GK4: t_3_Property:15:35408 | GL4: t_3_Property:15:35409 | GM4: t_3_Property:15:35410 | GN4: t_3_Property:15:35411 | GO4: t_3_Property:15:35415 | GP4: t_3_Property:15:35364 | GQ4: t_3_Property:15:1155 | GR4: t_3_Property:15:36254 | GS4: t_3_Property:15:965 | GT4: t_3_Property:12 | GU4: t_3_Property:7639:35392 | GV4: t_3_Property:7639:35393 | GW4: t_3_Property:7639:35394 | GX4: t_3_Property:7639:35395 | GY4: t_3_Property:7639:35397 | GZ4: t_3_Property:7639:35398 | HA4: t_3_Property:7639:35399 | HB4: t_3_Property:7639:35400 | HC4: t_3_Property:7639:35401 | HD4: t_3_Property:7639:35403 | HE4: t_3_Property:7639:35404 | HF4: t_3_Property:7639:35405 | HG4: t_3_Property:7639:35406 | HH4: t_3_Property:7639:35407 | HI4: t_3_Property:7639:35408 | HJ4: t_3_Property:7639:35409 | HK4: t_3_Property:7639:35410 | HL4: t_3_Property:7639:35411 | HM4: t_3_Property:7639:35412 | HN4: t_3_Property:7639:35413 | HO4: t_3_Property:7639:35414 | HP4: t_3_Property:7639:35415 | HQ4: t_3_Property:7639:36254 | HR4: t_3_Property:7639:98 | HS4: t_3_Property:7639:35364 | HT4: t_3_Property:7639:214835 | HU4: t_3_Property:7639:47217 | HV4: t_3_Property:7639:121 | HW4: t_3_Property:7639:35385 | HX4: t_3_Property:7639:35387 | HY4: t_3_Property:7639:35388 | HZ4: t_3_Property:7639:35390 | IA4: t_3_Property:7639:35391 | IB4: t_3_Property:82 | IC4: t_3_Property:83 | ID4: t_3_Property:75 | IE4: t_3_Property:1306 | IF4: t_3_Property:1192 | IG4: t_3_Property:6227 | IH4: t_3_Property:2103 | II4: t_3_Property:6926 | IJ4: t_3_Property:6930 - value|6926 | IK4: t_3_Property:6930 - unit|6926 | IL4: t_3_Property:6927 | IM4: t_3_Property:6931 - value|6927 | IN4: t_3_Property:6931 - unit|6927 | IO4: t_3_Property:6928 | IP4: t_3_Property:6934 - value|6928 | IQ4: t_3_Property:6934 - unit|6928 | IR4: t_3_Property:6547:35392 | IS4: t_3_Property:6547:35393 | IT4: t_3_Property:6547:35394 | IU4: t_3_Property:6547:35395 | IV4: t_3_Property:6547:35397 | IW4: t_3_Property:6547:35398 | IX4: t_3_Property:6547:35399 | IY4: t_3_Property:6547:35400 | IZ4: t_3_Property:6547:35401 | JA4: t_3_Property:6547:35403 | JB4: t_3_Property:6547:35404 | JC4: t_3_Property:6547:35405 | JD4: t_3_Property:6547:35406 | JE4: t_3_Property:6547:35407 | JF4: t_3_Property:6547:35408 | JG4: t_3_Property:6547:35409 | JH4: t_3_Property:6547:35410 | JI4: t_3_Property:6547:35411 | JJ4: t_3_Property:6547:35412 | JK4: t_3_Property:6547:35413 | JL4: t_3_Property:6547:35414 | JM4: t_3_Property:6547:35415 | JN4: t_3_Property:6547:36254 | JO4: t_3_Property:6547:35364 | JP4: t_3_Property:6547:47217 | JQ4: t_3_Property:6547:121 | JR4: t_3_Property:6547:35385 | JS4: t_3_Property:6547:35386 | JT4: t_3_Property:6547:35387 | JU4: t_3_Property:6547:35388 | JV4: t_3_Property:6547:35390 | JW4: t_3_Property:6547:35391 | JX4: t_3_Property:7654 | JY4: t_3_Property:7955 | JZ4: t_3_Property:84 | KA4: t_3_Property:203 | KB4: t_3_Property:6443 | KC4: t_3_Property:466 | KD4: t_3_Property:420 | KE4: t_3_Property:128 | KF4: t_4_Variation Theme | KG4: t_4_Size Family | KH4: t_4_Sub-Size Family | KI4: t_4_Size:3001 | KJ4: t_4_Sale Property:1001 | KK4: t_5_Size Chart Method | KL4: t_5_Size Chart Image | KM4: t_5_Unit | KN4: t_5_Size Chart Group:2 | KO4: t_5_Size Chart Element:13:Product:10013 | KP4: t_5_Size Chart Element:13:Product:10014 | KQ4: t_5_Size Chart Element:13:Product:10025 | KR4: t_5_Size Chart Element:13:Product:20033 | KS4: t_5_Size Chart Element:11:Product:10013 | KT4: t_5_Size Chart Element:11:Product:10014 | KU4: t_5_Size Chart Element:11:Product:10025 | KV4: t_5_Size Chart Element:11:Product:20033 | KW4: t_5_Size Chart Element:11:Product:33554443 | KX4: t_5_Size Chart Element:25:Product:10016 | KY4: t_5_Size Chart Element:25:Product:10017 | KZ4: t_5_Size Chart Element:25:Product:10018 | LA4: t_5_Size Chart Element:107:Product:10013 | LB4: t_5_Size Chart Element:107:Product:10014 | LC4: t_5_Size Chart Element:107:Product:10025 | LD4: t_5_Size Chart Element:107:Product:20033 | LE4: t_5_Size Chart Element:12:Product:10013 | LF4: t_5_Size Chart Element:12:Product:10014 | LG4: t_5_Size Chart Element:12:Product:10025 | LH4: t_5_Size Chart Element:12:Product:10032 | LI4: t_5_Size Chart Element:12:Product:10033 | LJ4: t_5_Size Chart Element:12:Product:10034 | LK4: t_5_Size Chart Element:12:Product:10035 | LL4: t_5_Size Chart Element:12:Product:10036 | LM4: t_5_Size Chart Element:12:Product:20033 | LN4: t_5_Size Chart Element:12:Product:33554443 | LO4: t_6_SKU Images URL | LP4: t_6_SKU Images URL | LQ4: t_6_SKU Images URL | LR4: t_6_SKU Images URL | LS4: t_6_SKU Images URL | LT4: t_6_SKU Images URL | LU4: t_6_SKU Images URL | LV4: t_6_SKU Images URL | LW4: t_6_SKU Images URL | LX4: t_6_SKU Images URL | LY4: t_6_Quantity | LZ4: t_6_Base Price - EUR | MA4: t_6_Reference Link | MB4: t_6_List Price - EUR | MC4: t_6_Not available for List price | MD4: t_6_Weight - g | ME4: t_6_Length - cm | MF4: t_6_Width - cm | MG4: t_6_Height - cm | MH4: t_6_SKU type | MI4: t_6_Individually packed | MJ4: t_6_Total packaging quantity | MK4: t_6_Packaging unit | ML4: t_6_Total item quantity | MM4: t_6_Item unit | MN4: t_6_Net content | MO4: t_6_Total net content | MP4: t_6_Net content unit | MQ4: t_6_External Product ID Type | MR4: t_6_External Product ID | MS4: t_7_Shipping Template | MT4: t_7_Handling Time | MU4: t_7_Fulfillment Channel | MV4: t_7_Item Tax Code | MW4: t_8_Country/Region of Origin | MX4: t_8_Province of Origin | MY4: t_8_SKU Packaging Information (with visible label) | MZ4: t_8_SKU Packaging Information (with visible label) | NA4: t_8_SKU Packaging Information (with visible label) | NB4: t_8_SKU Packaging Information (with visible label) | NC4: t_8_SKU Packaging Information (with visible label) | ND4: t_8_SKU Packaging Information (with visible label) | NE4: t_8_SKU Packaging Information (with visible label) | NF4: t_8_SKU Packaging Information (with visible label) | NG4: t_8_SKU Packaging Information (with visible label) | NH4: t_8_SKU Packaging Information (with visible label) | NI4: t_8_SKU Packaging Information (with visible label) | NJ4: t_8_SKU Packaging Information (with visible label) | NK4: t_8_SKU Packaging Information (with visible label) | NL4: t_8_SKU Packaging Information (with visible label) | NM4: t_8_SKU Packaging Information (with visible label) | NN4: t_8_SKU Packaging Information (with visible label) | NO4: t_8_SKU Packaging Information (with visible label) | NP4: t_8_SKU Packaging Information (with visible label) | NQ4: t_8_SKU Packaging Information (with visible label) | NR4: t_8_SKU Packaging Information (with visible label) | NS4: t_8_SKU Packaging Information (with visible label) | NT4: t_8_SKU Packaging Information (with visible label) | NU4: t_8_SKU Packaging Information (with visible label) | NV4: t_8_SKU Packaging Information (with visible label) | NW4: t_8_SKU Packaging Information (with visible label) | NX4: t_8_SKU Packaging Information (with visible label) | NY4: t_8_SKU Packaging Information (with visible label) | NZ4: t_8_SKU Packaging Information (with visible label) | OA4: t_8_SKU Packaging Information (with visible label) | OB4: t_8_SKU Packaging Information (with visible label) | OC4: t_8_SKU Packaging Information (with visible label) | OD4: t_8_SKU Packaging Information (with visible label) | OE4: t_8_SKU Packaging Information (with visible label) | OF4: t_8_SKU Packaging Information (with visible label) | OG4: t_8_SKU Packaging Information (with visible label) | OH4: t_8_SKU Packaging Information (with visible label) | OI4: t_8_SKU Packaging Information (with visible label) | OJ4: t_8_SKU Packaging Information (with visible label) | OK4: t_8_SKU Packaging Information (with visible label) | OL4: t_8_SKU Packaging Information (with visible label) | OM4: t_8_SKU Packaging Information (with visible label) | ON4: t_8_SKU Packaging Information (with visible label) | OO4: t_8_SKU Packaging Information (with visible label) | OP4: t_8_SKU Packaging Information (with visible label) | OQ4: t_8_SKU Packaging Information (with visible label) | OR4: t_8_Origin Label & Manufacturer Information | OS4: t_8_Origin Label & Manufacturer Information | OT4: t_8_Origin Label & Manufacturer Information | OU4: t_8_Origin Label & Manufacturer Information | OV4: t_8_Origin Label & Manufacturer Information | OW4: t_8_Governance Property:1100100115 | OX4: t_8_Governance Property:3 | OY4: t_8_Governance Property:2 | OZ4: t_8_Governance Property:1100100224
F5: =IFERROR(VLOOKUP(INDIRECT(ADDRESS(ROW(), COLUMN()-1)), 'Category Name'!$A:$B, 2, FALSE), "Please select the [category] first. After selecting, the full category path will be displayed here. Please do not modify the functions in the cells") -> 0
F6: =IFERROR(VLOOKUP(INDIRECT(ADDRESS(ROW(), COLUMN()-1)), 'Category Name'!$A:$B, 2, FALSE), "Please select the [category] first. After selecting, the full category path will be displayed here. Please do not modify the functions in the cells") -> 0
F7: =IFERROR(VLOOKUP(INDIRECT(ADDRESS(ROW(), COLUMN()-1)), 'Category Name'!$A:$B, 2, FALSE), "Please select the [category] first. After selecting, the full category path will be displayed here. Please do not modify the functions in the cells") -> 0
F8: =IFERROR(VLOOKUP(INDIRECT(ADDRESS(ROW(), COLUMN()-1)), 'Category Name'!$A:$B, 2, FALSE), "Please select the [category] first. After selecting, the full category path will be displayed here. Please do not modify the functions in the cells") -> 0
F9: =IFERROR(VLOOKUP(INDIRECT(ADDRESS(ROW(), COLUMN()-1)), 'Category Name'!$A:$B, 2, FALSE), "Please select the [category] first. After selecting, the full category path will be displayed here. Please do not modify the functions in the cells") -> 0
F10: =IFERROR(VLOOKUP(INDIRECT(ADDRESS(ROW(), COLUMN()-1)), 'Category Name'!$A:$B, 2, FALSE), "Please select the [category] first. After selecting, the full category path will be displayed here. Please do not modify the functions in the cells") -> 0
F11: =IFERROR(VLOOKUP(INDIRECT(ADDRESS(ROW(), COLUMN()-1)), 'Category Name'!$A:$B, 2, FALSE), "Please select the [category] first. After selecting, the full category path will be displayed here. Please do not modify the functions in the cells") -> 0
F12: =IFERROR(VLOOKUP(INDIRECT(ADDRESS(ROW(), COLUMN()-1)), 'Category Name'!$A:$B, 2, FALSE), "Please select the [category] first. After selecting, the full category path will be displayed here. Please do not modify the functions in the cells") -> 0
F13: =IFERROR(VLOOKUP(INDIRECT(ADDRESS(ROW(), COLUMN()-1)), 'Category Name'!$A:$B, 2, FALSE), "Please select the [category] first. After selecting, the full category path will be displayed here. Please do not modify the functions in the cells") -> 0
F14: =IFERROR(VLOOKUP(INDIRECT(ADDRESS(ROW(), COLUMN()-1)), 'Category Name'!$A:$B, 2, FALSE), "Please select the [category] first. After selecting, the full category path will be displayed here. Please do not modify the functions in the cells") -> 0
F15: =IFERROR(VLOOKUP(INDIRECT(ADDRESS(ROW(), COLUMN()-1)), 'Category Name'!$A:$B, 2, FALSE), "Please select the [category] first. After selecting, the full category path will be displayed here. Please do not modify the functions in the cells") -> 0
F16: =IFERROR(VLOOKUP(INDIRECT(ADDRESS(ROW(), COLUMN()-1)), 'Category Name'!$A:$B, 2, FALSE), "Please select the [category] first. After selecting, the full category path will be displayed here. Please do not modify the functions in the cells") -> 0
... F5000: =IFERROR(VLOOKUP(INDIRECT(ADDRESS(ROW(), COLUMN()-1)), 'Category Name'!$A:$B, 2, FALSE), "Please select the [category] first. After selecting, the full category path will be displayed here. Please do not modify the functions in the cells") -> 0

Sheet Dropdown Lists
A1: t_1_Category | B1: t_973431DD2C61366DBACC56E61E132E05 | C1: 26942 | D1: 26964 | E1: 29180 | F1: 29194 | G1: 29728 | H1: 29950 | I1: 30053 | J1: 30533 | K1: 30542 | L1: 30858 | M1: 30859 | N1: 30862 | O1: 39012 | P1: 54718 | Q1: 54722 | R1: 54726 | S1: 54835
A2: t_1_Product type | B2: t_CE9696B61FAB33F2B7AC38BD1A6904FE | C2: Normal product | D2: Custom product
A3: t_1_Custom product_Customization processing technique | B3: t_E596E04876A938D89430E31F12190EAE | C3: Single technique | D3: Combined techniques
A4: t_1_Custom product_Single technique_Primary technique | B4: t_210AC56516C831C3B975426026564B85 | C4: Basic technique | D4: Canvas/paper customization technique | E4: Organic material (e.g., acrylic/resin) customization technique | F4: Wood product customization technique | G4: Metal product customization technique | H4: Leather/fabric customization technique
A5: t_1_Custom product_Combined techniques_Primary technique | B5: t_5DB35C4529DB3F96BF4F53E1FEC22A97 | C5: Canvas/paper customization technique | D5: Organic material (e.g., acrylic/resin) customization technique | E5: Wood product customization technique | F5: Metal product customization technique | G5: Leather/fabric customization technique
A6: t_1_Custom product_Combined techniques_Metal product customization technique_Secondary technique | B6: t_5A2E371F897639048DDE5DABAB9B152C | C6: Laser engraving - text | D6: Laser engraving - images | E6: Mechanical engraving - text | F6: Debossing | G6: Welding | H6: UV | I6: Silk screen printing - text | J6: Silk screen printing - image | K6: Spray painting | L6: Soft enamel | M6: Laser cutting - text | N6: Laser cutting - image | O6: Rhinestone setting | P6: Electroplating
A7: t_1_Custom product_Single technique_Organic material (e.g., acrylic/resin) customization technique_Secondary technique | B7: t_6CC11CB0854138C9A2CAB6DC90AACA9A | C7: Laser engraving - text | D7: Laser engraving - images | E7: Mechanical engraving - text | F7: Debossing | G7: UV | H7: Silk screen printing - text | I7: Silk screen printing - image | J7: Laser cutting - text | K7: Laser cutting - image | L7: Hand-painted nail art
A8: t_1_Custom product_Single technique_Wood product customization technique_Secondary technique | B8: t_4BDCEE54E14C361091E3B7E7BC6BFA58 | C8: Laser engraving - text | D8: Laser engraving - images | E8: Mechanical engraving - text | F8: Debossing
A9: t_1_Custom product_Combined techniques_Organic material (e.g., acrylic/resin) customization technique_Secondary technique | B9: t_4E8EB62C344D3136894C37789B634AC8 | C9: Laser engraving - text | D9: Laser engraving - images | E9: Mechanical engraving - text | F9: Debossing | G9: UV | H9: Silk screen printing - text | I9: Silk screen printing - image | J9: Laser cutting - text | K9: Laser cutting - image
A10: t_1_Custom product_Single technique_Canvas/paper customization technique_Secondary technique | B10: t_B0B8A13405AC332B85C28D653BD74B34 | C10: Hand-painting - sketch | D10: Hand-painting - watercolor | E10: Hand-painting - oil painting | F10: Hand-painting - printmaking | G10: Hand-painting - comic | H10: Debossing
A11: t_1_Custom product_Single technique_Metal product customization technique_Secondary technique | B11: t_BA7DD3CAEAAF3F6C820F178068C1218E | C11: Laser engraving - text | D11: Laser engraving - images | E11: Mechanical engraving - text | F11: Debossing | G11: Welding | H11: Etching | I11: UV | J11: Silk screen printing - text | K11: Silk screen printing - image | L11: Spray painting | M11: Soft enamel | N11: Epoxy - text | O11: Epoxy - images | P11: Laser cutting - text | Q11: Laser cutting - image | R11: Rhinestone setting | S11: Electroplating
A12: t_1_Custom product_Combined techniques_Canvas/paper customization technique_Secondary technique | B12: t_4D36BB0BF9A633DDA10597E97D2DE70D | C12: Silk screen printing - text | D12: Silk screen printing - image | E12: Hot stamping - text | F12: Hot stamping - image | G12: Debossing
A13: t_1_Custom product_Combined techniques_Leather/fabric customization technique_Secondary technique | B13: t_B8ED491BA39F3348BAC02EDEAF8D3E6A | C13: Laser engraving - text | D13: Laser engraving - images | E13: UV | F13: Silk screen printing - text | G13: Silk screen printing - image | H13: Soft enamel | I13: Hot stamping - text | J13: Hot stamping - image | K13: Debossing
A14: t_1_Custom product_Single technique_Leather/fabric customization technique_Secondary technique | B14: t_82B46A7862C13CCC82AB8265B43CD5D1 | C14: Laser engraving - text | D14: Laser engraving - images | E14: UV | F14: Silk screen printing - text | G14: Silk screen printing - image | H14: Soft enamel | I14: Epoxy - text | J14: Epoxy - images | K14: Hot stamping - text | L14: Hot stamping - image | M14: Tin stamping | N14: Heat transfer printing - text | O14: Heat transfer printing - image | P14: Embroidery | Q14: Flocking | R14: Heat press printing - text | S14: Heat press printing - image | T14: Digital printing | U14: Debossing | V14: Woven pattern - adhesive patch
A15: t_1_Custom product_Combined techniques_Wood product customization technique_Secondary technique | B15: t_102B0F8B23393DE98AFB27DE3D742D48 | C15: Laser engraving - text | D15: Laser engraving - images | E15: Mechanical engraving - text | F15: Debossing
A16: t_1_Update or Add | B16: t_59D4DF059C473EBE9972B0D6D3C6BFD5 | C16: Update | D16: PartialUpdate | E16: Add
A17: t_1_Brand | B17: t_BCE822F8514631DFAA900D604C1FA3AD | C17: OSTROVIT
A18: t_1_OSTROVIT_Trademark | B18: t_4E2BBC766FB4340DA4F274AC6BC0E42A | C18: OstroVit
A19: t_3_39012_1259 - Upper Material | B19: t_FC32CA4BE4523AFA87DDD9FFB97F7808 | C19: PU | D19: PVC | E19: Leather | F19: First Layer Cow Suede | G19: Flannel | H19: Polyester Fiber (polyester)
A20: t_3_30858_1259 - Upper Material | B20: t_C085911E85C936C6BD19084938DB0495 | C20: PU | D20: EVA | E20: Fabric | F20: Nylon | G20: PVC | H20: Plastic | I20: Rubber | J20: Canvas | K20: Cow leather | L20: Split cow leather | M20: First Layer Cow Suede | N20: Two-layer Cow Suede | O20: Pig leather | P20: Sheep (sheep Suede) | Q20: ovine leather | R20: Pig split leather | S20: coated leather | T20: Microfiber coating materials
A21: t_3_30862_1259 - Upper Material | B21: t_94660DF92DF63DDEA8BF802328086FC7 | C21: PU | D21: EVA | E21: Fabric | F21: Nylon | G21: PVC | H21: Plastic | I21: Rubber | J21: Canvas | K21: Cow leather | L21: Split cow leather | M21: First Layer Cow Suede | N21: Two-layer Cow Suede | O21: Pig leather | P21: Sheep (sheep Suede) | Q21: ovine leather | R21: Pig split leather | S21: coated leather | T21: Microfiber coating materials
A22: t_3_29728_1259 - Upper Material | B22: t_73E6512CB46F348A83947FB39BCF752F | C22: PU | D22: EVA | E22: Fabric | F22: Nylon | G22: PVC | H22: Plastic | I22: Rubber | J22: Canvas | K22: Cow leather | L22: Split cow leather | M22: First Layer Cow Suede | N22: Two-layer Cow Suede | O22: Pig leather | P22: Sheep (sheep Suede) | Q22: ovine leather | R22: Pig split leather | S22: coated leather | T22: Microfiber coating materials
A23: t_3_29950_1259 - Upper Material | B23: t_C8870444BCC03E0F81602AC536FFB503 | C23: PU | D23: EVA | E23: Fabric | F23: Nylon | G23: PVC | H23: Plastic | I23: Rubber | J23: Canvas | K23: Cow leather | L23: Split cow leather | M23: First Layer Cow Suede | N23: Two-layer Cow Suede | O23: Pig leather | P23: Sheep (sheep Suede) | Q23: ovine leather | R23: Pig split leather | S23: coated leather | T23: Microfiber coating materials | U23: Cow suede leather | V23: Cow split suede leather | W23: Pig suede leather | X23: Pig split suede leather | Y23: Sheep suede leather
A24: t_3_29180_1259 - Upper Material | B24: t_F76924BDB46A359E806CC3D9D6088934 | C24: EVA | D24: Fabric | E24: Flax | F24: PVC | G24: Plastic | H24: Rubber | I24: Canvas | J24: Denim | K24: PP (polypropylene) | L24: Cow leather | M24: Split cow leather | N24: ovine leather | O24: Genuine shearling | P24: Tanned Rabbit Pelt | Q24: Wool | R24: Rabbit hair | S24: Pig leather | T24: Pig split leather | U24: Non-woven Fabric | V24: Polyurethane coating materials | W24: Polyvinyl chloride coating materials | X24: Microfiber coating materials | Y24: TPU | Z24: coating materials | AA24: Polyurethane Foam | AB24: Flannel | AC24: leather | AD24: Split Leather | AE24: leather | AF24: Tanned Horse Pelt | AG24: Superfine Fiber | AH24: Cow suede leather | AI24: Cow split suede leather | AJ24: Pig suede leather | AK24: Pig split suede leather | AL24: Sheep suede leather
A25: t_3_30542_1259 - Upper Material | B25: t_26E3C87B829339BE8536D2D39B5C0888 | C25: PU | D25: EVA | E25: Fabric | F25: Nylon | G25: PVC | H25: Plastic | I25: Rubber | J25: Canvas | K25: Cow leather | L25: Split cow leather | M25: First Layer Cow Suede | N25: Two-layer Cow Suede | O25: Pig leather | P25: Sheep (sheep Suede) | Q25: ovine leather | R25: Pig split leather | S25: coated leather | T25: Microfiber coating materials | U25: Polyolefin Elastomers | V25: Cow suede leather | W25: Cow split suede leather | X25: Pig suede leather | Y25: Pig split suede leather | Z25: Sheep suede leather | AA25: TPU
A26: t_3_30053_1259 - Upper Material | B26: t_7EF3CCB8B63637A7A601CBF4D95C11D1 | C26: PU | D26: EVA | E26: Fabric | F26: Nylon | G26: PVC | H26: Plastic | I26: Rubber | J26: Canvas | K26: Cow leather | L26: Split cow leather | M26: First Layer Cow Suede | N26: Two-layer Cow Suede | O26: Pig leather | P26: Sheep (sheep Suede) | Q26: ovine leather | R26: Pig split leather | S26: coated leather | T26: Microfiber coating materials | U26: Cow suede leather | V26: Cow split suede leather | W26: Pig suede leather | X26: Pig split suede leather | Y26: Sheep suede leather
A27: t_3_54835_1259 - Upper Material | B27: t_AB465CBD00B53EAB84E00C94A08B5DEA | C27: EVA | D27: Fabric | E27: Flax | F27: PVC | G27: Plastic | H27: Rubber | I27: Canvas | J27: Denim | K27: PP (polypropylene) | L27: Cow leather | M27: Split cow leather | N27: ovine leather | O27: Genuine shearling | P27: Tanned Rabbit Pelt | Q27: Wool | R27: Rabbit hair | S27: Pig leather | T27: Pig split leather | U27: Non-woven Fabric | V27: Polyurethane coating materials | W27: Polyvinyl chloride coating materials | X27: Microfiber coating materials | Y27: TPU | Z27: coating materials | AA27: Polyurethane Foam | AB27: Flannel | AC27: leather | AD27: Split Leather | AE27: leather | AF27: Tanned Horse Pelt | AG27: Superfine Fiber | AH27: Cow suede leather | AI27: Cow split suede leather | AJ27: Pig suede leather | AK27: Pig split suede leather | AL27: Sheep suede leather
A28: t_3_54726_1259 - Upper Material | B28: t_D3C5568F8E863690832B5922067B68BD | C28: EVA | D28: Fabric | E28: Flax | F28: PVC | G28: Plastic | H28: Rubber | I28: Canvas | J28: Denim | K28: PP (polypropylene) | L28: Cow leather | M28: Split cow leather | N28: ovine leather | O28: Genuine shearling | P28: Tanned Rabbit Pelt | Q28: Wool | R28: Rabbit hair | S28: Pig leather | T28: Pig split leather | U28: Non-woven Fabric | V28: Polyurethane coating materials | W28: Polyvinyl chloride coating materials | X28: Microfiber coating materials | Y28: TPU | Z28: coating materials | AA28: Polyurethane Foam | AB28: Flannel | AC28: leather | AD28: Split Leather | AE28: leather | AF28: Vine Grass | AG28: Tanned Horse Pelt | AH28: Superfine Fiber | AI28: Cow suede leather | AJ28: Cow split suede leather | AK28: Pig suede leather | AL28: Pig split suede leather | AM28: Sheep suede leather
A29: t_3_54722_1259 - Upper Material | B29: t_CFCAAD4DFABC30AEAFB900B42A679B7C | C29: PU | D29: EVA | E29: Fabric | F29: Nylon | G29: PVC | H29: Plastic | I29: Rubber | J29: Canvas | K29: Cow leather | L29: Split cow leather | M29: First Layer Cow Suede | N29: Two-layer Cow Suede | O29: Pig leather | P29: Sheep (sheep Suede) | Q29: ovine leather | R29: Pig split leather | S29: coated leather | T29: Microfiber coating materials | U29: Polyolefin Elastomers | V29: Cow suede leather | W29: Cow split suede leather | X29: Pig suede leather | Y29: Pig split suede leather | Z29: Sheep suede leather
A30: t_3_26942_1259 - Upper Material | B30: t_DB9F6C5F247E3B5BBFF538B0768DAB78 | C30: PU | D30: EVA | E30: Fabric | F30: Nylon | G30: PVC | H30: Plastic | I30: Rubber | J30: Canvas | K30: Cow leather | L30: Split cow leather | M30: First Layer Cow Suede | N30: Two-layer Cow Suede | O30: Pig leather | P30: Sheep (sheep Suede) | Q30: ovine leather | R30: Pig split leather | S30: coated leather | T30: Microfiber coating materials | U30: Cow suede leather | V30: Cow split suede leather | W30: Pig suede leather | X30: Pig split suede leather | Y30: Sheep suede leather
A31: t_3_54718_1259 - Upper Material | B31: t_AA8D9890C22B3144A1B285F31A98A592 | C31: PU | D31: EVA | E31: Fabric | F31: Nylon | G31: PVC | H31: Plastic | I31: Rubber | J31: Canvas | K31: Cow leather | L31: Split cow leather | M31: First Layer Cow Suede | N31: Two-layer Cow Suede | O31: Pig leather | P31: Sheep (sheep Suede) | Q31: ovine leather | R31: Pig split leather | S31: coated leather | T31: Microfiber coating materials | U31: PE (polyethylene) | V31: Silicone | W31: TPU | X31: Flax | Y31: PP (polypropylene) | Z31: Polyurethane coating materials | AA31: Polyvinyl chloride coating materials | AB31: Microfiber coating materials | AC31: Polyurethane Foam | AD31: Vine Grass | AE31: Cow suede leather | AF31: Cow split suede leather | AG31: Pig suede leather | AH31: Pig split suede leather | AI31: Sheep suede leather
A32: t_3_30859_1259 - Upper Material | B32: t_1F78D7F4F84730749F0793B28E15DC40 | C32: PU | D32: EVA | E32: Fabric | F32: Nylon | G32: PVC | H32: Plastic | I32: Rubber | J32: Canvas | K32: Cow leather | L32: Split cow leather | M32: First Layer Cow Suede | N32: Two-layer Cow Suede | O32: Pig leather | P32: Sheep (sheep Suede) | Q32: ovine leather | R32: Pig split leather | S32: coated leather | T32: Microfiber coating materials
A33: t_3_30533_1259 - Upper Material | B33: t_164E2C004CFD34F692F316843ED05685 | C33: PU | D33: EVA | E33: Fabric | F33: Nylon | G33: PVC | H33: Plastic | I33: Rubber | J33: Canvas | K33: Cow leather | L33: Split cow leather | M33: First Layer Cow Suede | N33: Two-layer Cow Suede | O33: Pig leather | P33: Sheep (sheep Suede) | Q33: ovine leather | R33: Pig split leather | S33: coated leather | T33: Microfiber coating materials | U33: PE (polyethylene) | V33: Silicone | W33: TPU | X33: Flax | Y33: PP (polypropylene) | Z33: Polyurethane coating materials | AA33: Polyvinyl chloride coating materials | AB33: Microfiber coating materials | AC33: Polyurethane Foam | AD33: Vine Grass | AE33: Cow suede leather | AF33: Cow split suede leather | AG33: Pig suede leather | AH33: Pig split suede leather | AI33: Sheep suede leather
A34: t_3_29194_1259 - Upper Material | B34: t_2E9EA565169F3AAFA61C54E852739B92 | C34: EVA | D34: Fabric | E34: Flax | F34: PVC | G34: Plastic | H34: Rubber | I34: Canvas | J34: Denim | K34: PP (polypropylene) | L34: Cow leather | M34: Split cow leather | N34: ovine leather | O34: Genuine shearling | P34: Tanned Rabbit Pelt | Q34: Wool | R34: Rabbit hair | S34: Pig leather | T34: Pig split leather | U34: Non-woven Fabric | V34: Polyurethane coating materials | W34: Polyvinyl chloride coating materials | X34: Microfiber coating materials | Y34: TPU | Z34: coating materials | AA34: Polyurethane Foam | AB34: Flannel | AC34: leather | AD34: Split Leather | AE34: leather | AF34: Vine Grass | AG34: Tanned Horse Pelt | AH34: Superfine Fiber | AI34: Cow suede leather | AJ34: Cow split suede leather | AK34: Pig suede leather | AL34: Pig split suede leather | AM34: Sheep suede leather
A35: t_3_26964_1259 - Upper Material | B35: t_2F1C8F4BA36D3317B8A60F8F04E34E81 | C35: PU | D35: EVA | E35: Fabric | F35: Nylon | G35: PVC | H35: Plastic | I35: Rubber | J35: Canvas | K35: Cow leather | L35: Split cow leather | M35: First Layer Cow Suede | N35: Two-layer Cow Suede | O35: Pig leather | P35: Sheep (sheep Suede) | Q35: ovine leather | R35: Pig split leather | S35: coated leather | T35: Microfiber coating materials | U35: Cow suede leather | V35: Cow split suede leather | W35: Pig suede leather | X35: Pig split suede leather | Y35: Sheep suede leather
A36: t_3_7964 - Mesh Types of Fabric | B36: t_F21A47916C653886B5F7633E0C76CC00 | C36: Double-Layer Mesh | D36: No Mesh | E36: Single-Layer Mesh
A37: t_3_7550 - Fabric Material Composition | B37: t_DA1B0BA69BFB3BF69586BF4ED975D7AD | C37: Plant Fibres | D37: Man-made Fibers | E37: Animal Fine Hair
A38: t_3_26964_1261 - Sole Material | B38: t_96B6F55C541D3B82B4149970D9A046FE | C38: PU | D38: PVC | E38: Rubber | F38: EVA | G38: MD | H38: TPU | I38: TPR | J38: PHYLON | K38: Fabric | L38: Cow leather | M38: Cow split leather | N38: Cow suede leather | O38: Cow split suede leather | P38: Pig suede leather | Q38: Pig split suede leather | R38: Sheep suede leather
A39: t_3_29950_1261 - Sole Material | B39: t_1A68E0AEE23C30F9BFEF78A191852BDE | C39: PU | D39: PVC | E39: Rubber | F39: EVA | G39: MD | H39: TPU | I39: TPR | J39: PHYLON | K39: Fabric | L39: Cow leather | M39: Cow split leather | N39: Cow suede leather | O39: Cow split suede leather | P39: Pig suede leather | Q39: Pig split suede leather | R39: Sheep suede leather
A40: t_3_29728_1261 - Sole Material | B40: t_5EDF549B7C5A3BAC9E1416871DC2FDAF | C40: PU | D40: PVC | E40: Rubber | F40: EVA | G40: MD | H40: TPU | I40: TPR | J40: PHYLON | K40: Fabric | L40: Cow leather | M40: Cow split leather
A41: t_3_30858_1261 - Sole Material | B41: t_F89DD745747D3D5EB9B38DAB834260A9 | C41: PU | D41: PVC | E41: Rubber | F41: EVA | G41: MD | H41: TPU | I41: TPR | J41: PHYLON | K41: Fabric | L41: Cow leather | M41: Cow split leather
A42: t_3_54722_1261 - Sole Material | B42: t_95B334C7F57D3368AD089F0AE00AD0BA | C42: PU | D42: PVC | E42: Rubber | F42: EVA | G42: MD | H42: TPU | I42: TPR | J42: PHYLON | K42: Fabric | L42: Cow leather | M42: Cow split leather | N42: Polyolefin Elastomers | O42: Cow suede leather | P42: Cow split suede leather | Q42: Pig suede leather | R42: Pig split suede leather | S42: Sheep suede leather
A43: t_3_54835_1261 - Sole Material | B43: t_8C5BD9C9DBF23D6D8E539580040DA10C | C43: PU | D43: PVC | E43: Rubber | F43: EVA | G43: MD | H43: TPU | I43: TPR | J43: PHYLON | K43: Fabric | L43: Flax | M43: leather | N43: PP (polypropylene) | O43: Cow leather | P43: Cow split leather | Q43: Plastic | R43: Polyurethane coating materials | S43: Polyvinyl chloride coating materials | T43: Microfiber coating materials | U43: TR | V43: Canvas | W43: Non-woven Fabric | X43: ovine leather | Y43: Pig leather | Z43: Pig split leather | AA43: leather | AB43: Split Leather | AC43: Wood | AD43: Pig split suede leather | AE43: Pig suede leather | AF43: Cow suede leather | AG43: Sheep suede leather | AH43: Cow split suede leather
A44: t_3_26942_1261 - Sole Material | B44: t_D497537DA1F13695BD79B47E62B33DA2 | C44: PU | D44: PVC | E44: Rubber | F44: EVA | G44: MD | H44: TPU | I44: TPR | J44: PHYLON | K44: Fabric | L44: Cow leather | M44: Cow split leather | N44: Cow suede leather | O44: Cow split suede leather | P44: Pig suede leather | Q44: Pig split suede leather | R44: Sheep suede leather
A45: t_3_30533_1261 - Sole Material | B45: t_4D79DF73E5C93EEB8A7925BF6E60384D | C45: PU | D45: PVC | E45: Rubber | F45: EVA | G45: MD | H45: TPU | I45: TPR | J45: PHYLON | K45: Fabric | L45: Cow leather | M45: Cow split leather | N45: PE (polyethylene) | O45: Silicone | P45: Flax | Q45: PP (polypropylene) | R45: Plastic | S45: Polyurethane coating materials | T45: Polyvinyl chloride coating materials | U45: Microfiber coating materials | V45: TR | W45: Wood | X45: Vine Grass | Y45: Cow suede leather | Z45: Cow split suede leather | AA45: Pig suede leather | AB45: Pig split suede leather | AC45: Sheep suede leather
A46: t_3_30053_1261 - Sole Material | B46: t_4CFE4A5C24343316925FE6F113EAF0DA | C46: PU | D46: PVC | E46: Rubber | F46: EVA | G46: MD | H46: TPU | I46: TPR | J46: PHYLON | K46: Fabric | L46: Cow leather | M46: Cow split leather | N46: Cow suede leather | O46: Cow split suede leather | P46: Pig suede leather | Q46: Pig split suede leather | R46: Sheep suede leather
A47: t_3_30859_1261 - Sole Material | B47: t_9C9B8F8D92673BCFA86B74DABFA9D856 | C47: PU | D47: PVC | E47: Rubber | F47: EVA | G47: MD | H47: TPU | I47: TPR | J47: PHYLON | K47: Fabric | L47: Cow leather | M47: Cow split leather
A48: t_3_30862_1261 - Sole Material | B48: t_1DBC9E8133AF3C05946B29B34A4C48D0 | C48: PU | D48: PVC | E48: Rubber | F48: EVA | G48: MD | H48: TPU | I48: TPR | J48: PHYLON | K48: Fabric | L48: Cow leather | M48: Cow split leather
A49: t_3_29194_1261 - Sole Material | B49: t_FB0FDA8FA83B38899957AE743B80676D | C49: PU | D49: PVC | E49: Rubber | F49: EVA | G49: MD | H49: TPU | I49: TPR | J49: PHYLON | K49: Fabric | L49: Flax | M49: leather | N49: PP (polypropylene) | O49: Cow leather | P49: Cow split leather | Q49: Plastic | R49: Polyurethane coating materials | S49: Polyvinyl chloride coating materials | T49: Microfiber coating materials | U49: TR | V49: Canvas | W49: Non-woven Fabric | X49: ovine leather | Y49: Pig leather | Z49: Pig split leather | AA49: leather | AB49: Split Leather | AC49: Wood | AD49: Vine Grass | AE49: Pig split suede leather | AF49: Pig suede leather | AG49: Cow suede leather | AH49: Sheep suede leather | AI49: Cow split suede leather
A50: t_3_54718_1261 - Sole Material | B50: t_10AA201A7F9C369D904AC4FDF2E5F638 | C50: PU | D50: PVC | E50: Rubber | F50: EVA | G50: MD | H50: TPU | I50: TPR | J50: PHYLON | K50: Fabric | L50: Cow leather | M50: Cow split leather | N50: PE (polyethylene) | O50: Silicone | P50: Flax | Q50: PP (polypropylene) | R50: Plastic | S50: Polyurethane coating materials | T50: Polyvinyl chloride coating materials | U50: Microfiber coating materials | V50: TR | W50: Wood | X50: Vine Grass | Y50: Cow suede leather | Z50: Cow split suede leather | AA50: Pig suede leather | AB50: Pig split suede leather | AC50: Sheep suede leather
A51: t_3_54726_1261 - Sole Material | B51: t_E6899D1116443FB6936F2B4F5F9BC1AC | C51: PU | D51: PVC | E51: Rubber | F51: EVA | G51: MD | H51: TPU | I51: TPR | J51: PHYLON | K51: Fabric | L51: Flax | M51: leather | N51: PP (polypropylene) | O51: Cow leather | P51: Cow split leather | Q51: Plastic | R51: Polyurethane coating materials | S51: Polyvinyl chloride coating materials | T51: Microfiber coating materials | U51: TR | V51: Canvas | W51: Non-woven Fabric | X51: ovine leather | Y51: Pig leather | Z51: Pig split leather | AA51: leather | AB51: Split Leather | AC51: Wood | AD51: Vine Grass | AE51: Pig split suede leather | AF51: Pig suede leather | AG51: Cow suede leather | AH51: Sheep suede leather | AI51: Cow split suede leather
A52: t_3_30542_1261 - Sole Material | B52: t_4F97159A8B4D3DD0BD09A071FCD98B18 | C52: PU | D52: PVC | E52: Rubber | F52: EVA | G52: MD | H52: TPU | I52: TPR | J52: PHYLON | K52: Fabric | L52: Cow leather | M52: Cow split leather | N52: Polyolefin Elastomers | O52: Cow suede leather | P52: Cow split suede leather | Q52: Pig suede leather | R52: Pig split suede leather | S52: Sheep suede leather
A53: t_3_39012_1261 - Sole Material | B53: t_53B44E93E11B304895EDFEA6F3AF1904 | C53: PU | D53: PVC | E53: Rubber | F53: EVA | G53: TPU | H53: Polyvinyl chloride coating materials | I53: Silicone | J53: Polyester
A54: t_3_29180_1261 - Sole Material | B54: t_962B956138A734B78A21651BBEA7EFD1 | C54: PU | D54: PVC | E54: Rubber | F54: EVA | G54: MD | H54: TPU | I54: TPR | J54: PHYLON | K54: Fabric | L54: Flax | M54: leather | N54: PP (polypropylene) | O54: Cow leather | P54: Cow split leather | Q54: Plastic | R54: Polyurethane coating materials | S54: Polyvinyl chloride coating materials | T54: Microfiber coating materials | U54: TR | V54: Canvas | W54: Non-woven Fabric | X54: ovine leather | Y54: Pig leather | Z54: Pig split leather | AA54: leather | AB54: Split Leather | AC54: Wood | AD54: Pig split suede leather | AE54: Pig suede leather | AF54: Cow suede leather | AG54: Sheep suede leather | AH54: Cow split suede leather
A55: t_3_30862_1260 - Inner Material | B55: t_AF5EFC01161B3C7DB5C210293259F858 | C55: PVC | D55: PU | E55: Fabric | F55: EVA | G55: Cow leather | H55: Cow split leather | I55: ovine leather | J55: Microfiber coating materials | K55: Pig split leather | L55: Pig leather | M55: Rubber
A56: t_3_30858_1260 - Inner Material | B56: t_D675724A16653158972AB5FA2AB7D672 | C56: PVC | D56: PU | E56: Fabric | F56: EVA | G56: Cow leather | H56: Cow split leather | I56: ovine leather | J56: Microfiber coating materials | K56: Pig split leather | L56: Pig leather | M56: Rubber
A57: t_3_26964_1260 - Inner Material | B57: t_1A45D7239F783D2199C0A85AA469EA8B | C57: PVC | D57: PU | E57: Fabric | F57: EVA | G57: Cow leather | H57: Cow split leather | I57: ovine leather | J57: Microfiber coating materials | K57: Pig split leather | L57: Pig leather | M57: Rubber | N57: Cow suede leather | O57: Cow split suede leather | P57: Pig suede leather | Q57: Pig split suede leather | R57: Sheep suede leather
A58: t_3_29950_1260 - Inner Material | B58: t_14F0E574DE5F33B8841AA0C3A025C18B | C58: PVC | D58: PU | E58: Fabric | F58: EVA | G58: Cow leather | H58: Cow split leather | I58: ovine leather | J58: Microfiber coating materials | K58: Pig split leather | L58: Pig leather | M58: Rubber | N58: Cow suede leather | O58: Cow split suede leather | P58: Pig suede leather | Q58: Pig split suede leather | R58: Sheep suede leather
A59: t_3_30533_1260 - Inner Material | B59: t_0840E90374183A469D364E5B1077E4F9 | C59: PVC | D59: PU | E59: Fabric | F59: EVA | G59: Cow leather | H59: Cow split leather | I59: ovine leather | J59: Microfiber coating materials | K59: Pig split leather | L59: Pig leather | M59: Rubber | N59: PE (polyethylene) | O59: Wool | P59: TPU | Q59: Flax | R59: Polyurethane coating materials | S59: Polyvinyl chloride coating materials | T59: Microfiber coating materials | U59: Plastic | V59: PP (polypropylene) | W59: Polyurethane Foam | X59: ovine leather | Y59: Vine Grass | Z59: Cow suede leather | AA59: Cow split suede leather | AB59: Pig suede leather | AC59: Pig split suede leather | AD59: Sheep suede leather
A60: t_3_29194_1260 - Inner Material | B60: t_8B8C178010303A41AB4AE679DA70F99B | C60: PVC | D60: Flax | E60: Canvas | F60: Fabric | G60: Denim | H60: EVA | I60: Mesh | J60: Cow leather | K60: Cow split leather | L60: Pig split leather | M60: Pig leather | N60: Rubber | O60: coating materials | P60: Polyurethane coating materials | Q60: Polyvinyl chloride coating materials | R60: Microfiber coating materials | S60: Plastic | T60: PP (polypropylene) | U60: Polyurethane Foam | V60: TPU | W60: Corduroy | X60: Flannel | Y60: Non-woven Fabric | Z60: ovine leather | AA60: Rabbit hair | AB60: Tanned Rabbit Pelt | AC60: Wool | AD60: Genuine shearling | AE60: leather | AF60: Split Leather | AG60: leather | AH60: Vine Grass | AI60: Superfine Fiber | AJ60: Pig suede leather | AK60: Cow split suede leather | AL60: Sheep suede leather | AM60: Pig split suede leather | AN60: Cow suede leather
A61: t_3_54726_1260 - Inner Material | B61: t_EEB04CE295373D96A6D4EBFC8F3AA726 | C61: PVC | D61: Flax | E61: Canvas | F61: Fabric | G61: Denim | H61: EVA | I61: Mesh | J61: Cow leather | K61: Cow split leather | L61: Pig split leather | M61: Pig leather | N61: Rubber | O61: coating materials | P61: Polyurethane coating materials | Q61: Polyvinyl chloride coating materials | R61: Microfiber coating materials | S61: Plastic | T61: PP (polypropylene) | U61: Polyurethane Foam | V61: TPU | W61: Corduroy | X61: Flannel | Y61: Non-woven Fabric | Z61: ovine leather | AA61: Rabbit hair | AB61: Tanned Rabbit Pelt | AC61: Wool | AD61: Genuine shearling | AE61: leather | AF61: Split Leather | AG61: leather | AH61: Vine Grass | AI61: Superfine Fiber | AJ61: Pig suede leather | AK61: Cow split suede leather | AL61: Sheep suede leather | AM61: Pig split suede leather | AN61: Cow suede leather
A62: t_3_54835_1260 - Inner Material | B62: t_5852D6CFCE253B4888BD1004470F93A2 | C62: PVC | D62: Flax | E62: Canvas | F62: Fabric | G62: Denim | H62: EVA | I62: Mesh | J62: Cow leather | K62: Cow split leather | L62: Pig split leather | M62: Pig leather | N62: Rubber | O62: coating materials | P62: Polyurethane coating materials | Q62: Polyvinyl chloride coating materials | R62: Microfiber coating materials | S62: Plastic | T62: PP (polypropylene) | U62: Polyurethane Foam | V62: TPU | W62: Corduroy | X62: Flannel | Y62: Non-woven Fabric | Z62: ovine leather | AA62: Rabbit hair | AB62: Tanned Rabbit Pelt | AC62: Wool | AD62: Genuine shearling | AE62: leather | AF62: Split Leather | AG62: leather | AH62: Superfine Fiber | AI62: Pig suede leather | AJ62: Cow split suede leather | AK62: Sheep suede leather | AL62: Pig split suede leather | AM62: Cow suede leather
A63: t_3_54718_1260 - Inner Material | B63: t_7A13EC9B859B30C39538D7E6B50CBA44 | C63: PVC | D63: PU | E63: Fabric | F63: EVA | G63: Cow leather | H63: Cow split leather | I63: ovine leather | J63: Microfiber coating materials | K63: Pig split leather | L63: Pig leather | M63: Rubber | N63: PE (polyethylene) | O63: Wool | P63: TPU | Q63: Flax | R63: Polyurethane coating materials | S63: Polyvinyl chloride coating materials | T63: Microfiber coating materials | U63: Plastic | V63: PP (polypropylene) | W63: Polyurethane Foam | X63: ovine leather | Y63: Vine Grass | Z63: Cow suede leather | AA63: Cow split suede leather | AB63: Pig suede leather | AC63: Pig split suede leather | AD63: Sheep suede leather
A64: t_3_54722_1260 - Inner Material | B64: t_617601F726E83D6E9C3B563129E8D137 | C64: PVC | D64: PU | E64: Fabric | F64: EVA | G64: Cow leather | H64: Cow split leather | I64: ovine leather | J64: Microfiber coating materials | K64: Pig split leather | L64: Pig leather | M64: Rubber | N64: Cow suede leather | O64: Cow split suede leather | P64: Pig suede leather | Q64: Pig split suede leather | R64: Sheep suede leather
A65: t_3_30859_1260 - Inner Material | B65: t_64E269C152B232F99D679F781BCC3473 | C65: PVC | D65: PU | E65: Fabric | F65: EVA | G65: Cow leather | H65: Cow split leather | I65: ovine leather | J65: Microfiber coating materials | K65: Pig split leather | L65: Pig leather | M65: Rubber
A66: t_3_29728_1260 - Inner Material | B66: t_80A3EC632C9734FA97949D19C0532C8E | C66: PVC | D66: PU | E66: Fabric | F66: EVA | G66: Cow leather | H66: Cow split leather | I66: ovine leather | J66: Microfiber coating materials | K66: Pig split leather | L66: Pig leather | M66: Rubber
A67: t_3_29180_1260 - Inner Material | B67: t_734735D1A9483E1E98690C2C801DB449 | C67: PVC | D67: Flax | E67: Canvas | F67: Fabric | G67: Denim | H67: EVA | I67: Mesh | J67: Cow leather | K67: Cow split leather | L67: Pig split leather | M67: Pig leather | N67: Rubber | O67: coating materials | P67: Polyurethane coating materials | Q67: Polyvinyl chloride coating materials | R67: Microfiber coating materials | S67: Plastic | T67: PP (polypropylene) | U67: Polyurethane Foam | V67: TPU | W67: Corduroy | X67: Flannel | Y67: Non-woven Fabric | Z67: ovine leather | AA67: Rabbit hair | AB67: Tanned Rabbit Pelt | AC67: Wool | AD67: Genuine shearling | AE67: leather | AF67: Split Leather | AG67: leather | AH67: Superfine Fiber | AI67: Pig suede leather | AJ67: Cow split suede leather | AK67: Sheep suede leather | AL67: Pig split suede leather | AM67: Cow suede leather
A68: t_3_26942_1260 - Inner Material | B68: t_2B8FC9B7C78531ED8217A4DCA7D71EA7 | C68: PVC | D68: PU | E68: Fabric | F68: EVA | G68: Cow leather | H68: Cow split leather | I68: ovine leather | J68: Microfiber coating materials | K68: Pig split leather | L68: Pig leather | M68: Rubber | N68: Cow suede leather | O68: Cow split suede leather | P68: Pig suede leather | Q68: Pig split suede leather | R68: Sheep suede leather
A69: t_3_30053_1260 - Inner Material | B69: t_5FC8E3D420453BD696496CBC82B889ED | C69: PVC | D69: PU | E69: Fabric | F69: EVA | G69: Cow leather | H69: Cow split leather | I69: ovine leather | J69: Microfiber coating materials | K69: Pig split leather | L69: Pig leather | M69: Rubber | N69: Cow suede leather | O69: Cow split suede leather | P69: Pig suede leather | Q69: Pig split suede leather | R69: Sheep suede leather
A70: t_3_30542_1260 - Inner Material | B70: t_35B537F806153E66A2C56C8926FEDE5A | C70: PVC | D70: PU | E70: Fabric | F70: EVA | G70: Cow leather | H70: Cow split leather | I70: ovine leather | J70: Microfiber coating materials | K70: Pig split leather | L70: Pig leather | M70: Rubber | N70: Cow suede leather | O70: Cow split suede leather | P70: Pig suede leather | Q70: Pig split suede leather | R70: Sheep suede leather | S70: TPU
A71: t_3_30858_7965 - Lining Fabric Type | B71: t_285A6BF371913B29B74549788073FB1C | C71: Fabric Lining | D71: Short-Pile Lining | E71: Regular-Pile Lining | F71: Long-Pile Lining
A72: t_3_30859_7965 - Lining Fabric Type | B72: t_8FA0969E4D1835C4BB85CC0907353B45 | C72: Fabric Lining | D72: Short-Pile Lining | E72: Regular-Pile Lining | F72: Long-Pile Lining
A73: t_3_30862_7965 - Lining Fabric Type | B73: t_D1C2856E56A93687B6BAA2C290AEB511 | C73: Fabric Lining | D73: Short-Pile Lining | E73: Regular-Pile Lining | F73: Long-Pile Lining
A74: t_3_30053_7965 - Lining Fabric Type | B74: t_52C8C80827BE34C29190260DC30E3E20 | C74: Fabric Lining | D74: Short-Pile Lining | E74: Regular-Pile Lining | F74: Long-Pile Lining
A75: t_3_26964_7965 - Lining Fabric Type | B75: t_C917170A4F4F3B48B5AFBACD17F28127 | C75: Fabric Lining | D75: Short-Pile Lining | E75: Regular-Pile Lining | F75: Long-Pile Lining
A76: t_3_29728_7965 - Lining Fabric Type | B76: t_974C5F2B57623C13B0BB56C9ECBB4FEA | C76: Fabric Lining | D76: Short-Pile Lining | E76: Regular-Pile Lining | F76: Long-Pile Lining
A77: t_3_26942_7965 - Lining Fabric Type | B77: t_FC84102B9D0C34A0BD508903DCEDBCB0 | C77: Fabric Lining | D77: Short-Pile Lining | E77: Regular-Pile Lining | F77: Long-Pile Lining
A78: t_3_29950_7965 - Lining Fabric Type | B78: t_A5FAA459D231321AA5FC4730F7C15BCA | C78: Fabric Lining | D78: Short-Pile Lining | E78: Regular-Pile Lining | F78: Long-Pile Lining
A79: t_3_30862_92 - Closure Type | B79: t_194E16D48D303AC7B60CCA17EAA69DF7 | C79: Zipper | D79: Hook and Loop Fastener | E79: Other | F79: Magnetic closure | G79: Lace | H79: Slip On | I79: Elastic Band | J79: Buckle | K79: Double Buckle | L79: Rotary Buckle
A80: t_3_30542_92 - Closure Type | B80: t_BEC6588D05E73E958B7C9B80DD8DAEF2 | C80: Zipper | D80: Hook and Loop Fastener | E80: Other | F80: Magnetic closure | G80: Lace | H80: Slip On | I80: Elastic Band | J80: Buckle | K80: Double Buckle | L80: Rotary Buckle
A81: t_3_54718_92 - Closure Type | B81: t_1F955CADF6FD3981849BBF34E0F2BECB | C81: Zipper | D81: Hook and Loop Fastener | E81: Other | F81: Magnetic closure | G81: Lace | H81: Slip On | I81: Elastic Band | J81: Buckle | K81: Double Buckle | L81: Rotary Buckle
A82: t_3_29728_92 - Closure Type | B82: t_48E52998E063393DA2C427BFB71824D8 | C82: Zipper | D82: Hook and Loop Fastener | E82: Other | F82: Magnetic closure | G82: Lace | H82: Slip On | I82: Elastic Band | J82: Buckle | K82: Double Buckle | L82: Rotary Buckle
A83: t_3_30859_92 - Closure Type | B83: t_8E3CF8DE0DE33284B6F54E48D349C5EC | C83: Zipper | D83: Hook and Loop Fastener | E83: Other | F83: Magnetic closure | G83: Lace | H83: Slip On | I83: Elastic Band | J83: Buckle | K83: Double Buckle | L83: Rotary Buckle
A84: t_3_26942_92 - Closure Type | B84: t_9C2E0CC3C65B3FBB99DD135FB2A8959A | C84: Zipper | D84: Hook and Loop Fastener | E84: Other | F84: Magnetic closure | G84: Lace | H84: Slip On | I84: Elastic Band | J84: Buckle | K84: Double Buckle | L84: Rotary Buckle
A85: t_3_30858_92 - Closure Type | B85: t_F51DC59B247B3D1C9DED46FE4B8E56A2 | C85: Zipper | D85: Hook and Loop Fastener | E85: Other | F85: Magnetic closure | G85: Lace | H85: Slip On | I85: Elastic Band | J85: Buckle | K85: Double Buckle | L85: Rotary Buckle
A86: t_3_26964_92 - Closure Type | B86: t_60BED6665EB73F86BB9E73E488B7B64C | C86: Zipper | D86: Hook and Loop Fastener | E86: Other | F86: Magnetic closure | G86: Lace | H86: Slip On | I86: Elastic Band | J86: Buckle | K86: Double Buckle | L86: Rotary Buckle
A87: t_3_29950_92 - Closure Type | B87: t_92F77C068DEE32C0A61F4E115ECF2D17 | C87: Zipper | D87: Hook and Loop Fastener | E87: Other | F87: Magnetic closure | G87: Lace | H87: Slip On | I87: Elastic Band | J87: Buckle | K87: Double Buckle | L87: Rotary Buckle
A88: t_3_54722_92 - Closure Type | B88: t_51AEA2583B2036B38E008C3B95176A8E | C88: Zipper | D88: Hook and Loop Fastener | E88: Other | F88: Magnetic closure | G88: Lace | H88: Slip On | I88: Elastic Band | J88: Buckle | K88: Double Buckle | L88: Rotary Buckle
A89: t_3_30053_92 - Closure Type | B89: t_150837EB78413DB5B5EE70BC297AF858 | C89: Zipper | D89: Hook and Loop Fastener | E89: Other | F89: Magnetic closure | G89: Lace | H89: Slip On | I89: Elastic Band | J89: Buckle | K89: Double Buckle | L89: Rotary Buckle
A90: t_3_30533_92 - Closure Type | B90: t_3076DA0E140E3032854B0BB14F713404 | C90: Zipper | D90: Hook and Loop Fastener | E90: Other | F90: Magnetic closure | G90: Lace | H90: Slip On | I90: Elastic Band | J90: Buckle | K90: Double Buckle | L90: Rotary Buckle
A91: t_3_54722_1264 - Toe Cap | B91: t_B60DC7FD98FD3C8A89418FFB55ED3165 | C91: Round Toe | D91: Pointed Toe | E91: Square Toe
A92: t_3_30542_1264 - Toe Cap | B92: t_301C057620D8341E91906F4A38938595 | C92: Round Toe | D92: Pointed Toe | E92: Square Toe
A93: t_3_30533_1264 - Toe Cap | B93: t_913790C9C2F83936B7D6D8E9DEEC55B7 | C93: Round Toe | D93: Pointed Toe | E93: Square Toe
A94: t_3_30858_1264 - Toe Cap | B94: t_8F22D10E765639C784B75B462D35AC17 | C94: Round Toe | D94: Pointed Toe | E94: Square Toe
A95: t_3_30862_1264 - Toe Cap | B95: t_53C4BB4385643A338DDE12AC10E89289 | C95: Round Toe | D95: Pointed Toe | E95: Square Toe
A96: t_3_54718_1264 - Toe Cap | B96: t_25885AF4BC0F3C7B8A316421864D0A48 | C96: Round Toe | D96: Pointed Toe | E96: Square Toe
A97: t_3_29728_1264 - Toe Cap | B97: t_7D6374EF21C63CEC9228659507C8F75B | C97: Round Toe | D97: Pointed Toe | E97: Square Toe
A98: t_3_30859_1264 - Toe Cap | B98: t_7431428388E93C0988A51946443E092F | C98: Round Toe | D98: Pointed Toe | E98: Square Toe
A99: t_3_29728_1449 - Applicable Age | B99: t_34576B53C0AC3F909A64FD3E5BB1DEA2 | C99: 14 And Under | D99: Over 13 Years Old
A100: t_3_30859_1449 - Applicable Age | B100: t_E56C82B0475B308F98C40CE4DB87FD06 | C100: 14 And Under | D100: Over 13 Years Old
...

Sheet GoodsLevelMode
A1: t_0_Goods Id | B1: t_0_Sku Id | C1: t_0_Status | D1: t_0_Details | E1: t_1_Category | F1: t_1_Category Name | G1: t_1_Product type | H1: t_1_Customization processing technique | I1: t_1_Primary technique | J1: t_1_Secondary technique | K1: t_1_Secondary technique | L1: t_1_Product Name | M1: t_1_Contribution Goods | N1: t_1_Contribution SKU | O1: t_1_Update or Add | P1: t_1_Goods Id | Q1: t_1_Sku Id | R1: t_1_Brand | S1: t_1_Trademark | T1: t_2_Product Description | U1: t_2_Bullet Point | V1: t_2_Bullet Point | W1: t_2_Bullet Point | X1: t_2_Bullet Point | Y1: t_2_Bullet Point | Z1: t_2_Bullet Point | AA1: t_2_Detail Images URL | AB1: t_2_Detail Images URL | AC1: t_2_Detail Images URL | AD1: t_2_Detail Images URL | AE1: t_2_Detail Images URL | AF1: t_2_Detail Images URL | AG1: t_2_Detail Images URL | AH1: t_2_Detail Images URL | AI1: t_2_Detail Images URL | AJ1: t_2_Detail Images URL | AK1: t_2_Detail Images URL | AL1: t_2_Detail Images URL | AM1: t_2_Detail Images URL | AN1: t_2_Detail Images URL | AO1: t_2_Detail Images URL | AP1: t_2_Detail Images URL | AQ1: t_2_Detail Images URL | AR1: t_2_Detail Images URL | AS1: t_2_Detail Images URL | AT1: t_2_Detail Images URL | AU1: t_2_Detail Images URL | AV1: t_2_Detail Images URL | AW1: t_2_Detail Images URL | AX1: t_2_Detail Images URL | AY1: t_2_Detail Images URL | AZ1: t_2_Detail Images URL | BA1: t_2_Detail Images URL | BB1: t_2_Detail Images URL | BC1: t_2_Detail Images URL | BD1: t_2_Detail Images URL | BE1: t_2_Detail Images URL | BF1: t_2_Detail Images URL | BG1: t_2_Detail Images URL | BH1: t_2_Detail Images URL | BI1: t_2_Detail Images URL | BJ1: t_2_Detail Images URL | BK1: t_2_Detail Images URL | BL1: t_2_Detail Images URL | BM1: t_2_Detail Images URL | BN1: t_2_Detail Images URL | BO1: t_2_Detail Images URL | BP1: t_2_Detail Images URL | BQ1: t_2_Detail Images URL | BR1: t_2_Detail Images URL | BS1: t_2_Detail Images URL | BT1: t_2_Detail Images URL | BU1: t_2_Detail Images URL | BV1: t_2_Detail Images URL | BW1: t_2_Detail Images URL | BX1: t_2_Detail Images URL | BY1: t_2_Detail Images URL | BZ1: t_2_Detail Images URL | CA1: t_2_Detail Images URL | CB1: t_2_Detail Images URL | CC1: t_2_Detail Images URL | CD1: t_2_Detail Images URL | CE1: t_2_Detail Images URL | CF1: t_2_Detail Images URL | CG1: t_2_Detail Images URL | CH1: t_2_Detail Images URL | CI1: t_2_Detail Images URL | CJ1: t_2_Detail Images URL | CK1: t_2_Detail Images URL | CL1: t_2_Detail Images URL | CM1: t_2_Detail Images URL | CN1: t_2_Detail Images URL | CO1: t_2_Detail Images URL | CP1: t_2_Detail Images URL | CQ1: t_2_Detail Images URL | CR1: t_2_Detail Images URL | CS1: t_2_Detail Images URL | CT1: t_2_Detail Images URL | CU1: t_2_Detail Images URL | CV1: t_2_Detail Images URL | CW1: t_2_Detail Images URL | CX1: t_2_Detail Images URL | CY1: t_2_Detail Images URL | CZ1: t_2_Detail Images URL | DA1: t_2_Detail Images URL | DB1: t_2_Detail Images URL | DC1: t_2_Detail Images URL | DD1: t_2_Detail Images URL | DE1: t_2_Detail Images URL | DF1: t_2_Detail Images URL | DG1: t_2_Detail Images URL | DH1: t_2_Detail Images URL | DI1: t_2_Detail Images URL | DJ1: t_2_Detail Images URL | DK1: t_2_Detail Images URL | DL1: t_2_Detail Images URL | DM1: t_2_Detail Images URL | DN1: t_2_Detail Images URL | DO1: t_2_Detail Images URL | DP1: t_2_Detail Images URL | DQ1: t_2_Detail Images URL | DR1: t_2_Detail Video URL | DS1: t_3_Property:1259 | DT1: t_3_Property:1259 | DU1: t_3_Property:7964|1259 | DV1: t_3_Property:7550|1259:7964 | DW1: t_3_Property:1261 | DX1: t_3_Property:1261 | DY1: t_3_Property:1260 | DZ1: t_3_Property:1260 | EA1: t_3_Property:7965|1260 | EB1: t_3_Property:92 | EC1: t_3_Property:92 | ED1: t_3_Property:92 | EE1: t_3_Property:92 | EF1: t_3_Property:1264 | EG1: t_3_Property:1449 | EH1: t_3_Property:90 | EI1: t_3_Property:90 | EJ1: t_3_Property:90 | EK1: t_3_Property:19 | EL1: t_3_Property:19 | EM1: t_3_Property:19 | EN1: t_3_Property:143 | EO1: t_3_Property:143 | EP1: t_3_Property:143 | EQ1: t_3_Property:1093 | ER1: t_3_Property:1093 | ES1: t_3_Property:1093 | ET1: t_3_Property:76 | EU1: t_3_Property:76 | EV1: t_3_Property:76 | EW1: t_3_Property:115 | EX1: t_3_Property:115 | EY1: t_3_Property:115 | EZ1: t_3_Property:26 | FA1: t_3_Property:26 | FB1: t_3_Property:26 | FC1: t_3_Property:1101 | FD1: t_3_Property:1262 | FE1: t_3_Property:1262 | FF1: t_3_Property:1132 | FG1: t_3_Property:137 | FH1: t_3_Property:20 | FI1: t_3_Property:1919 | FJ1: t_3_Property:7963 | FK1: t_3_Property:7969|7963 | FL1: t_3_Property:7970|7963:7969 | FM1: t_3_Property:9154 | FN1: t_3_Property:9154 | FO1: t_3_Property:9154 | FP1: t_3_Property:7550|1259 | FQ1: t_3_Property:15:35385 | FR1: t_3_Property:15:35386 | FS1: t_3_Property:15:35387 | FT1: t_3_Property:15:35388 | FU1: t_3_Property:15:35390 | FV1: t_3_Property:15:35391 | FW1: t_3_Property:15:35392 | FX1: t_3_Property:15:35393 | FY1: t_3_Property:15:35394 | FZ1: t_3_Property:15:35395 | GA1: t_3_Property:15:35397 | GB1: t_3_Property:15:35398 | GC1: t_3_Property:15:35399 | GD1: t_3_Property:15:35400 | GE1: t_3_Property:15:35401 | GF1: t_3_Property:15:35403 | GG1: t_3_Property:15:35404 | GH1: t_3_Property:15:35405 | GI1: t_3_Property:15:35406 | GJ1: t_3_Property:15:35407 | GK1: t_3_Property:15:35408 | GL1: t_3_Property:15:35409 | GM1: t_3_Property:15:35410 | GN1: t_3_Property:15:35411 | GO1: t_3_Property:15:35415 | GP1: t_3_Property:15:35364 | GQ1: t_3_Property:15:1155 | GR1: t_3_Property:15:36254 | GS1: t_3_Property:15:965 | GT1: t_3_Property:12 | GU1: t_3_Property:7639:35392 | GV1: t_3_Property:7639:35393 | GW1: t_3_Property:7639:35394 | GX1: t_3_Property:7639:35395 | GY1: t_3_Property:7639:35397 | GZ1: t_3_Property:7639:35398 | HA1: t_3_Property:7639:35399 | HB1: t_3_Property:7639:35400 | HC1: t_3_Property:7639:35401 | HD1: t_3_Property:7639:35403 | HE1: t_3_Property:7639:35404 | HF1: t_3_Property:7639:35405 | HG1: t_3_Property:7639:35406 | HH1: t_3_Property:7639:35407 | HI1: t_3_Property:7639:35408 | HJ1: t_3_Property:7639:35409 | HK1: t_3_Property:7639:35410 | HL1: t_3_Property:7639:35411 | HM1: t_3_Property:7639:35412 | HN1: t_3_Property:7639:35413 | HO1: t_3_Property:7639:35414 | HP1: t_3_Property:7639:35415 | HQ1: t_3_Property:7639:36254 | HR1: t_3_Property:7639:98 | HS1: t_3_Property:7639:35364 | HT1: t_3_Property:7639:214835 | HU1: t_3_Property:7639:47217 | HV1: t_3_Property:7639:121 | HW1: t_3_Property:7639:35385 | HX1: t_3_Property:7639:35387 | HY1: t_3_Property:7639:35388 | HZ1: t_3_Property:7639:35390 | IA1: t_3_Property:7639:35391 | IB1: t_3_Property:82 | IC1: t_3_Property:83 | ID1: t_3_Property:75 | IE1: t_3_Property:1306 | IF1: t_3_Property:1192 | IG1: t_3_Property:6227 | IH1: t_3_Property:2103 | II1: t_3_Property:6926 | IJ1: t_3_Property:6930 - value|6926 | IK1: t_3_Property:6930 - unit|6926 | IL1: t_3_Property:6927 | IM1: t_3_Property:6931 - value|6927 | IN1: t_3_Property:6931 - unit|6927 | IO1: t_3_Property:6928 | IP1: t_3_Property:6934 - value|6928 | IQ1: t_3_Property:6934 - unit|6928 | IR1: t_3_Property:6547:35392 | IS1: t_3_Property:6547:35393 | IT1: t_3_Property:6547:35394 | IU1: t_3_Property:6547:35395 | IV1: t_3_Property:6547:35397 | IW1: t_3_Property:6547:35398 | IX1: t_3_Property:6547:35399 | IY1: t_3_Property:6547:35400 | IZ1: t_3_Property:6547:35401 | JA1: t_3_Property:6547:35403 | JB1: t_3_Property:6547:35404 | JC1: t_3_Property:6547:35405 | JD1: t_3_Property:6547:35406 | JE1: t_3_Property:6547:35407 | JF1: t_3_Property:6547:35408 | JG1: t_3_Property:6547:35409 | JH1: t_3_Property:6547:35410 | JI1: t_3_Property:6547:35411 | JJ1: t_3_Property:6547:35412 | JK1: t_3_Property:6547:35413 | JL1: t_3_Property:6547:35414 | JM1: t_3_Property:6547:35415 | JN1: t_3_Property:6547:36254 | JO1: t_3_Property:6547:35364 | JP1: t_3_Property:6547:47217 | JQ1: t_3_Property:6547:121 | JR1: t_3_Property:6547:35385 | JS1: t_3_Property:6547:35386 | JT1: t_3_Property:6547:35387 | JU1: t_3_Property:6547:35388 | JV1: t_3_Property:6547:35390 | JW1: t_3_Property:6547:35391 | JX1: t_3_Property:7654 | JY1: t_3_Property:7955 | JZ1: t_3_Property:84 | KA1: t_3_Property:203 | KB1: t_3_Property:6443 | KC1: t_3_Property:466 | KD1: t_3_Property:420 | KE1: t_3_Property:128 | KF1: t_4_Variation Theme | KG1: t_4_Size Family | KH1: t_4_Sub-Size Family | KI1: t_4_Size:3001 | KJ1: t_4_Sale Property:1001 | KK1: t_5_Size Chart Method | KL1: t_5_Size Chart Image | KM1: t_5_Unit | KN1: t_5_Size Chart Group:2 | KO1: t_5_Size Chart Element:13:Product:10013 | KP1: t_5_Size Chart Element:13:Product:10014 | KQ1: t_5_Size Chart Element:13:Product:10025 | KR1: t_5_Size Chart Element:13:Product:20033 | KS1: t_5_Size Chart Element:11:Product:10013 | KT1: t_5_Size Chart Element:11:Product:10014 | KU1: t_5_Size Chart Element:11:Product:10025 | KV1: t_5_Size Chart Element:11:Product:20033 | KW1: t_5_Size Chart Element:11:Product:33554443 | KX1: t_5_Size Chart Element:25:Product:10016 | KY1: t_5_Size Chart Element:25:Product:10017 | KZ1: t_5_Size Chart Element:25:Product:10018 | LA1: t_5_Size Chart Element:107:Product:10013 | LB1: t_5_Size Chart Element:107:Product:10014 | LC1: t_5_Size Chart Element:107:Product:10025 | LD1: t_5_Size Chart Element:107:Product:20033 | LE1: t_5_Size Chart Element:12:Product:10013 | LF1: t_5_Size Chart Element:12:Product:10014 | LG1: t_5_Size Chart Element:12:Product:10025 | LH1: t_5_Size Chart Element:12:Product:10032 | LI1: t_5_Size Chart Element:12:Product:10033 | LJ1: t_5_Size Chart Element:12:Product:10034 | LK1: t_5_Size Chart Element:12:Product:10035 | LL1: t_5_Size Chart Element:12:Product:10036 | LM1: t_5_Size Chart Element:12:Product:20033 | LN1: t_5_Size Chart Element:12:Product:33554443 | LO1: t_6_SKU Images URL | LP1: t_6_SKU Images URL | LQ1: t_6_SKU Images URL | LR1: t_6_SKU Images URL | LS1: t_6_SKU Images URL | LT1: t_6_SKU Images URL | LU1: t_6_SKU Images URL | LV1: t_6_SKU Images URL | LW1: t_6_SKU Images URL | LX1: t_6_SKU Images URL | LY1: t_6_Quantity | LZ1: t_6_Base Price - EUR | MA1: t_6_Reference Link | MB1: t_6_List Price - EUR | MC1: t_6_Not available for List price | MD1: t_6_Weight - g | ME1: t_6_Length - cm | MF1: t_6_Width - cm | MG1: t_6_Height - cm | MH1: t_6_SKU type | MI1: t_6_Individually packed | MJ1: t_6_Total packaging quantity | MK1: t_6_Packaging unit | ML1: t_6_Total item quantity | MM1: t_6_Item unit | MN1: t_6_Net content | MO1: t_6_Total net content | MP1: t_6_Net content unit | MQ1: t_6_External Product ID Type | MR1: t_6_External Product ID | MS1: t_7_Shipping Template | MT1: t_7_Handling Time | MU1: t_7_Fulfillment Channel | MV1: t_7_Item Tax Code | MW1: t_8_Country/Region of Origin | MX1: t_8_Province of Origin | MY1: t_8_SKU Packaging Information (with visible label) | MZ1: t_8_SKU Packaging Information (with visible label) | NA1: t_8_SKU Packaging Information (with visible label) | NB1: t_8_SKU Packaging Information (with visible label) | NC1: t_8_SKU Packaging Information (with visible label) | ND1: t_8_SKU Packaging Information (with visible label) | NE1: t_8_SKU Packaging Information (with visible label) | NF1: t_8_SKU Packaging Information (with visible label) | NG1: t_8_SKU Packaging Information (with visible label) | NH1: t_8_SKU Packaging Information (with visible label) | NI1: t_8_SKU Packaging Information (with visible label) | NJ1: t_8_SKU Packaging Information (with visible label) | NK1: t_8_SKU Packaging Information (with visible label) | NL1: t_8_SKU Packaging Information (with visible label) | NM1: t_8_SKU Packaging Information (with visible label) | NN1: t_8_SKU Packaging Information (with visible label) | NO1: t_8_SKU Packaging Information (with visible label) | NP1: t_8_SKU Packaging Information (with visible label) | NQ1: t_8_SKU Packaging Information (with visible label) | NR1: t_8_SKU Packaging Information (with visible label) | NS1: t_8_SKU Packaging Information (with visible label) | NT1: t_8_SKU Packaging Information (with visible label) | NU1: t_8_SKU Packaging Information (with visible label) | NV1: t_8_SKU Packaging Information (with visible label) | NW1: t_8_SKU Packaging Information (with visible label) | NX1: t_8_SKU Packaging Information (with visible label) | NY1: t_8_SKU Packaging Information (with visible label) | NZ1: t_8_SKU Packaging Information (with visible label) | OA1: t_8_SKU Packaging Information (with visible label) | OB1: t_8_SKU Packaging Information (with visible label) | OC1: t_8_SKU Packaging Information (with visible label) | OD1: t_8_SKU Packaging Information (with visible label) | OE1: t_8_SKU Packaging Information (with visible label) | OF1: t_8_SKU Packaging Information (with visible label) | OG1: t_8_SKU Packaging Information (with visible label) | OH1: t_8_SKU Packaging Information (with visible label) | OI1: t_8_SKU Packaging Information (with visible label) | OJ1: t_8_SKU Packaging Information (with visible label) | OK1: t_8_SKU Packaging Information (with visible label) | OL1: t_8_SKU Packaging Information (with visible label) | OM1: t_8_SKU Packaging Information (with visible label) | ON1: t_8_SKU Packaging Information (with visible label) | OO1: t_8_SKU Packaging Information (with visible label) | OP1: t_8_SKU Packaging Information (with visible label) | OQ1: t_8_SKU Packaging Information (with visible label) | OR1: t_8_Origin Label & Manufacturer Information | OS1: t_8_Origin Label & Manufacturer Information | OT1: t_8_Origin Label & Manufacturer Information | OU1: t_8_Origin Label & Manufacturer Information | OV1: t_8_Origin Label & Manufacturer Information | OW1: t_8_Governance Property:1100100115 | OX1: t_8_Governance Property:3 | OY1: t_8_Governance Property:2 | OZ1: t_8_Governance Property:1100100224
A2: 26942_require | E2: require | L2: require | M2: require | N2: require | DS2: require | DT2: require | DW2: require | DX2: require | DY2: require | DZ2: require | KF2: require | KG2: require | KH2: require | KI2: require | KJ2: require | KM2: require | KO2: require | LO2: require | LY2: require | LZ2: require | MB2: require | MD2: require | ME2: require | MF2: require | MG2: require | MI2: require | MJ2: require | MK2: require | MS2: require | MW2: require | OW2: require | OX2: require | OY2: require
A3: 26942_disabled | EF3: disabled | EG3: disabled | EN3: disabled | EO3: disabled | EP3: disabled | EQ3: disabled | ER3: disabled | ES3: disabled | FC3: disabled | FP3: disabled | FQ3: disabled | FR3: disabled | FS3: disabled | FT3: disabled | FU3: disabled | FV3: disabled | FW3: disabled | FX3: disabled | FY3: disabled | FZ3: disabled | GA3: disabled | GB3: disabled | GC3: disabled | GD3: disabled | GE3: disabled | GF3: disabled | GG3: disabled | GH3: disabled | GI3: disabled | GJ3: disabled | GK3: disabled | GL3: disabled | GM3: disabled | GN3: disabled | GO3: disabled | GP3: disabled | GQ3: disabled | GR3: disabled | GS3: disabled | GT3: disabled | GU3: disabled | GV3: disabled | GW3: disabled | GX3: disabled | GY3: disabled | GZ3: disabled | HA3: disabled | HB3: disabled | HC3: disabled | HD3: disabled | HE3: disabled | HF3: disabled | HG3: disabled | HH3: disabled | HI3: disabled | HJ3: disabled | HK3: disabled | HL3: disabled | HM3: disabled | HN3: disabled | HO3: disabled | HP3: disabled | HQ3: disabled | HR3: disabled | HS3: disabled | HT3: disabled | HU3: disabled | HV3: disabled | HW3: disabled | HX3: disabled | HY3: disabled | HZ3: disabled | IA3: disabled | IB3: disabled | IC3: disabled | ID3: disabled | IE3: disabled | IF3: disabled | IG3: disabled | IH3: disabled | II3: disabled | IJ3: disabled | IK3: disabled | IL3: disabled | IM3: disabled | IN3: disabled | IO3: disabled | IP3: disabled | IQ3: disabled | IR3: disabled | IS3: disabled | IT3: disabled | IU3: disabled | IV3: disabled | IW3: disabled | IX3: disabled | IY3: disabled | IZ3: disabled | JA3: disabled | JB3: disabled | JC3: disabled | JD3: disabled | JE3: disabled | JF3: disabled | JG3: disabled | JH3: disabled | JI3: disabled | JJ3: disabled | JK3: disabled | JL3: disabled | JM3: disabled | JN3: disabled | JO3: disabled | JP3: disabled | JQ3: disabled | JR3: disabled | JS3: disabled | JT3: disabled | JU3: disabled | JV3: disabled | JW3: disabled | JX3: disabled | JY3: disabled | JZ3: disabled | KA3: disabled | KB3: disabled | KC3: disabled | KD3: disabled | KE3: disabled | KS3: disabled | KT3: disabled | KU3: disabled | KV3: disabled | KW3: disabled | KX3: disabled | KY3: disabled | KZ3: disabled | LA3: disabled | LB3: disabled | LC3: disabled | LD3: disabled | LE3: disabled | LF3: disabled | LG3: disabled | LH3: disabled | LI3: disabled | LJ3: disabled | LK3: disabled | LL3: disabled | LM3: disabled | LN3: disabled
A4: 26942_condition_require | MX4: condition_require
A5: 26964_require | E5: require | L5: require | M5: require | N5: require | DS5: require | DT5: require | DW5: require | DX5: require | DY5: require | DZ5: require | KF5: require | KG5: require | KH5: require | KI5: require | KJ5: require | KM5: require | LA5: require | LO5: require | LY5: require | LZ5: require | MB5: require | MD5: require | ME5: require | MF5: require | MG5: require | MI5: require | MJ5: require | MK5: require | MS5: require | MW5: require | OW5: require | OX5: require | OY5: require
A6: 26964_disabled | EF6: disabled | EG6: disabled | EN6: disabled | EO6: disabled | EP6: disabled | EQ6: disabled | ER6: disabled | ES6: disabled | FC6: disabled | FP6: disabled | FQ6: disabled | FR6: disabled | FS6: disabled | FT6: disabled | FU6: disabled | FV6: disabled | FW6: disabled | FX6: disabled | FY6: disabled | FZ6: disabled | GA6: disabled | GB6: disabled | GC6: disabled | GD6: disabled | GE6: disabled | GF6: disabled | GG6: disabled | GH6: disabled | GI6: disabled | GJ6: disabled | GK6: disabled | GL6: disabled | GM6: disabled | GN6: disabled | GO6: disabled | GP6: disabled | GQ6: disabled | GR6: disabled | GS6: disabled | GT6: disabled | GU6: disabled | GV6: disabled | GW6: disabled | GX6: disabled | GY6: disabled | GZ6: disabled | HA6: disabled | HB6: disabled | HC6: disabled | HD6: disabled | HE6: disabled | HF6: disabled | HG6: disabled | HH6: disabled | HI6: disabled | HJ6: disabled | HK6: disabled | HL6: disabled | HM6: disabled | HN6: disabled | HO6: disabled | HP6: disabled | HQ6: disabled | HR6: disabled | HS6: disabled | HT6: disabled | HU6: disabled | HV6: disabled | HW6: disabled | HX6: disabled | HY6: disabled | HZ6: disabled | IA6: disabled | IB6: disabled | IC6: disabled | ID6: disabled | IE6: disabled | IF6: disabled | IG6: disabled | IH6: disabled | II6: disabled | IJ6: disabled | IK6: disabled | IL6: disabled | IM6: disabled | IN6: disabled | IO6: disabled | IP6: disabled | IQ6: disabled | IR6: disabled | IS6: disabled | IT6: disabled | IU6: disabled | IV6: disabled | IW6: disabled | IX6: disabled | IY6: disabled | IZ6: disabled | JA6: disabled | JB6: disabled | JC6: disabled | JD6: disabled | JE6: disabled | JF6: disabled | JG6: disabled | JH6: disabled | JI6: disabled | JJ6: disabled | JK6: disabled | JL6: disabled | JM6: disabled | JN6: disabled | JO6: disabled | JP6: disabled | JQ6: disabled | JR6: disabled | JS6: disabled | JT6: disabled | JU6: disabled | JV6: disabled | JW6: disabled | JX6: disabled | JY6: disabled | JZ6: disabled | KA6: disabled | KB6: disabled | KC6: disabled | KD6: disabled | KE6: disabled | KO6: disabled | KP6: disabled | KQ6: disabled | KR6: disabled | KS6: disabled | KT6: disabled | KU6: disabled | KV6: disabled | KW6: disabled | KX6: disabled | KY6: disabled | KZ6: disabled | LE6: disabled | LF6: disabled | LG6: disabled | LH6: disabled | LI6: disabled | LJ6: disabled | LK6: disabled | LL6: disabled | LM6: disabled | LN6: disabled
A7: 26964_condition_require | MX7: condition_require
A8: 29180_require | E8: require | L8: require | M8: require | N8: require | DS8: require | DT8: require | DW8: require | DX8: require | DY8: require | DZ8: require | FD8: require | FE8: require | KF8: require | KG8: require | KH8: require | KI8: require | KJ8: require | KM8: require | LE8: require | LM8: require | LO8: require | LY8: require | LZ8: require | MB8: require | MD8: require | ME8: require | MF8: require | MG8: require | MI8: require | MJ8: require | MK8: require | MS8: require | MW8: require | OW8: require | OX8: require | OY8: require
A9: 29180_disabled | DU9: disabled | DV9: disabled | EA9: disabled | EB9: disabled | EC9: disabled | ED9: disabled | EE9: disabled | EF9: disabled | EG9: disabled | EH9: disabled | EI9: disabled | EJ9: disabled | EN9: disabled | EO9: disabled | EP9: disabled | EQ9: disabled | ER9: disabled | ES9: disabled | ET9: disabled | EU9: disabled | EV9: disabled | EW9: disabled | EX9: disabled | EY9: disabled | FC9: disabled | FF9: disabled | FG9: disabled | FJ9: disabled | FK9: disabled | FL9: disabled | FQ9: disabled | FR9: disabled | FS9: disabled | FT9: disabled | FU9: disabled | FV9: disabled | FW9: disabled | FX9: disabled | FY9: disabled | FZ9: disabled | GA9: disabled | GB9: disabled | GC9: disabled | GD9: disabled | GE9: disabled | GF9: disabled | GG9: disabled | GH9: disabled | GI9: disabled | GJ9: disabled | GK9: disabled | GL9: disabled | GM9: disabled | GN9: disabled | GO9: disabled | GP9: disabled | GQ9: disabled | GR9: disabled | GS9: disabled | GT9: disabled | GU9: disabled | GV9: disabled | GW9: disabled | GX9: disabled | GY9: disabled | GZ9: disabled | HA9: disabled | HB9: disabled | HC9: disabled | HD9: disabled | HE9: disabled | HF9: disabled | HG9: disabled | HH9: disabled | HI9: disabled | HJ9: disabled | HK9: disabled | HL9: disabled | HM9: disabled | HN9: disabled | HO9: disabled | HP9: disabled | HQ9: disabled | HR9: disabled | HS9: disabled | HT9: disabled | HU9: disabled | HV9: disabled | HW9: disabled | HX9: disabled | HY9: disabled | HZ9: disabled | IA9: disabled | IB9: disabled | IC9: disabled | ID9: disabled | IE9: disabled | IF9: disabled | IH9: disabled | II9: disabled | IJ9: disabled | IK9: disabled | IL9: disabled | IM9: disabled | IN9: disabled | IO9: disabled | IP9: disabled | IQ9: disabled | IR9: disabled | IS9: disabled | IT9: disabled | IU9: disabled | IV9: disabled | IW9: disabled | IX9: disabled | IY9: disabled | IZ9: disabled | JA9: disabled | JB9: disabled | JC9: disabled | JD9: disabled | JE9: disabled | JF9: disabled | JG9: disabled | JH9: disabled | JI9: disabled | JJ9: disabled | JK9: disabled | JL9: disabled | JM9: disabled | JN9: disabled | JO9: disabled | JP9: disabled | JQ9: disabled | JR9: disabled | JS9: disabled | JT9: disabled | JU9: disabled | JV9: disabled | JW9: disabled | JZ9: disabled | KO9: disabled | KP9: disabled | KQ9: disabled | KR9: disabled | KS9: disabled | KT9: disabled | KU9: disabled | KV9: disabled | KW9: disabled | KX9: disabled | KY9: disabled | KZ9: disabled | LA9: disabled | LB9: disabled | LC9: disabled | LD9: disabled
A10: 29180_condition_require | MX10: condition_require
A11: 29194_require | E11: require | L11: require | M11: require | N11: require | DS11: require | DW11: require | DX11: require | DY11: require | DZ11: require | FD11: require | FE11: require | KF11: require | KG11: require | KH11: require | KI11: require | KJ11: require | KM11: require | LE11: require | LM11: require | LO11: require | LY11: require | LZ11: require | MB11: require | MD11: require | ME11: require | MF11: require | MG11: require | MI11: require | MJ11: require | MK11: require | MS11: require | MW11: require | OW11: require | OX11: require | OY11: require
A12: 29194_disabled | DT12: disabled | DU12: disabled | DV12: disabled | EA12: disabled | EB12: disabled | EC12: disabled | ED12: disabled | EE12: disabled | EF12: disabled | EG12: disabled | EH12: disabled | EI12: disabled | EJ12: disabled | EN12: disabled | EO12: disabled | EP12: disabled | EQ12: disabled | ER12: disabled | ES12: disabled | ET12: disabled | EU12: disabled | EV12: disabled | EW12: disabled | EX12: disabled | EY12: disabled | FC12: disabled | FF12: disabled | FG12: disabled | FJ12: disabled | FK12: disabled | FL12: disabled | FQ12: disabled | FR12: disabled | FS12: disabled | FT12: disabled | FU12: disabled | FV12: disabled | FW12: disabled | FX12: disabled | FY12: disabled | FZ12: disabled | GA12: disabled | GB12: disabled | GC12: disabled | GD12: disabled | GE12: disabled | GF12: disabled | GG12: disabled | GH12: disabled | GI12: disabled | GJ12: disabled | GK12: disabled | GL12: disabled | GM12: disabled | GN12: disabled | GO12: disabled | GP12: disabled | GQ12: disabled | GR12: disabled | GS12: disabled | GT12: disabled | GU12: disabled | GV12: disabled | GW12: disabled | GX12: disabled | GY12: disabled | GZ12: disabled | HA12: disabled | HB12: disabled | HC12: disabled | HD12: disabled | HE12: disabled | HF12: disabled | HG12: disabled | HH12: disabled | HI12: disabled | HJ12: disabled | HK12: disabled | HL12: disabled | HM12: disabled | HN12: disabled | HO12: disabled | HP12: disabled | HQ12: disabled | HR12: disabled | HS12: disabled | HT12: disabled | HU12: disabled | HV12: disabled | HW12: disabled | HX12: disabled | HY12: disabled | HZ12: disabled | IA12: disabled | IB12: disabled | IC12: disabled | ID12: disabled | IE12: disabled | IF12: disabled | IH12: disabled | II12: disabled | IJ12: disabled | IK12: disabled | IL12: disabled | IM12: disabled | IN12: disabled | IO12: disabled | IP12: disabled | IQ12: disabled | IR12: disabled | IS12: disabled | IT12: disabled | IU12: disabled | IV12: disabled | IW12: disabled | IX12: disabled | IY12: disabled | IZ12: disabled | JA12: disabled | JB12: disabled | JC12: disabled | JD12: disabled | JE12: disabled | JF12: disabled | JG12: disabled | JH12: disabled | JI12: disabled | JJ12: disabled | JK12: disabled | JL12: disabled | JM12: disabled | JN12: disabled | JO12: disabled | JP12: disabled | JQ12: disabled | JR12: disabled | JS12: disabled | JT12: disabled | JU12: disabled | JV12: disabled | JW12: disabled | JX12: disabled | KC12: disabled | KD12: disabled | KE12: disabled | KO12: disabled | KP12: disabled | KQ12: disabled | KR12: disabled | KS12: disabled | KT12: disabled | KU12: disabled | KV12: disabled | KW12: disabled | KX12: disabled | KY12: disabled | KZ12: disabled | LA12: disabled | LB12: disabled | LC12: disabled | LD12: disabled
A13: 29194_condition_require | MX13: condition_require
A14: 29728_require | E14: require | L14: require | M14: require | N14: require | DS14: require | DW14: require | DX14: require | DY14: require | DZ14: require | EG14: require | ET14: require | EU14: require | EV14: require | FD14: require | FE14: require | KF14: require | KG14: require | KH14: require | KI14: require | KJ14: require | KM14: require | KO14: require | LO14: require | LY14: require | LZ14: require | MB14: require | MD14: require | ME14: require | MF14: require | MG14: require | MI14: require | MJ14: require | MK14: require | MS14: require | MW14: require | OW14: require | OX14: require | OY14: require
A15: 29728_disabled | DT15: disabled | FP15: disabled | FQ15: disabled | FR15: disabled | FS15: disabled | FT15: disabled | FU15: disabled | FV15: disabled | FW15: disabled | FX15: disabled | FY15: disabled | FZ15: disabled | GA15: disabled | GB15: disabled | GC15: disabled | GD15: disabled | GE15: disabled | GF15: disabled | GG15: disabled | GH15: disabled | GI15: disabled | GJ15: disabled | GK15: disabled | GL15: disabled | GM15: disabled | GN15: disabled | GO15: disabled | GP15: disabled | GQ15: disabled | GR15: disabled | GS15: disabled | GT15: disabled | GU15: disabled | GV15: disabled | GW15: disabled | GX15: disabled | GY15: disabled | GZ15: disabled | HA15: disabled | HB15: disabled | HC15: disabled | HD15: disabled | HE15: disabled | HF15: disabled | HG15: disabled | HH15: disabled | HI15: disabled | HJ15: disabled | HK15: disabled | HL15: disabled | HM15: disabled | HN15: disabled | HO15: disabled | HP15: disabled | HQ15: disabled | HR15: disabled | HS15: disabled | HT15: disabled | HU15: disabled | HV15: disabled | HW15: disabled | HX15: disabled | HY15: disabled | HZ15: disabled | IA15: disabled | IB15: disabled | IC15: disabled | ID15: disabled | IE15: disabled | IF15: disabled | IG15: disabled | IH15: disabled | II15: disabled | IJ15: disabled | IK15: disabled | IL15: disabled | IM15: disabled | IN15: disabled | IO15: disabled | IP15: disabled | IQ15: disabled | IR15: disabled | IS15: disabled | IT15: disabled | IU15: disabled | IV15: disabled | IW15: disabled | IX15: disabled | IY15: disabled | IZ15: disabled | JA15: disabled | JB15: disabled | JC15: disabled | JD15: disabled | JE15: disabled | JF15: disabled | JG15: disabled | JH15: disabled | JI15: disabled | JJ15: disabled | JK15: disabled | JL15: disabled | JM15: disabled | JN15: disabled | JO15: disabled | JP15: disabled | JQ15: disabled | JR15: disabled | JS15: disabled | JT15: disabled | JU15: disabled | JV15: disabled | JW15: disabled | JX15: disabled | JY15: disabled | JZ15: disabled | KA15: disabled | KB15: disabled | KC15: disabled | KD15: disabled | KE15: disabled | KS15: disabled | KT15: disabled | KU15: disabled | KV15: disabled | KW15: disabled | KX15: disabled | KY15: disabled | KZ15: disabled | LA15: disabled | LB15: disabled | LC15: disabled | LD15: disabled | LE15: disabled | LF15: disabled | LG15: disabled | LH15: disabled | LI15: disabled | LJ15: disabled | LK15: disabled | LL15: disabled | LM15: disabled | LN15: disabled
A16: 29728_condition_require | MX16: condition_require
A17: 29950_require | E17: require | L17: require | M17: require | N17: require | DS17: require | DT17: require | DW17: require | DX17: require | DY17: require | DZ17: require | KF17: require | KG17: require | KH17: require | KI17: require | KJ17: require | KM17: require | KO17: require | LO17: require | LY17: require | LZ17: require | MB17: require | MD17: require | ME17: require | MF17: require | MG17: require | MI17: require | MJ17: require | MK17: require | MS17: require | MW17: require | OW17: require | OX17: require | OY17: require
A18: 29950_disabled | EF18: disabled | EG18: disabled | EN18: disabled | EO18: disabled | EP18: disabled | EQ18: disabled | ER18: disabled | ES18: disabled | FC18: disabled | FP18: disabled | FQ18: disabled | FR18: disabled | FS18: disabled | FT18: disabled | FU18: disabled | FV18: disabled | FW18: disabled | FX18: disabled | FY18: disabled | FZ18: disabled | GA18: disabled | GB18: disabled | GC18: disabled | GD18: disabled | GE18: disabled | GF18: disabled | GG18: disabled | GH18: disabled | GI18: disabled | GJ18: disabled | GK18: disabled | GL18: disabled | GM18: disabled | GN18: disabled | GO18: disabled | GP18: disabled | GQ18: disabled | GR18: disabled | GS18: disabled | GT18: disabled | GU18: disabled | GV18: disabled | GW18: disabled | GX18: disabled | GY18: disabled | GZ18: disabled | HA18: disabled | HB18: disabled | HC18: disabled | HD18: disabled | HE18: disabled | HF18: disabled | HG18: disabled | HH18: disabled | HI18: disabled | HJ18: disabled | HK18: disabled | HL18: disabled | HM18: disabled | HN18: disabled | HO18: disabled | HP18: disabled | HQ18: disabled | HR18: disabled | HS18: disabled | HT18: disabled | HU18: disabled | HV18: disabled | HW18: disabled | HX18: disabled | HY18: disabled | HZ18: disabled | IA18: disabled | IB18: disabled | IC18: disabled | ID18: disabled | IE18: disabled | IF18: disabled | IG18: disabled | IH18: disabled | II18: disabled | IJ18: disabled | IK18: disabled | IL18: disabled | IM18: disabled | IN18: disabled | IO18: disabled | IP18: disabled | IQ18: disabled | IR18: disabled | IS18: disabled | IT18: disabled | IU18: disabled | IV18: disabled | IW18: disabled | IX18: disabled | IY18: disabled | IZ18: disabled | JA18: disabled | JB18: disabled | JC18: disabled | JD18: disabled | JE18: disabled | JF18: disabled | JG18: disabled | JH18: disabled | JI18: disabled | JJ18: disabled | JK18: disabled | JL18: disabled | JM18: disabled | JN18: disabled | JO18: disabled | JP18: disabled | JQ18: disabled | JR18: disabled | JS18: disabled | JT18: disabled | JU18: disabled | JV18: disabled | JW18: disabled | JX18: disabled | JY18: disabled | JZ18: disabled | KA18: disabled | KB18: disabled | KC18: disabled | KD18: disabled | KE18: disabled | KS18: disabled | KT18: disabled | KU18: disabled | KV18: disabled | KW18: disabled | KX18: disabled | KY18: disabled | KZ18: disabled | LA18: disabled | LB18: disabled | LC18: disabled | LD18: disabled | LE18: disabled | LF18: disabled | LG18: disabled | LH18: disabled | LI18: disabled | LJ18: disabled | LK18: disabled | LL18: disabled | LM18: disabled | LN18: disabled
A19: 29950_condition_require | MX19: condition_require
A20: 30053_require | E20: require | L20: require | M20: require | N20: require | DS20: require | DW20: require | DX20: require | DY20: require | DZ20: require | KF20: require | KG20: require | KH20: require | KI20: require | KJ20: require | KM20: require | LA20: require | LO20: require | LY20: require | LZ20: require | MB20: require | MD20: require | ME20: require | MF20: require | MG20: require | MI20: require | MJ20: require | MK20: require | MS20: require | MW20: require | OW20: require | OX20: require | OY20: require
A21: 30053_disabled | DT21: disabled | EF21: disabled | EG21: disabled | EN21: disabled | EO21: disabled | EP21: disabled | EQ21: disabled | ER21: disabled | ES21: disabled | FC21: disabled | FP21: disabled | FQ21: disabled | FR21: disabled | FS21: disabled | FT21: disabled | FU21: disabled | FV21: disabled | FW21: disabled | FX21: disabled | FY21: disabled | FZ21: disabled | GA21: disabled | GB21: disabled | GC21: disabled | GD21: disabled | GE21: disabled | GF21: disabled | GG21: disabled | GH21: disabled | GI21: disabled | GJ21: disabled | GK21: disabled | GL21: disabled | GM21: disabled | GN21: disabled | GO21: disabled | GP21: disabled | GQ21: disabled | GR21: disabled | GS21: disabled | GT21: disabled | GU21: disabled | GV21: disabled | GW21: disabled | GX21: disabled | GY21: disabled | GZ21: disabled | HA21: disabled | HB21: disabled | HC21: disabled | HD21: disabled | HE21: disabled | HF21: disabled | HG21: disabled | HH21: disabled | HI21: disabled | HJ21: disabled | HK21: disabled | HL21: disabled | HM21: disabled | HN21: disabled | HO21: disabled | HP21: disabled | HQ21: disabled | HR21: disabled | HS21: disabled | HT21: disabled | HU21: disabled | HV21: disabled | HW21: disabled | HX21: disabled | HY21: disabled | HZ21: disabled | IA21: disabled | IB21: disabled | IC21: disabled | ID21: disabled | IE21: disabled | IF21: disabled | IG21: disabled | IH21: disabled | II21: disabled | IJ21: disabled | IK21: disabled | IL21: disabled | IM21: disabled | IN21: disabled | IO21: disabled | IP21: disabled | IQ21: disabled | IR21: disabled | IS21: disabled | IT21: disabled | IU21: disabled | IV21: disabled | IW21: disabled | IX21: disabled | IY21: disabled | IZ21: disabled | JA21: disabled | JB21: disabled | JC21: disabled | JD21: disabled | JE21: disabled | JF21: disabled | JG21: disabled | JH21: disabled | JI21: disabled | JJ21: disabled | JK21: disabled | JL21: disabled | JM21: disabled | JN21: disabled | JO21: disabled | JP21: disabled | JQ21: disabled | JR21: disabled | JS21: disabled | JT21: disabled | JU21: disabled | JV21: disabled | JW21: disabled | JX21: disabled | JY21: disabled | JZ21: disabled | KA21: disabled | KB21: disabled | KC21: disabled | KD21: disabled | KE21: disabled | KO21: disabled | KP21: disabled | KQ21: disabled | KR21: disabled | KS21: disabled | KT21: disabled | KU21: disabled | KV21: disabled | KW21: disabled | KX21: disabled | KY21: disabled | KZ21: disabled | LE21: disabled | LF21: disabled | LG21: disabled | LH21: disabled | LI21: disabled | LJ21: disabled | LK21: disabled | LL21: disabled | LM21: disabled | LN21: disabled
A22: 30053_condition_require | MX22: condition_require
A23: 30533_require | E23: require | L23: require | M23: require | N23: require | DS23: require | DW23: require | DX23: require | DY23: require | DZ23: require | ET23: require | EU23: require | EV23: require | FD23: require | FE23: require | KF23: require | KG23: require | KH23: require | KI23: require | KJ23: require | KM23: require | KS23: require | LO23: require | LY23: require | LZ23: require | MB23: require | MD23: require | ME23: require | MF23: require | MG23: require | MI23: require | MJ23: require | MK23: require | MS23: require | MW23: require | OW23: require | OX23: require | OY23: require
A24: 30533_disabled | DT24: disabled | DU24: disabled | DV24: disabled | EA24: disabled | EG24: disabled | EN24: disabled | EO24: disabled | EP24: disabled | EQ24: disabled | ER24: disabled | ES24: disabled | FC24: disabled | FF24: disabled | FG24: disabled | FK24: disabled | FL24: disabled | FQ24: disabled | FR24: disabled | FS24: disabled | FT24: disabled | FU24: disabled | FV24: disabled | FW24: disabled | FX24: disabled | FY24: disabled | FZ24: disabled | GA24: disabled | GB24: disabled | GC24: disabled | GD24: disabled | GE24: disabled | GF24: disabled | GG24: disabled | GH24: disabled | GI24: disabled | GJ24: disabled | GK24: disabled | GL24: disabled | GM24: disabled | GN24: disabled | GO24: disabled | GP24: disabled | GQ24: disabled | GR24: disabled | GS24: disabled | GT24: disabled | GU24: disabled | GV24: disabled | GW24: disabled | GX24: disabled | GY24: disabled | GZ24: disabled | HA24: disabled | HB24: disabled | HC24: disabled | HD24: disabled | HE24: disabled | HF24: disabled | HG24: disabled | HH24: disabled | HI24: disabled | HJ24: disabled | HK24: disabled | HL24: disabled | HM24: disabled | HN24: disabled | HO24: disabled | HP24: disabled | HQ24: disabled | HR24: disabled | HS24: disabled | HT24: disabled | HU24: disabled | HV24: disabled | HW24: disabled | HX24: disabled | HY24: disabled | HZ24: disabled | IA24: disabled | IB24: disabled | IC24: disabled | ID24: disabled | IE24: disabled | IF24: disabled | IG24: disabled | IH24: disabled | II24: disabled | IJ24: disabled | IK24: disabled | IL24: disabled | IM24: disabled | IN24: disabled | IO24: disabled | IP24: disabled | IQ24: disabled | IR24: disabled | IS24: disabled | IT24: disabled | IU24: disabled | IV24: disabled | IW24: disabled | IX24: disabled | IY24: disabled | IZ24: disabled | JA24: disabled | JB24: disabled | JC24: disabled | JD24: disabled | JE24: disabled | JF24: disabled | JG24: disabled | JH24: disabled | JI24: disabled | JJ24: disabled | JK24: disabled | JL24: disabled | JM24: disabled | JN24: disabled | JO24: disabled | JP24: disabled | JQ24: disabled | JR24: disabled | JS24: disabled | JT24: disabled | JU24: disabled | JV24: disabled | JW24: disabled | JX24: disabled | JZ24: disabled | KA24: disabled | KB24: disabled | KC24: disabled | KD24: disabled | KE24: disabled | KO24: disabled | KP24: disabled | KQ24: disabled | KR24: disabled | KX24: disabled | KY24: disabled | KZ24: disabled | LA24: disabled | LB24: disabled | LC24: disabled | LD24: disabled | LE24: disabled | LF24: disabled | LG24: disabled | LH24: disabled | LI24: disabled | LJ24: disabled | LK24: disabled | LL24: disabled | LM24: disabled | LN24: disabled
A25: 30533_condition_require | MX25: condition_require
A26: 30542_require | E26: require | L26: require | M26: require | N26: require | DS26: require | DW26: require | DX26: require | DY26: require | DZ26: require | FD26: require | FE26: require | KF26: require | KG26: require | KH26: require | KI26: require | KJ26: require | KM26: require | KS26: require | LO26: require | LY26: require | LZ26: require | MB26: require | MD26: require | ME26: require | MF26: require | MG26: require | MI26: require | MJ26: require | MK26: require | MS26: require | MW26: require | OW26: require | OX26: require | OY26: require
A27: 30542_disabled | DT27: disabled | DU27: disabled | DV27: disabled | EA27: disabled | EG27: disabled | EN27: disabled | EO27: disabled | EP27: disabled | EQ27: disabled | ER27: disabled | ES27: disabled | FC27: disabled | FF27: disabled | FG27: disabled | FK27: disabled | FL27: disabled | FQ27: disabled | FR27: disabled | FS27: disabled | FT27: disabled | FU27: disabled | FV27: disabled | FW27: disabled | FX27: disabled | FY27: disabled | FZ27: disabled | GA27: disabled | GB27: disabled | GC27: disabled | GD27: disabled | GE27: disabled | GF27: disabled | GG27: disabled | GH27: disabled | GI27: disabled | GJ27: disabled | GK27: disabled | GL27: disabled | GM27: disabled | GN27: disabled | GO27: disabled | GP27: disabled | GQ27: disabled | GR27: disabled | GS27: disabled | GT27: disabled | GU27: disabled | GV27: disabled | GW27: disabled | GX27: disabled | GY27: disabled | GZ27: disabled | HA27: disabled | HB27: disabled | HC27: disabled | HD27: disabled | HE27: disabled | HF27: disabled | HG27: disabled | HH27: disabled | HI27: disabled | HJ27: disabled | HK27: disabled | HL27: disabled | HM27: disabled | HN27: disabled | HO27: disabled | HP27: disabled | HQ27: disabled | HR27: disabled | HS27: disabled | HT27: disabled | HU27: disabled | HV27: disabled | HW27: disabled | HX27: disabled | HY27: disabled | HZ27: disabled | IA27: disabled | IB27: disabled | IC27: disabled | ID27: disabled | IE27: disabled | IF27: disabled | IG27: disabled | IH27: disabled | II27: disabled | IJ27: disabled | IK27: disabled | IL27: disabled | IM27: disabled | IN27: disabled | IO27: disabled | IP27: disabled | IQ27: disabled | IR27: disabled | IS27: disabled | IT27: disabled | IU27: disabled | IV27: disabled | IW27: disabled | IX27: disabled | IY27: disabled | IZ27: disabled | JA27: disabled | JB27: disabled | JC27: disabled | JD27: disabled | JE27: disabled | JF27: disabled | JG27: disabled | JH27: disabled | JI27: disabled | JJ27: disabled | JK27: disabled | JL27: disabled | JM27: disabled | JN27: disabled | JO27: disabled | JP27: disabled | JQ27: disabled | JR27: disabled | JS27: disabled | JT27: disabled | JU27: disabled | JV27: disabled | JW27: disabled | JX27: disabled | JZ27: disabled | KA27: disabled | KB27: disabled | KC27: disabled | KD27: disabled | KE27: disabled | KO27: disabled | KP27: disabled | KQ27: disabled | KR27: disabled | KX27: disabled | KY27: disabled | KZ27: disabled | LA27: disabled | LB27: disabled | LC27: disabled | LD27: disabled | LE27: disabled | LF27: disabled | LG27: disabled | LH27: disabled | LI27: disabled | LJ27: disabled | LK27: disabled | LL27: disabled | LM27: disabled | LN27: disabled
A28: 30542_condition_require | MX28: condition_require
A29: 30858_require | E29: require | L29: require | M29: require | N29: require | DS29: require | DW29: require | DX29: require | DY29: require | DZ29: require | EG29: require | FD29: require | FE29: require | KF29: require | KG29: require | KH29: require | KI29: require | KJ29: require | KM29: require | LA29: require | LO29: require | LY29: require | LZ29: require | MB29: require | MD29: require | ME29: require | MF29: require | MG29: require | MI29: require | MJ29: require | MK29: require | MS29: require | MW29: require | OW29: require | OX29: require | OY29: require
A30: 30858_disabled | DT30: disabled | FP30: disabled | FQ30: disabled | FR30: disabled | FS30: disabled | FT30: disabled | FU30: disabled | FV30: disabled | FW30: disabled | FX30: disabled | FY30: disabled | FZ30: disabled | GA30: disabled | GB30: disabled | GC30: disabled | GD30: disabled | GE30: disabled | GF30: disabled | GG30: disabled | GH30: disabled | GI30: disabled | GJ30: disabled | GK30: disabled | GL30: disabled | GM30: disabled | GN30: disabled | GO30: disabled | GP30: disabled | GQ30: disabled | GR30: disabled | GS30: disabled | GT30: disabled | GU30: disabled | GV30: disabled | GW30: disabled | GX30: disabled | GY30: disabled | GZ30: disabled | HA30: disabled | HB30: disabled | HC30: disabled | HD30: disabled | HE30: disabled | HF30: disabled | HG30: disabled | HH30: disabled | HI30: disabled | HJ30: disabled | HK30: disabled | HL30: disabled | HM30: disabled | HN30: disabled | HO30: disabled | HP30: disabled | HQ30: disabled | HR30: disabled | HS30: disabled | HT30: disabled | HU30: disabled | HV30: disabled | HW30: disabled | HX30: disabled | HY30: disabled | HZ30: disabled | IA30: disabled | IB30: disabled | IC30: disabled | ID30: disabled | IE30: disabled | IF30: disabled | IG30: disabled | IH30: disabled | II30: disabled | IJ30: disabled | IK30: disabled | IL30: disabled | IM30: disabled | IN30: disabled | IO30: disabled | IP30: disabled | IQ30: disabled | IR30: disabled | IS30: disabled | IT30: disabled | IU30: disabled | IV30: disabled | IW30: disabled | IX30: disabled | IY30: disabled | IZ30: disabled | JA30: disabled | JB30: disabled | JC30: disabled | JD30: disabled | JE30: disabled | JF30: disabled | JG30: disabled | JH30: disabled | JI30: disabled | JJ30: disabled | JK30: disabled | JL30: disabled | JM30: disabled | JN30: disabled | JO30: disabled | JP30: disabled | JQ30: disabled | JR30: disabled | JS30: disabled | JT30: disabled | JU30: disabled | JV30: disabled | JW30: disabled | JX30: disabled | JY30: disabled | JZ30: disabled | KA30: disabled | KB30: disabled | KC30: disabled | KD30: disabled | KE30: disabled | KO30: disabled | KP30: disabled | KQ30: disabled | KR30: disabled | KS30: disabled | KT30: disabled | KU30: disabled | KV30: disabled | KW30: disabled | KX30: disabled | KY30: disabled | KZ30: disabled | LE30: disabled | LF30: disabled | LG30: disabled | LH30: disabled | LI30: disabled | LJ30: disabled | LK30: disabled | LL30: disabled | LM30: disabled | LN30: disabled
A31: 30858_condition_require | MX31: condition_require
A32: 30859_require | E32: require | L32: require | M32: require | N32: require | DS32: require | DW32: require | DX32: require | DY32: require | DZ32: require | EG32: require | FD32: require | FE32: require | KF32: require | KG32: require | KH32: require | KI32: require | KJ32: require | KM32: require | LA32: require | LO32: require | LY32: require | LZ32: require | MB32: require | MD32: require | ME32: require | MF32: require | MG32: require | MI32: require | MJ32: require | MK32: require | MS32: require | MW32: require | OW32: require | OX32: require | OY32: require
A33: 30859_disabled | DT33: disabled | FP33: disabled | FQ33: disabled | FR33: disabled | FS33: disabled | FT33: disabled | FU33: disabled | FV33: disabled | FW33: disabled | FX33: disabled | FY33: disabled | FZ33: disabled | GA33: disabled | GB33: disabled | GC33: disabled | GD33: disabled | GE33: disabled | GF33: disabled | GG33: disabled | GH33: disabled | GI33: disabled | GJ33: disabled | GK33: disabled | GL33: disabled | GM33: disabled | GN33: disabled | GO33: disabled | GP33: disabled | GQ33: disabled | GR33: disabled | GS33: disabled | GT33: disabled | GU33: disabled | GV33: disabled | GW33: disabled | GX33: disabled | GY33: disabled | GZ33: disabled | HA33: disabled | HB33: disabled | HC33: disabled | HD33: disabled | HE33: disabled | HF33: disabled | HG33: disabled | HH33: disabled | HI33: disabled | HJ33: disabled | HK33: disabled | HL33: disabled | HM33: disabled | HN33: disabled | HO33: disabled | HP33: disabled | HQ33: disabled | HR33: disabled | HS33: disabled | HT33: disabled | HU33: disabled | HV33: disabled | HW33: disabled | HX33: disabled | HY33: disabled | HZ33: disabled | IA33: disabled | IB33: disabled | IC33: disabled | ID33: disabled | IE33: disabled | IF33: disabled | IG33: disabled | IH33: disabled | II33: disabled | IJ33: disabled | IK33: disabled | IL33: disabled | IM33: disabled | IN33: disabled | IO33: disabled | IP33: disabled | IQ33: disabled | IR33: disabled | IS33: disabled | IT33: disabled | IU33: disabled | IV33: disabled | IW33: disabled | IX33: disabled | IY33: disabled | IZ33: disabled | JA33: disabled | JB33: disabled | JC33: disabled | JD33: disabled | JE33: disabled | JF33: disabled | JG33: disabled | JH33: disabled | JI33: disabled | JJ33: disabled | JK33: disabled | JL33: disabled | JM33: disabled | JN33: disabled | JO33: disabled | JP33: disabled | JQ33: disabled | JR33: disabled | JS33: disabled | JT33: disabled | JU33: disabled | JV33: disabled | JW33: disabled | JX33: disabled | JY33: disabled | JZ33: disabled | KA33: disabled | KB33: disabled | KC33: disabled | KD33: disabled | KE33: disabled | KO33: disabled | KP33: disabled | KQ33: disabled | KR33: disabled | KS33: disabled | KT33: disabled | KU33: disabled | KV33: disabled | KW33: disabled | KX33: disabled | KY33: disabled | KZ33: disabled | LE33: disabled | LF33: disabled | LG33: disabled | LH33: disabled | LI33: disabled | LJ33: disabled | LK33: disabled | LL33: disabled | LM33: disabled | LN33: disabled
A34: 30859_condition_require | MX34: condition_require
A35: 30862_require | E35: require | L35: require | M35: require | N35: require | DS35: require | DW35: require | DX35: require | DY35: require | DZ35: require | EG35: require | ET35: require | EU35: require | EV35: require | FD35: require | FE35: require | KF35: require | KG35: require | KH35: require | KI35: require | KJ35: require | KM35: require | LA35: require | LO35: require | LY35: require | LZ35: require | MB35: require | MD35: require | ME35: require | MF35: require | MG35: require | MI35: require | MJ35: require | MK35: require | MS35: require | MW35: require | OW35: require | OX35: require | OY35: require
A36: 30862_disabled | DT36: disabled | FP36: disabled | FQ36: disabled | FR36: disabled | FS36: disabled | FT36: disabled | FU36: disabled | FV36: disabled | FW36: disabled | FX36: disabled | FY36: disabled | FZ36: disabled | GA36: disabled | GB36: disabled | GC36: disabled | GD36: disabled | GE36: disabled | GF36: disabled | GG36: disabled | GH36: disabled | GI36: disabled | GJ36: disabled | GK36: disabled | GL36: disabled | GM36: disabled | GN36: disabled | GO36: disabled | GP36: disabled | GQ36: disabled | GR36: disabled | GS36: disabled | GT36: disabled | GU36: disabled | GV36: disabled | GW36: disabled | GX36: disabled | GY36: disabled | GZ36: disabled | HA36: disabled | HB36: disabled | HC36: disabled | HD36: disabled | HE36: disabled | HF36: disabled | HG36: disabled | HH36: disabled | HI36: disabled | HJ36: disabled | HK36: disabled | HL36: disabled | HM36: disabled | HN36: disabled | HO36: disabled | HP36: disabled | HQ36: disabled | HR36: disabled | HS36: disabled | HT36: disabled | HU36: disabled | HV36: disabled | HW36: disabled | HX36: disabled | HY36: disabled | HZ36: disabled | IA36: disabled | IB36: disabled | IC36: disabled | ID36: disabled | IE36: disabled | IF36: disabled | IG36: disabled | IH36: disabled | II36: disabled | IJ36: disabled | IK36: disabled | IL36: disabled | IM36: disabled | IN36: disabled | IO36: disabled | IP36: disabled | IQ36: disabled | IR36: disabled | IS36: disabled | IT36: disabled | IU36: disabled | IV36: disabled | IW36: disabled | IX36: disabled | IY36: disabled | IZ36: disabled | JA36: disabled | JB36: disabled | JC36: disabled | JD36: disabled | JE36: disabled | JF36: disabled | JG36: disabled | JH36: disabled | JI36: disabled | JJ36: disabled | JK36: disabled | JL36: disabled | JM36: disabled | JN36: disabled | JO36: disabled | JP36: disabled | JQ36: disabled | JR36: disabled | JS36: disabled | JT36: disabled | JU36: disabled | JV36: disabled | JW36: disabled | JX36: disabled | JY36: disabled | JZ36: disabled | KA36: disabled | KB36: disabled | KC36: disabled | KD36: disabled | KE36: disabled | KO36: disabled | KP36: disabled | KQ36: disabled | KR36: disabled | KS36: disabled | KT36: disabled | KU36: disabled | KV36: disabled | KW36: disabled | KX36: disabled | KY36: disabled | KZ36: disabled | LE36: disabled | LF36: disabled | LG36: disabled | LH36: disabled | LI36: disabled | LJ36: disabled | LK36: disabled | LL36: disabled | LM36: disabled | LN36: disabled
A37: 30862_condition_require | MX37: condition_require
A38: 39012_require | E38: require | L38: require | M38: require | N38: require | FQ38: require | FR38: require | FS38: require | FT38: require | FU38: require | FV38: require | FW38: require | FX38: require | FY38: require | FZ38: require | GA38: require | GB38: require | GC38: require | GD38: require | GE38: require | GF38: require | GG38: require | GH38: require | GI38: require | GJ38: require | GK38: require | GL38: require | GM38: require | GN38: require | GO38: require | GP38: require | GQ38: require | GR38: require | GS38: require | GT38: require | KF38: require | KG38: require | KH38: require | KI38: require | KJ38: require | KM38: require | KX38: require | KY38: require | LO38: require | LY38: require | LZ38: require | MB38: require | MD38: require | ME38: require | MF38: require | MG38: require | MI38: require | MJ38: require | MK38: require | MS38: require | MW38: require | OW38: require | OX38: require | OY38: require
A39: 39012_disabled | DT39: disabled | DU39: disabled | DV39: disabled | DY39: disabled | DZ39: disabled | EA39: disabled | EB39: disabled | EC39: disabled | ED39: disabled | EE39: disabled | EF39: disabled | EG39: disabled | EH39: disabled | EI39: disabled | EJ39: disabled | EN39: disabled | EO39: disabled | EP39: disabled | EQ39: disabled | ER39: disabled | ES39: disabled | ET39: disabled | EU39: disabled | EV39: disabled | EW39: disabled | EX39: disabled | EY39: disabled | FC39: disabled | FD39: disabled | FE39: disabled | FF39: disabled | FG39: disabled | FI39: disabled | FJ39: disabled | FK39: disabled | FL39: disabled | FM39: disabled | FN39: disabled | FO39: disabled | FP39: disabled | JY39: disabled | JZ39: disabled | KA39: disabled | KB39: disabled | KC39: disabled | KD39: disabled | KE39: disabled | KN39: disabled | KO39: disabled | KP39: disabled | KQ39: disabled | KR39: disabled | KS39: disabled | KT39: disabled | KU39: disabled | KV39: disabled | KW39: disabled | LA39: disabled | LB39: disabled | LC39: disabled | LD39: disabled | LE39: disabled | LF39: disabled | LG39: disabled | LH39: disabled | LI39: disabled | LJ39: disabled | LK39: disabled | LL39: disabled | LM39: disabled | LN39: disabled
A40: 39012_condition_require | IJ40: condition_require | IK40: condition_require | MX40: condition_require
A41: 54718_require | E41: require | L41: require | M41: require | N41: require | DS41: require | DT41: require | DW41: require | DX41: require | DY41: require | DZ41: require | ET41: require | EU41: require | EV41: require | FD41: require | FE41: require | KF41: require | KG41: require | KH41: require | KI41: require | KJ41: require | KM41: require | KS41: require | LO41: require | LY41: require | LZ41: require | MB41: require | MD41: require | ME41: require | MF41: require | MG41: require | MI41: require | MJ41: require | MK41: require | MS41: require | MW41: require | OW41: require | OX41: require | OY41: require
A42: 54718_disabled | DU42: disabled | DV42: disabled | EA42: disabled | EG42: disabled | EN42: disabled | EO42: disabled | EP42: disabled | EQ42: disabled | ER42: disabled | ES42: disabled | FC42: disabled | FF42: disabled | FG42: disabled | FK42: disabled | FL42: disabled | FQ42: disabled | FR42: disabled | FS42: disabled | FT42: disabled | FU42: disabled | FV42: disabled | FW42: disabled | FX42: disabled | FY42: disabled | FZ42: disabled | GA42: disabled | GB42: disabled | GC42: disabled | GD42: disabled | GE42: disabled | GF42: disabled | GG42: disabled | GH42: disabled | GI42: disabled | GJ42: disabled | GK42: disabled | GL42: disabled | GM42: disabled | GN42: disabled | GO42: disabled | GP42: disabled | GQ42: disabled | GR42: disabled | GS42: disabled | GT42: disabled | GU42: disabled | GV42: disabled | GW42: disabled | GX42: disabled | GY42: disabled | GZ42: disabled | HA42: disabled | HB42: disabled | HC42: disabled | HD42: disabled | HE42: disabled | HF42: disabled | HG42: disabled | HH42: disabled | HI42: disabled | HJ42: disabled | HK42: disabled | HL42: disabled | HM42: disabled | HN42: disabled | HO42: disabled | HP42: disabled | HQ42: disabled | HR42: disabled | HS42: disabled | HT42: disabled | HU42: disabled | HV42: disabled | HW42: disabled | HX42: disabled | HY42: disabled | HZ42: disabled | IA42: disabled | IB42: disabled | IC42: disabled | ID42: disabled | IE42: disabled | IF42: disabled | IG42: disabled | IH42: disabled | II42: disabled | IJ42: disabled | IK42: disabled | IL42: disabled | IM42: disabled | IN42: disabled | IO42: disabled | IP42: disabled | IQ42: disabled | IR42: disabled | IS42: disabled | IT42: disabled | IU42: disabled | IV42: disabled | IW42: disabled | IX42: disabled | IY42: disabled | IZ42: disabled | JA42: disabled | JB42: disabled | JC42: disabled | JD42: disabled | JE42: disabled | JF42: disabled | JG42: disabled | JH42: disabled | JI42: disabled | JJ42: disabled | JK42: disabled | JL42: disabled | JM42: disabled | JN42: disabled | JO42: disabled | JP42: disabled | JQ42: disabled | JR42: disabled | JS42: disabled | JT42: disabled | JU42: disabled | JV42: disabled | JW42: disabled | JX42: disabled | JY42: disabled | JZ42: disabled | KA42: disabled | KB42: disabled | KC42: disabled | KD42: disabled | KE42: disabled | KO42: disabled | KP42: disabled | KQ42: disabled | KR42: disabled | KX42: disabled | KY42: disabled | KZ42: disabled | LA42: disabled | LB42: disabled | LC42: disabled | LD42: disabled | LE42: disabled | LF42: disabled | LG42: disabled | LH42: disabled | LI42: disabled | LJ42: disabled | LK42: disabled | LL42: disabled | LM42: disabled | LN42: disabled
A43: 54718_condition_require | MX43: condition_require
A44: 54722_require | E44: require | L44: require | M44: require | N44: require | DS44: require | DW44: require | DX44: require | DY44: require | DZ44: require | FD44: require | FE44: require | KF44: require | KG44: require | KH44: require | KI44: require | KJ44: require | KM44: require | KS44: require | LO44: require | LY44: require | LZ44: require | MB44: require | MD44: require | ME44: require | MF44: require | MG44: require | MI44: require | MJ44: require | MK44: require | MS44: require | MW44: require | OW44: require | OX44: require | OY44: require
A45: 54722_disabled | DT45: disabled | DU45: disabled | DV45: disabled | EA45: disabled | EG45: disabled | EN45: disabled | EO45: disabled | EP45: disabled | EQ45: disabled | ER45: disabled | ES45: disabled | FC45: disabled | FF45: disabled | FG45: disabled | FK45: disabled | FL45: disabled | FQ45: disabled | FR45: disabled | FS45: disabled | FT45: disabled | FU45: disabled | FV45: disabled | FW45: disabled | FX45: disabled | FY45: disabled | FZ45: disabled | GA45: disabled | GB45: disabled | GC45: disabled | GD45: disabled | GE45: disabled | GF45: disabled | GG45: disabled | GH45: disabled | GI45: disabled | GJ45: disabled | GK45: disabled | GL45: disabled | GM45: disabled | GN45: disabled | GO45: disabled | GP45: disabled | GQ45: disabled | GR45: disabled | GS45: disabled | GT45: disabled | GU45: disabled | GV45: disabled | GW45: disabled | GX45: disabled | GY45: disabled | GZ45: disabled | HA45: disabled | HB45: disabled | HC45: disabled | HD45: disabled | HE45: disabled | HF45: disabled | HG45: disabled | HH45: disabled | HI45: disabled | HJ45: disabled | HK45: disabled | HL45: disabled | HM45: disabled | HN45: disabled | HO45: disabled | HP45: disabled | HQ45: disabled | HR45: disabled | HS45: disabled | HT45: disabled | HU45: disabled | HV45: disabled | HW45: disabled | HX45: disabled | HY45: disabled | HZ45: disabled | IA45: disabled | IB45: disabled | IC45: disabled | ID45: disabled | IE45: disabled | IF45: disabled | IG45: disabled | IH45: disabled | II45: disabled | IJ45: disabled | IK45: disabled | IL45: disabled | IM45: disabled | IN45: disabled | IO45: disabled | IP45: disabled | IQ45: disabled | IR45: disabled | IS45: disabled | IT45: disabled | IU45: disabled | IV45: disabled | IW45: disabled | IX45: disabled | IY45: disabled | IZ45: disabled | JA45: disabled | JB45: disabled | JC45: disabled | JD45: disabled | JE45: disabled | JF45: disabled | JG45: disabled | JH45: disabled | JI45: disabled | JJ45: disabled | JK45: disabled | JL45: disabled | JM45: disabled | JN45: disabled | JO45: disabled | JP45: disabled | JQ45: disabled | JR45: disabled | JS45: disabled | JT45: disabled | JU45: disabled | JV45: disabled | JW45: disabled | JX45: disabled | JY45: disabled | JZ45: disabled | KA45: disabled | KB45: disabled | KC45: disabled | KD45: disabled | KE45: disabled | KO45: disabled | KP45: disabled | KQ45: disabled | KR45: disabled | KX45: disabled | KY45: disabled | KZ45: disabled | LA45: disabled | LB45: disabled | LC45: disabled | LD45: disabled | LE45: disabled | LF45: disabled | LG45: disabled | LH45: disabled | LI45: disabled | LJ45: disabled | LK45: disabled | LL45: disabled | LM45: disabled | LN45: disabled
A46: 54722_condition_require | MX46: condition_require
A47: 54726_require | E47: require | L47: require | M47: require | N47: require | DS47: require | DW47: require | DX47: require | DY47: require | DZ47: require | FD47: require | FE47: require | KA47: require | KF47: require | KG47: require | KH47: require | KI47: require | KJ47: require | KM47: require | LE47: require | LM47: require | LO47: require | LY47: require | LZ47: require | MB47: require | MD47: require | ME47: require | MF47: require | MG47: require | MI47: require | MJ47: require | MK47: require | MS47: require | MW47: require | OW47: require | OX47: require | OY47: require
A48: 54726_disabled | DT48: disabled | DU48: disabled | DV48: disabled | EA48: disabled | EB48: disabled | EC48: disabled | ED48: disabled | EE48: disabled | EF48: disabled | EG48: disabled | EH48: disabled | EI48: disabled | EJ48: disabled | EN48: disabled | EO48: disabled | EP48: disabled | EQ48: disabled | ER48: disabled | ES48: disabled | ET48: disabled | EU48: disabled | EV48: disabled | EW48: disabled | EX48: disabled | EY48: disabled | FC48: disabled | FF48: disabled | FG48: disabled | FJ48: disabled | FK48: disabled | FL48: disabled | FQ48: disabled | FR48: disabled | FS48: disabled | FT48: disabled | FU48: disabled | FV48: disabled | FW48: disabled | FX48: disabled | FY48: disabled | FZ48: disabled | GA48: disabled | GB48: disabled | GC48: disabled | GD48: disabled | GE48: disabled | GF48: disabled | GG48: disabled | GH48: disabled | GI48: disabled | GJ48: disabled | GK48: disabled | GL48: disabled | GM48: disabled | GN48: disabled | GO48: disabled | GP48: disabled | GQ48: disabled | GR48: disabled | GS48: disabled | GT48: disabled | GU48: disabled | GV48: disabled | GW48: disabled | GX48: disabled | GY48: disabled | GZ48: disabled | HA48: disabled | HB48: disabled | HC48: disabled | HD48: disabled | HE48: disabled | HF48: disabled | HG48: disabled | HH48: disabled | HI48: disabled | HJ48: disabled | HK48: disabled | HL48: disabled | HM48: disabled | HN48: disabled | HO48: disabled | HP48: disabled | HQ48: disabled | HR48: disabled | HS48: disabled | HT48: disabled | HU48: disabled | HV48: disabled | HW48: disabled | HX48: disabled | HY48: disabled | HZ48: disabled | IA48: disabled | IB48: disabled | IC48: disabled | ID48: disabled | IE48: disabled | IF48: disabled | IH48: disabled | II48: disabled | IJ48: disabled | IK48: disabled | IL48: disabled | IM48: disabled | IN48: disabled | IO48: disabled | IP48: disabled | IQ48: disabled | IR48: disabled | IS48: disabled | IT48: disabled | IU48: disabled | IV48: disabled | IW48: disabled | IX48: disabled | IY48: disabled | IZ48: disabled | JA48: disabled | JB48: disabled | JC48: disabled | JD48: disabled | JE48: disabled | JF48: disabled | JG48: disabled | JH48: disabled | JI48: disabled | JJ48: disabled | JK48: disabled | JL48: disabled | JM48: disabled | JN48: disabled | JO48: disabled | JP48: disabled | JQ48: disabled | JR48: disabled | JS48: disabled | JT48: disabled | JU48: disabled | JV48: disabled | JW48: disabled | JX48: disabled | JY48: disabled | KC48: disabled | KD48: disabled | KE48: disabled | KO48: disabled | KP48: disabled | KQ48: disabled | KR48: disabled | KS48: disabled | KT48: disabled | KU48: disabled | KV48: disabled | KW48: disabled | KX48: disabled | KY48: disabled | KZ48: disabled | LA48: disabled | LB48: disabled | LC48: disabled | LD48: disabled
A49: 54726_condition_require | MX49: condition_require
A50: 54835_require | E50: require | L50: require | M50: require | N50: require | DS50: require | DW50: require | DX50: require | DY50: require | DZ50: require | FD50: require | FE50: require | KF50: require | KG50: require | KH50: require | KI50: require | KJ50: require | KM50: require | LE50: require | LM50: require | LO50: require | LY50: require | LZ50: require | MB50: require | MD50: require | ME50: require | MF50: require | MG50: require | MI50: require | MJ50: require | MK50: require | MS50: require | MW50: require | OW50: require | OX50: require
